{
"meta":{"test_sets":[],"test_metrics":[],"learn_metrics":[{"best_value":"Min","name":"RMSE"}],"launch_mode":"Train","parameters":"","iteration_count":1000,"learn_sets":["learn"],"name":"experiment"},
"iterations":[
{"learn":[9.174960635],"iteration":0,"passed_time":0.001542498592,"remaining_time":1.540956093},
{"learn":[9.158544086],"iteration":1,"passed_time":0.002926000276,"remaining_time":1.460074138},
{"learn":[9.145748713],"iteration":2,"passed_time":0.004283706176,"remaining_time":1.423618353},
{"learn":[9.13238346],"iteration":3,"passed_time":0.005698374728,"remaining_time":1.418895307},
{"learn":[9.118979189],"iteration":4,"passed_time":0.007025730243,"remaining_time":1.398120318},
{"learn":[9.105112823],"iteration":5,"passed_time":0.00853192549,"remaining_time":1.413455656},
{"learn":[9.093421214],"iteration":6,"passed_time":0.00990887747,"remaining_time":1.405645047},
{"learn":[9.087185525],"iteration":7,"passed_time":0.01121678018,"remaining_time":1.390880743},
{"learn":[9.073592539],"iteration":8,"passed_time":0.01254511429,"remaining_time":1.381356473},
{"learn":[9.064968233],"iteration":9,"passed_time":0.01381446907,"remaining_time":1.367632438},
{"learn":[9.057664197],"iteration":10,"passed_time":0.01512845599,"remaining_time":1.360185725},
{"learn":[9.045593204],"iteration":11,"passed_time":0.01643194539,"remaining_time":1.352896837},
{"learn":[9.032397138],"iteration":12,"passed_time":0.01782197149,"remaining_time":1.353098913},
{"learn":[9.016135386],"iteration":13,"passed_time":0.01926008417,"remaining_time":1.356460214},
{"learn":[9.00588181],"iteration":14,"passed_time":0.0206699795,"remaining_time":1.357328654},
{"learn":[8.99504777],"iteration":15,"passed_time":0.02229516328,"remaining_time":1.371152541},
{"learn":[8.982710518],"iteration":16,"passed_time":0.02380869534,"remaining_time":1.376702795},
{"learn":[8.972528472],"iteration":17,"passed_time":0.0253096236,"remaining_time":1.380780577},
{"learn":[8.957282339],"iteration":18,"passed_time":0.02669859007,"remaining_time":1.378490361},
{"learn":[8.947224423],"iteration":19,"passed_time":0.02803849844,"remaining_time":1.373886424},
{"learn":[8.940954381],"iteration":20,"passed_time":0.02937157231,"remaining_time":1.369274728},
{"learn":[8.934292064],"iteration":21,"passed_time":0.03084144227,"remaining_time":1.371042297},
{"learn":[8.925997015],"iteration":22,"passed_time":0.03232358066,"remaining_time":1.373049492},
{"learn":[8.917012025],"iteration":23,"passed_time":0.03361419522,"remaining_time":1.366977272},
{"learn":[8.910076728],"iteration":24,"passed_time":0.03508802044,"remaining_time":1.368432797},
{"learn":[8.901155102],"iteration":25,"passed_time":0.03668645699,"remaining_time":1.37433112},
{"learn":[8.897148527],"iteration":26,"passed_time":0.038184129,"remaining_time":1.376042871},
{"learn":[8.888038215],"iteration":27,"passed_time":0.03967748324,"remaining_time":1.37737549},
{"learn":[8.880719755],"iteration":28,"passed_time":0.04102953846,"remaining_time":1.373782132},
{"learn":[8.872248478],"iteration":29,"passed_time":0.04238876392,"remaining_time":1.370570033},
{"learn":[8.862504365],"iteration":30,"passed_time":0.0437674433,"remaining_time":1.368085567},
{"learn":[8.853380011],"iteration":31,"passed_time":0.04542471677,"remaining_time":1.374097682},
{"learn":[8.843422015],"iteration":32,"passed_time":0.04698643467,"remaining_time":1.376844919},
{"learn":[8.836006385],"iteration":33,"passed_time":0.0486534944,"remaining_time":1.382331635},
{"learn":[8.828027288],"iteration":34,"passed_time":0.05049255303,"remaining_time":1.392151819},
{"learn":[8.82072397],"iteration":35,"passed_time":0.05211135293,"remaining_time":1.395426229},
{"learn":[8.808684308],"iteration":36,"passed_time":0.05373129576,"remaining_time":1.398465887},
{"learn":[8.802708182],"iteration":37,"passed_time":0.05526211486,"remaining_time":1.399004066},
{"learn":[8.798420413],"iteration":38,"passed_time":0.05676431582,"remaining_time":1.398730962},
{"learn":[8.789145404],"iteration":39,"passed_time":0.05815845742,"remaining_time":1.395802978},
{"learn":[8.784152014],"iteration":40,"passed_time":0.0595635193,"remaining_time":1.393205244},
{"learn":[8.781737582],"iteration":41,"passed_time":0.06096458687,"remaining_time":1.390573196},
{"learn":[8.775960726],"iteration":42,"passed_time":0.06238751097,"remaining_time":1.388484837},
{"learn":[8.766736419],"iteration":43,"passed_time":0.0638765705,"remaining_time":1.387863668},
{"learn":[8.761341729],"iteration":44,"passed_time":0.06554090267,"remaining_time":1.390923601},
{"learn":[8.754582885],"iteration":45,"passed_time":0.06695150331,"remaining_time":1.38851596},
{"learn":[8.750011911],"iteration":46,"passed_time":0.06851887041,"remaining_time":1.389329436},
{"learn":[8.745893599],"iteration":47,"passed_time":0.06994597433,"remaining_time":1.387261824},
{"learn":[8.73467183],"iteration":48,"passed_time":0.07159452824,"remaining_time":1.389518293},
{"learn":[8.729647862],"iteration":49,"passed_time":0.07315929307,"remaining_time":1.390026568},
{"learn":[8.722688186],"iteration":50,"passed_time":0.07469365547,"remaining_time":1.389887824},
{"learn":[8.716066804],"iteration":51,"passed_time":0.07614615586,"remaining_time":1.388202995},
{"learn":[8.708359803],"iteration":52,"passed_time":0.07770456433,"remaining_time":1.388419291},
{"learn":[8.701227697],"iteration":53,"passed_time":0.07930194384,"remaining_time":1.389252572},
{"learn":[8.694390673],"iteration":54,"passed_time":0.08087202585,"remaining_time":1.389528444},
{"learn":[8.689142584],"iteration":55,"passed_time":0.08254283187,"remaining_time":1.391436309},
{"learn":[8.684934507],"iteration":56,"passed_time":0.08420994551,"remaining_time":1.39315752},
{"learn":[8.67657095],"iteration":57,"passed_time":0.08591604878,"remaining_time":1.395395137},
{"learn":[8.674323643],"iteration":58,"passed_time":0.08775708058,"remaining_time":1.399651065},
{"learn":[8.666861373],"iteration":59,"passed_time":0.0892611071,"remaining_time":1.398424011},
{"learn":[8.663041831],"iteration":60,"passed_time":0.09087339038,"remaining_time":1.398854321},
{"learn":[8.657907178],"iteration":61,"passed_time":0.092351765,"remaining_time":1.397192832},
{"learn":[8.649056909],"iteration":62,"passed_time":0.09396064776,"remaining_time":1.397478206},
{"learn":[8.642003898],"iteration":63,"passed_time":0.09562862585,"remaining_time":1.398568653},
{"learn":[8.635728231],"iteration":64,"passed_time":0.09716283358,"remaining_time":1.397649991},
{"learn":[8.628715058],"iteration":65,"passed_time":0.09884465393,"remaining_time":1.398801618},
{"learn":[8.617718946],"iteration":66,"passed_time":0.1004706821,"remaining_time":1.399091737},
{"learn":[8.60954165],"iteration":67,"passed_time":0.1021571604,"remaining_time":1.400154022},
{"learn":[8.604813403],"iteration":68,"passed_time":0.103662083,"remaining_time":1.398686946},
{"learn":[8.597131079],"iteration":69,"passed_time":0.1052570409,"remaining_time":1.398414972},
{"learn":[8.593312987],"iteration":70,"passed_time":0.1067880838,"remaining_time":1.397269435},
{"learn":[8.587575386],"iteration":71,"passed_time":0.108279888,"remaining_time":1.395607446},
{"learn":[8.583161969],"iteration":72,"passed_time":0.1099168402,"remaining_time":1.395793299},
{"learn":[8.579046766],"iteration":73,"passed_time":0.1114689361,"remaining_time":1.394868039},
{"learn":[8.574010568],"iteration":74,"passed_time":0.1129863922,"remaining_time":1.393498837},
{"learn":[8.569814969],"iteration":75,"passed_time":0.1146597618,"remaining_time":1.394021315},
{"learn":[8.563452914],"iteration":76,"passed_time":0.1162218951,"remaining_time":1.393153365},
{"learn":[8.558686456],"iteration":77,"passed_time":0.1177294024,"remaining_time":1.39162191},
{"learn":[8.556589535],"iteration":78,"passed_time":0.1192802614,"remaining_time":1.390596465},
{"learn":[8.55124425],"iteration":79,"passed_time":0.120885986,"remaining_time":1.390188839},
{"learn":[8.545741333],"iteration":80,"passed_time":0.1223077196,"remaining_time":1.387664127},
{"learn":[8.538604887],"iteration":81,"passed_time":0.1238337595,"remaining_time":1.38633404},
{"learn":[8.532437733],"iteration":82,"passed_time":0.1255234811,"remaining_time":1.386807617},
{"learn":[8.527829732],"iteration":83,"passed_time":0.127136537,"remaining_time":1.386393666},
{"learn":[8.522412112],"iteration":84,"passed_time":0.1287864621,"remaining_time":1.386348387},
{"learn":[8.516394728],"iteration":85,"passed_time":0.1305985055,"remaining_time":1.387988767},
{"learn":[8.511177374],"iteration":86,"passed_time":0.132176037,"remaining_time":1.387088756},
{"learn":[8.509386924],"iteration":87,"passed_time":0.1337375124,"remaining_time":1.386006947},
{"learn":[8.504166584],"iteration":88,"passed_time":0.1353290483,"remaining_time":1.385222056},
{"learn":[8.499732062],"iteration":89,"passed_time":0.136869892,"remaining_time":1.383906686},
{"learn":[8.49646993],"iteration":90,"passed_time":0.1386547241,"remaining_time":1.385023562},
{"learn":[8.490354138],"iteration":91,"passed_time":0.140302064,"remaining_time":1.384720371},
{"learn":[8.486950021],"iteration":92,"passed_time":0.1418367551,"remaining_time":1.383289644},
{"learn":[8.481614282],"iteration":93,"passed_time":0.1433226264,"remaining_time":1.381386165},
{"learn":[8.474817714],"iteration":94,"passed_time":0.1450397455,"remaining_time":1.381694418},
{"learn":[8.464974616],"iteration":95,"passed_time":0.1466243093,"remaining_time":1.380712246},
{"learn":[8.459721737],"iteration":96,"passed_time":0.1482816872,"remaining_time":1.380395501},
{"learn":[8.452269393],"iteration":97,"passed_time":0.1499630098,"remaining_time":1.380271784},
{"learn":[8.446552125],"iteration":98,"passed_time":0.1514152558,"remaining_time":1.378031773},
{"learn":[8.443589301],"iteration":99,"passed_time":0.1530184742,"remaining_time":1.377166267},
{"learn":[8.440385419],"iteration":100,"passed_time":0.1546186065,"remaining_time":1.376258686},
{"learn":[8.436781677],"iteration":101,"passed_time":0.1561298628,"remaining_time":1.374555066},
{"learn":[8.428491387],"iteration":102,"passed_time":0.1576283702,"remaining_time":1.372744156},
{"learn":[8.42348505],"iteration":103,"passed_time":0.1591615518,"remaining_time":1.371237984},
{"learn":[8.420787397],"iteration":104,"passed_time":0.160817042,"remaining_time":1.370773835},
{"learn":[8.413251448],"iteration":105,"passed_time":0.1625679314,"remaining_time":1.371091799},
{"learn":[8.403166664],"iteration":106,"passed_time":0.1641850243,"remaining_time":1.370254455},
{"learn":[8.401476106],"iteration":107,"passed_time":0.1657986372,"remaining_time":1.369373929},
{"learn":[8.398597395],"iteration":108,"passed_time":0.167354771,"remaining_time":1.3680101},
{"learn":[8.392982113],"iteration":109,"passed_time":0.1689345879,"remaining_time":1.366834393},
{"learn":[8.387732166],"iteration":110,"passed_time":0.1704662339,"remaining_time":1.365265603},
{"learn":[8.384830094],"iteration":111,"passed_time":0.1720451072,"remaining_time":1.364071922},
{"learn":[8.378706019],"iteration":112,"passed_time":0.1735708631,"remaining_time":1.362454474},
{"learn":[8.374557976],"iteration":113,"passed_time":0.1750892472,"remaining_time":1.360781342},
{"learn":[8.370614289],"iteration":114,"passed_time":0.1767638367,"remaining_time":1.360313004},
{"learn":[8.368011404],"iteration":115,"passed_time":0.1783421799,"remaining_time":1.359090405},
{"learn":[8.363298388],"iteration":116,"passed_time":0.1801448682,"remaining_time":1.35955486},
{"learn":[8.360684361],"iteration":117,"passed_time":0.1819429072,"remaining_time":1.359946137},
{"learn":[8.35402903],"iteration":118,"passed_time":0.1835925367,"remaining_time":1.359201889},
{"learn":[8.35088171],"iteration":119,"passed_time":0.1851875865,"remaining_time":1.358042301},
{"learn":[8.348336871],"iteration":120,"passed_time":0.1868766931,"remaining_time":1.357558787},
{"learn":[8.344401344],"iteration":121,"passed_time":0.1884779435,"remaining_time":1.356423232},
{"learn":[8.336890396],"iteration":122,"passed_time":0.1899720331,"remaining_time":1.354516041},
{"learn":[8.332910986],"iteration":123,"passed_time":0.1916333254,"remaining_time":1.353796718},
{"learn":[8.326687911],"iteration":124,"passed_time":0.1933106414,"remaining_time":1.35317449},
{"learn":[8.324371345],"iteration":125,"passed_time":0.1948858759,"remaining_time":1.351827425},
{"learn":[8.320934887],"iteration":126,"passed_time":0.1963682578,"remaining_time":1.349838496},
{"learn":[8.316485178],"iteration":127,"passed_time":0.1979234438,"remaining_time":1.348353461},
{"learn":[8.31103192],"iteration":128,"passed_time":0.1995470095,"remaining_time":1.347329033},
{"learn":[8.307330359],"iteration":129,"passed_time":0.2010508475,"remaining_time":1.345494133},
{"learn":[8.303284668],"iteration":130,"passed_time":0.2025697786,"remaining_time":1.343764409},
{"learn":[8.300540968],"iteration":131,"passed_time":0.2041324446,"remaining_time":1.342325469},
{"learn":[8.295458716],"iteration":132,"passed_time":0.2057382573,"remaining_time":1.341165933},
{"learn":[8.289437562],"iteration":133,"passed_time":0.2074330001,"remaining_time":1.340574463},
{"learn":[8.283403826],"iteration":134,"passed_time":0.2090767968,"remaining_time":1.339640217},
{"learn":[8.276159124],"iteration":135,"passed_time":0.2107343688,"remaining_time":1.338783049},
{"learn":[8.275421292],"iteration":136,"passed_time":0.2121397951,"remaining_time":1.336325862},
{"learn":[8.270093603],"iteration":137,"passed_time":0.2138914161,"remaining_time":1.336046382},
{"learn":[8.267259424],"iteration":138,"passed_time":0.2153521612,"remaining_time":1.333943963},
{"learn":[8.261925571],"iteration":139,"passed_time":0.2169761515,"remaining_time":1.332853502},
{"learn":[8.256895614],"iteration":140,"passed_time":0.2185254069,"remaining_time":1.331300174},
{"learn":[8.253816653],"iteration":141,"passed_time":0.2199953944,"remaining_time":1.329267946},
{"learn":[8.249405656],"iteration":142,"passed_time":0.2218011866,"remaining_time":1.329256062},
{"learn":[8.242712389],"iteration":143,"passed_time":0.2234626841,"remaining_time":1.328361511},
{"learn":[8.239939841],"iteration":144,"passed_time":0.2251415055,"remaining_time":1.327558532},
{"learn":[8.233907738],"iteration":145,"passed_time":0.2266170879,"remaining_time":1.325554747},
{"learn":[8.226040754],"iteration":146,"passed_time":0.2282220801,"remaining_time":1.324309077},
{"learn":[8.223248828],"iteration":147,"passed_time":0.2298937595,"remaining_time":1.323442453},
{"learn":[8.219696359],"iteration":148,"passed_time":0.2316344179,"remaining_time":1.322958991},
{"learn":[8.209993701],"iteration":149,"passed_time":0.2333342555,"remaining_time":1.322227448},
{"learn":[8.206360408],"iteration":150,"passed_time":0.2348141697,"remaining_time":1.320246557},
{"learn":[8.203013906],"iteration":151,"passed_time":0.2362930281,"remaining_time":1.318266367},
{"learn":[8.199261315],"iteration":152,"passed_time":0.2378127432,"remaining_time":1.316518912},
{"learn":[8.195479388],"iteration":153,"passed_time":0.2394583751,"remaining_time":1.315466139},
{"learn":[8.192510641],"iteration":154,"passed_time":0.24110478,"remaining_time":1.31440993},
{"learn":[8.186613668],"iteration":155,"passed_time":0.2426034927,"remaining_time":1.312547102},
{"learn":[8.182432253],"iteration":156,"passed_time":0.244387041,"remaining_time":1.312218315},
{"learn":[8.177378633],"iteration":157,"passed_time":0.2458391521,"remaining_time":1.310104848},
{"learn":[8.170455079],"iteration":158,"passed_time":0.2476039599,"remaining_time":1.309653649},
{"learn":[8.167605801],"iteration":159,"passed_time":0.249292537,"remaining_time":1.308785819},
{"learn":[8.161003206],"iteration":160,"passed_time":0.2507308252,"remaining_time":1.306603493},
{"learn":[8.155496112],"iteration":161,"passed_time":0.2522836477,"remaining_time":1.30502282},
{"learn":[8.152261857],"iteration":162,"passed_time":0.254052448,"remaining_time":1.304551527},
{"learn":[8.149025587],"iteration":163,"passed_time":0.255672725,"remaining_time":1.303307306},
{"learn":[8.147377376],"iteration":164,"passed_time":0.256807,"remaining_time":1.29959906},
{"learn":[8.140575791],"iteration":165,"passed_time":0.2583517342,"remaining_time":1.297984014},
{"learn":[8.133178006],"iteration":166,"passed_time":0.2601016907,"remaining_time":1.297393463},
{"learn":[8.125471572],"iteration":167,"passed_time":0.2617389313,"remaining_time":1.296230898},
{"learn":[8.121280942],"iteration":168,"passed_time":0.2633092085,"remaining_time":1.294733446},
{"learn":[8.116368521],"iteration":169,"passed_time":0.264887278,"remaining_time":1.293273181},
{"learn":[8.114034116],"iteration":170,"passed_time":0.2664196409,"remaining_time":1.291589955},
{"learn":[8.108257337],"iteration":171,"passed_time":0.2679146552,"remaining_time":1.289728689},
{"learn":[8.105750437],"iteration":172,"passed_time":0.2695892782,"remaining_time":1.288730249},
{"learn":[8.103909096],"iteration":173,"passed_time":0.2711282249,"remaining_time":1.287079964},
{"learn":[8.098193436],"iteration":174,"passed_time":0.2726546995,"remaining_time":1.285372155},
{"learn":[8.091008985],"iteration":175,"passed_time":0.274144513,"remaining_time":1.283494766},
{"learn":[8.083704795],"iteration":176,"passed_time":0.2756782155,"remaining_time":1.281825827},
{"learn":[8.077721332],"iteration":177,"passed_time":0.2771765541,"remaining_time":1.279995098},
{"learn":[8.075008714],"iteration":178,"passed_time":0.2786173568,"remaining_time":1.27790419},
{"learn":[8.067872155],"iteration":179,"passed_time":0.2801536199,"remaining_time":1.276255379},
{"learn":[8.060270107],"iteration":180,"passed_time":0.2817508061,"remaining_time":1.274883482},
{"learn":[8.056906428],"iteration":181,"passed_time":0.2831979907,"remaining_time":1.272834925},
{"learn":[8.049034278],"iteration":182,"passed_time":0.2850310552,"remaining_time":1.272515694},
{"learn":[8.043838944],"iteration":183,"passed_time":0.2866812309,"remaining_time":1.271368937},
{"learn":[8.036503246],"iteration":184,"passed_time":0.2883946033,"remaining_time":1.270495144},
{"learn":[8.033554874],"iteration":185,"passed_time":0.2899558713,"remaining_time":1.268946663},
{"learn":[8.027499746],"iteration":186,"passed_time":0.2916135541,"remaining_time":1.267817217},
{"learn":[8.024190399],"iteration":187,"passed_time":0.2932043572,"remaining_time":1.266393287},
{"learn":[8.018519786],"iteration":188,"passed_time":0.2947009152,"remaining_time":1.264563187},
{"learn":[8.015437328],"iteration":189,"passed_time":0.2961897108,"remaining_time":1.262703504},
{"learn":[8.007638976],"iteration":190,"passed_time":0.2978038996,"remaining_time":1.261378821},
{"learn":[7.999007114],"iteration":191,"passed_time":0.2995752277,"remaining_time":1.260712417},
{"learn":[7.995721638],"iteration":192,"passed_time":0.3012733112,"remaining_time":1.259728301},
{"learn":[7.991257615],"iteration":193,"passed_time":0.3029515645,"remaining_time":1.258654438},
{"learn":[7.989355752],"iteration":194,"passed_time":0.3044802081,"remaining_time":1.256956757},
{"learn":[7.984934793],"iteration":195,"passed_time":0.3059057631,"remaining_time":1.254837926},
{"learn":[7.981420351],"iteration":196,"passed_time":0.3073859722,"remaining_time":1.252948912},
{"learn":[7.977712199],"iteration":197,"passed_time":0.308825342,"remaining_time":1.250898607},
{"learn":[7.974137363],"iteration":198,"passed_time":0.3102253324,"remaining_time":1.248695936},
{"learn":[7.971662105],"iteration":199,"passed_time":0.3115545232,"remaining_time":1.246218093},
{"learn":[7.965011265],"iteration":200,"passed_time":0.3129830325,"remaining_time":1.244146482},
{"learn":[7.963185531],"iteration":201,"passed_time":0.3143354766,"remaining_time":1.241780744},
{"learn":[7.958690868],"iteration":202,"passed_time":0.3157298469,"remaining_time":1.239589596},
{"learn":[7.954738463],"iteration":203,"passed_time":0.3174602208,"remaining_time":1.238717332},
{"learn":[7.950068085],"iteration":204,"passed_time":0.3190723554,"remaining_time":1.237378159},
{"learn":[7.948229738],"iteration":205,"passed_time":0.3205256871,"remaining_time":1.23542425},
{"learn":[7.940187497],"iteration":206,"passed_time":0.3219703766,"remaining_time":1.233442071},
{"learn":[7.939049035],"iteration":207,"passed_time":0.3230355729,"remaining_time":1.230020066},
{"learn":[7.936216477],"iteration":208,"passed_time":0.3247102532,"remaining_time":1.228927322},
{"learn":[7.932478715],"iteration":209,"passed_time":0.3264187724,"remaining_time":1.227956334},
{"learn":[7.929834842],"iteration":210,"passed_time":0.3278725209,"remaining_time":1.226025683},
{"learn":[7.926537199],"iteration":211,"passed_time":0.3293134225,"remaining_time":1.224051778},
{"learn":[7.920801521],"iteration":212,"passed_time":0.3308648734,"remaining_time":1.22249134},
{"learn":[7.913113305],"iteration":213,"passed_time":0.3325852064,"remaining_time":1.221551272},
{"learn":[7.907616916],"iteration":214,"passed_time":0.3342243544,"remaining_time":1.220307526},
{"learn":[7.905088982],"iteration":215,"passed_time":0.3357936511,"remaining_time":1.218806586},
{"learn":[7.901536942],"iteration":216,"passed_time":0.337247345,"remaining_time":1.216887885},
{"learn":[7.895401311],"iteration":217,"passed_time":0.3388831643,"remaining_time":1.215626764},
{"learn":[7.887457811],"iteration":218,"passed_time":0.3403576677,"remaining_time":1.213786934},
{"learn":[7.884417741],"iteration":219,"passed_time":0.3418059276,"remaining_time":1.21185738},
{"learn":[7.880098195],"iteration":220,"passed_time":0.3433942094,"remaining_time":1.210425743},
{"learn":[7.87468354],"iteration":221,"passed_time":0.3448844331,"remaining_time":1.208649049},
{"learn":[7.871064755],"iteration":222,"passed_time":0.346507598,"remaining_time":1.207338133},
{"learn":[7.87045029],"iteration":223,"passed_time":0.3480608075,"remaining_time":1.205782083},
{"learn":[7.867296809],"iteration":224,"passed_time":0.3497458321,"remaining_time":1.204680088},
{"learn":[7.861837323],"iteration":225,"passed_time":0.3513382112,"remaining_time":1.203255644},
{"learn":[7.859450566],"iteration":226,"passed_time":0.3528649408,"remaining_time":1.201606164},
{"learn":[7.857363423],"iteration":227,"passed_time":0.3545505409,"remaining_time":1.200495691},
{"learn":[7.851547077],"iteration":228,"passed_time":0.3560130001,"remaining_time":1.198628922},
{"learn":[7.84718655],"iteration":229,"passed_time":0.3574414001,"remaining_time":1.196651644},
{"learn":[7.841812331],"iteration":230,"passed_time":0.3590532012,"remaining_time":1.195289661},
{"learn":[7.837385731],"iteration":231,"passed_time":0.36054439,"remaining_time":1.193526257},
{"learn":[7.836763716],"iteration":232,"passed_time":0.3620895842,"remaining_time":1.191942966},
{"learn":[7.833389452],"iteration":233,"passed_time":0.3638113557,"remaining_time":1.190938028},
{"learn":[7.828664446],"iteration":234,"passed_time":0.3653451589,"remaining_time":1.189315092},
{"learn":[7.81993731],"iteration":235,"passed_time":0.3668376888,"remaining_time":1.187559298},
{"learn":[7.814568523],"iteration":236,"passed_time":0.368321603,"remaining_time":1.185777988},
{"learn":[7.813841685],"iteration":237,"passed_time":0.3697246125,"remaining_time":1.183740146},
{"learn":[7.809109099],"iteration":238,"passed_time":0.3711336605,"remaining_time":1.181726844},
{"learn":[7.80814891],"iteration":239,"passed_time":0.3725426742,"remaining_time":1.179718468},
{"learn":[7.804950163],"iteration":240,"passed_time":0.3739889636,"remaining_time":1.177832462},
{"learn":[7.801873066],"iteration":241,"passed_time":0.3754579985,"remaining_time":1.176021334},
{"learn":[7.798028987],"iteration":242,"passed_time":0.377022206,"remaining_time":1.174509506},
{"learn":[7.794015777],"iteration":243,"passed_time":0.3786202299,"remaining_time":1.173102024},
{"learn":[7.791071416],"iteration":244,"passed_time":0.3800936264,"remaining_time":1.17130893},
{"learn":[7.787604643],"iteration":245,"passed_time":0.3817091124,"remaining_time":1.169953946},
{"learn":[7.782483429],"iteration":246,"passed_time":0.3832796391,"remaining_time":1.16845979},
{"learn":[7.778822895],"iteration":247,"passed_time":0.3848521683,"remaining_time":1.166971091},
{"learn":[7.776479638],"iteration":248,"passed_time":0.3862844284,"remaining_time":1.165058658},
{"learn":[7.774487712],"iteration":249,"passed_time":0.3877763163,"remaining_time":1.163328949},
{"learn":[7.772282532],"iteration":250,"passed_time":0.3892428039,"remaining_time":1.161525339},
{"learn":[7.769524715],"iteration":251,"passed_time":0.3908114947,"remaining_time":1.16002777},
{"learn":[7.766344818],"iteration":252,"passed_time":0.3924349403,"remaining_time":1.158691306},
{"learn":[7.762218704],"iteration":253,"passed_time":0.394120153,"remaining_time":1.157533993},
{"learn":[7.758910998],"iteration":254,"passed_time":0.3957794539,"remaining_time":1.156296836},
{"learn":[7.750857226],"iteration":255,"passed_time":0.3973839322,"remaining_time":1.154897053},
{"learn":[7.746677455],"iteration":256,"passed_time":0.3989811768,"remaining_time":1.153474764},
{"learn":[7.744800104],"iteration":257,"passed_time":0.4005932273,"remaining_time":1.1520937},
{"learn":[7.742871399],"iteration":258,"passed_time":0.4021497604,"remaining_time":1.150552017},
{"learn":[7.738929285],"iteration":259,"passed_time":0.4035978222,"remaining_time":1.148701494},
{"learn":[7.737894298],"iteration":260,"passed_time":0.4049321357,"remaining_time":1.146531986},
{"learn":[7.730565194],"iteration":261,"passed_time":0.4063604323,"remaining_time":1.144633584},
{"learn":[7.730111156],"iteration":262,"passed_time":0.4076340896,"remaining_time":1.142305415},
{"learn":[7.72272596],"iteration":263,"passed_time":0.4090505183,"remaining_time":1.140383263},
{"learn":[7.720095688],"iteration":264,"passed_time":0.4108825997,"remaining_time":1.139617776},
{"learn":[7.716506718],"iteration":265,"passed_time":0.4125728362,"remaining_time":1.138452864},
{"learn":[7.712458089],"iteration":266,"passed_time":0.4140618403,"remaining_time":1.136731569},
{"learn":[7.708861954],"iteration":267,"passed_time":0.4156974945,"remaining_time":1.13541256},
{"learn":[7.70609927],"iteration":268,"passed_time":0.4171717822,"remaining_time":1.133652687},
{"learn":[7.697007305],"iteration":269,"passed_time":0.4186862535,"remaining_time":1.132003574},
{"learn":[7.692809805],"iteration":270,"passed_time":0.420334369,"remaining_time":1.130714963},
{"learn":[7.689442667],"iteration":271,"passed_time":0.4218556037,"remaining_time":1.129084116},
{"learn":[7.683979601],"iteration":272,"passed_time":0.4233528032,"remaining_time":1.127390066},
{"learn":[7.681665454],"iteration":273,"passed_time":0.4249715336,"remaining_time":1.126019465},
{"learn":[7.678160348],"iteration":274,"passed_time":0.4264435529,"remaining_time":1.124260276},
{"learn":[7.675174208],"iteration":275,"passed_time":0.4279345734,"remaining_time":1.122553011},
{"learn":[7.671137272],"iteration":276,"passed_time":0.4295035842,"remaining_time":1.121050871},
{"learn":[7.668290848],"iteration":277,"passed_time":0.4310564799,"remaining_time":1.119506397},
{"learn":[7.662829327],"iteration":278,"passed_time":0.4325421713,"remaining_time":1.117788192},
{"learn":[7.659445375],"iteration":279,"passed_time":0.434163933,"remaining_time":1.116421542},
{"learn":[7.658667374],"iteration":280,"passed_time":0.4357042178,"remaining_time":1.1148446},
{"learn":[7.65567397],"iteration":281,"passed_time":0.4373168856,"remaining_time":1.113452212},
{"learn":[7.651926744],"iteration":282,"passed_time":0.438819558,"remaining_time":1.111779587},
{"learn":[7.64761902],"iteration":283,"passed_time":0.4404846364,"remaining_time":1.110517604},
{"learn":[7.647246312],"iteration":284,"passed_time":0.4420832636,"remaining_time":1.109086082},
{"learn":[7.639666777],"iteration":285,"passed_time":0.443676921,"remaining_time":1.107640985},
{"learn":[7.634246838],"iteration":286,"passed_time":0.445277755,"remaining_time":1.10621268},
{"learn":[7.631267635],"iteration":287,"passed_time":0.4467943849,"remaining_time":1.104575007},
{"learn":[7.630100433],"iteration":288,"passed_time":0.4482223908,"remaining_time":1.102720138},
{"learn":[7.623922496],"iteration":289,"passed_time":0.4498173049,"remaining_time":1.10127685},
{"learn":[7.61886963],"iteration":290,"passed_time":0.4513145363,"remaining_time":1.099594523},
{"learn":[7.618471944],"iteration":291,"passed_time":0.452854066,"remaining_time":1.098016023},
{"learn":[7.613908323],"iteration":292,"passed_time":0.454417421,"remaining_time":1.096495279},
{"learn":[7.607019244],"iteration":293,"passed_time":0.4560633228,"remaining_time":1.095172469},
{"learn":[7.602454063],"iteration":294,"passed_time":0.4577840927,"remaining_time":1.094026391},
{"learn":[7.595828867],"iteration":295,"passed_time":0.4593924716,"remaining_time":1.092609122},
{"learn":[7.588985576],"iteration":296,"passed_time":0.4610595793,"remaining_time":1.091329577},
{"learn":[7.588212273],"iteration":297,"passed_time":0.4624165981,"remaining_time":1.089316953},
{"learn":[7.584022069],"iteration":298,"passed_time":0.4639969014,"remaining_time":1.0878322},
{"learn":[7.579276752],"iteration":299,"passed_time":0.4654277085,"remaining_time":1.085997987},
{"learn":[7.57827598],"iteration":300,"passed_time":0.4668636573,"remaining_time":1.084178393},
{"learn":[7.574952825],"iteration":301,"passed_time":0.468386883,"remaining_time":1.082563061},
{"learn":[7.571060185],"iteration":302,"passed_time":0.4698685139,"remaining_time":1.080852654},
{"learn":[7.568218173],"iteration":303,"passed_time":0.471296895,"remaining_time":1.079021838},
{"learn":[7.567861585],"iteration":304,"passed_time":0.4727043245,"remaining_time":1.07714592},
{"learn":[7.565731052],"iteration":305,"passed_time":0.474158121,"remaining_time":1.075378222},
{"learn":[7.561298918],"iteration":306,"passed_time":0.4755630564,"remaining_time":1.073502274},
{"learn":[7.55965016],"iteration":307,"passed_time":0.4769406613,"remaining_time":1.071567979},
{"learn":[7.559123581],"iteration":308,"passed_time":0.47828324,"remaining_time":1.069558961},
{"learn":[7.55395128],"iteration":309,"passed_time":0.4796705303,"remaining_time":1.067653761},
{"learn":[7.553251751],"iteration":310,"passed_time":0.4809826463,"remaining_time":1.065585348},
{"learn":[7.55061726],"iteration":311,"passed_time":0.4823225666,"remaining_time":1.063583096},
{"learn":[7.545320549],"iteration":312,"passed_time":0.4836983288,"remaining_time":1.061663744},
{"learn":[7.544474417],"iteration":313,"passed_time":0.4850807813,"remaining_time":1.059762471},
{"learn":[7.539987653],"iteration":314,"passed_time":0.4864704512,"remaining_time":1.057880188},
{"learn":[7.537678915],"iteration":315,"passed_time":0.4878994394,"remaining_time":1.056086128},
{"learn":[7.531345463],"iteration":316,"passed_time":0.4893282038,"remaining_time":1.05429389},
{"learn":[7.530920022],"iteration":317,"passed_time":0.490102638,"remaining_time":1.051100626},
{"learn":[7.528372784],"iteration":318,"passed_time":0.4916816894,"remaining_time":1.049640221},
{"learn":[7.526873777],"iteration":319,"passed_time":0.4931552057,"remaining_time":1.047954812},
{"learn":[7.522612777],"iteration":320,"passed_time":0.4949131808,"remaining_time":1.046872429},
{"learn":[7.519509791],"iteration":321,"passed_time":0.4963946403,"remaining_time":1.045203622},
{"learn":[7.516841458],"iteration":322,"passed_time":0.4979725477,"remaining_time":1.043738126},
{"learn":[7.51604369],"iteration":323,"passed_time":0.4994104395,"remaining_time":1.041979806},
{"learn":[7.514342187],"iteration":324,"passed_time":0.500900977,"remaining_time":1.040332798},
{"learn":[7.51000279],"iteration":325,"passed_time":0.5024733303,"remaining_time":1.038855904},
{"learn":[7.509521841],"iteration":326,"passed_time":0.5041174434,"remaining_time":1.037526114},
{"learn":[7.50645329],"iteration":327,"passed_time":0.505712717,"remaining_time":1.036094347},
{"learn":[7.506071068],"iteration":328,"passed_time":0.5071471563,"remaining_time":1.034333562},
{"learn":[7.502566051],"iteration":329,"passed_time":0.5086285395,"remaining_time":1.032670065},
{"learn":[7.501799062],"iteration":330,"passed_time":0.5103061113,"remaining_time":1.031404195},
{"learn":[7.500850444],"iteration":331,"passed_time":0.5119131101,"remaining_time":1.029993848},
{"learn":[7.498250016],"iteration":332,"passed_time":0.5135984793,"remaining_time":1.028739296},
{"learn":[7.491707566],"iteration":333,"passed_time":0.5152087906,"remaining_time":1.027332499},
{"learn":[7.489805523],"iteration":334,"passed_time":0.5167841191,"remaining_time":1.025855042},
{"learn":[7.485809959],"iteration":335,"passed_time":0.518451097,"remaining_time":1.02455812},
{"learn":[7.485088942],"iteration":336,"passed_time":0.5200583323,"remaining_time":1.023141467},
{"learn":[7.484755395],"iteration":337,"passed_time":0.521511531,"remaining_time":1.021421993},
{"learn":[7.484403827],"iteration":338,"passed_time":0.5230819357,"remaining_time":1.019932624},
{"learn":[7.48186013],"iteration":339,"passed_time":0.5245718173,"remaining_time":1.018286469},
{"learn":[7.478410035],"iteration":340,"passed_time":0.5260877557,"remaining_time":1.016691586},
{"learn":[7.471724233],"iteration":341,"passed_time":0.5275723431,"remaining_time":1.015036847},
{"learn":[7.465313347],"iteration":342,"passed_time":0.5291225979,"remaining_time":1.013508883},
{"learn":[7.463228987],"iteration":343,"passed_time":0.5307126362,"remaining_time":1.012056655},
{"learn":[7.460533923],"iteration":344,"passed_time":0.5322383716,"remaining_time":1.010481546},
{"learn":[7.457350435],"iteration":345,"passed_time":0.5337142295,"remaining_time":1.008812445},
{"learn":[7.451415948],"iteration":346,"passed_time":0.5352424221,"remaining_time":1.007242944},
{"learn":[7.450312238],"iteration":347,"passed_time":0.5367023616,"remaining_time":1.005545804},
{"learn":[7.44889495],"iteration":348,"passed_time":0.5381780897,"remaining_time":1.003879474},
{"learn":[7.443554624],"iteration":349,"passed_time":0.5398073923,"remaining_time":1.002499443},
{"learn":[7.437738566],"iteration":350,"passed_time":0.5413099945,"remaining_time":1.000883722},
{"learn":[7.430061186],"iteration":351,"passed_time":0.5428927691,"remaining_time":0.9994162341},
{"learn":[7.424728758],"iteration":352,"passed_time":0.5444927174,"remaining_time":0.9979795699},
{"learn":[7.420251478],"iteration":353,"passed_time":0.545937224,"remaining_time":0.9962583241},
{"learn":[7.412924099],"iteration":354,"passed_time":0.5473894192,"remaining_time":0.9945526067},
{"learn":[7.411837605],"iteration":355,"passed_time":0.5488811668,"remaining_time":0.9929198636},
{"learn":[7.411486324],"iteration":356,"passed_time":0.550511283,"remaining_time":0.9915371287},
{"learn":[7.407056215],"iteration":357,"passed_time":0.5520106485,"remaining_time":0.9899185373},
{"learn":[7.403068753],"iteration":358,"passed_time":0.5533920399,"remaining_time":0.9880899653},
{"learn":[7.401196985],"iteration":359,"passed_time":0.5549387666,"remaining_time":0.9865578073},
{"learn":[7.396521795],"iteration":360,"passed_time":0.5564076959,"remaining_time":0.9848878607},
{"learn":[7.391085346],"iteration":361,"passed_time":0.5578890234,"remaining_time":0.9832408755},
{"learn":[7.390682475],"iteration":362,"passed_time":0.5593280013,"remaining_time":0.9815204871},
{"learn":[7.39020665],"iteration":363,"passed_time":0.560866626,"remaining_time":0.9799757532},
{"learn":[7.389479206],"iteration":364,"passed_time":0.5623095937,"remaining_time":0.9782646357},
{"learn":[7.386772456],"iteration":365,"passed_time":0.5637108275,"remaining_time":0.9764826903},
{"learn":[7.386526158],"iteration":366,"passed_time":0.5652399322,"remaining_time":0.9749233708},
{"learn":[7.379658836],"iteration":367,"passed_time":0.5667348187,"remaining_time":0.9733054494},
{"learn":[7.371927197],"iteration":368,"passed_time":0.5682358577,"remaining_time":0.9716987161},
{"learn":[7.370760477],"iteration":369,"passed_time":0.5696734149,"remaining_time":0.9699844633},
{"learn":[7.361632053],"iteration":370,"passed_time":0.5712392115,"remaining_time":0.9684891214},
{"learn":[7.356398031],"iteration":371,"passed_time":0.5727504373,"remaining_time":0.9669012758},
{"learn":[7.355913068],"iteration":372,"passed_time":0.5742046684,"remaining_time":0.9652180351},
{"learn":[7.354213956],"iteration":373,"passed_time":0.5757389092,"remaining_time":0.963669939},
{"learn":[7.351487946],"iteration":374,"passed_time":0.5771683392,"remaining_time":0.9619472319},
{"learn":[7.34844703],"iteration":375,"passed_time":0.5786377436,"remaining_time":0.9602924256},
{"learn":[7.343065298],"iteration":376,"passed_time":0.5801909859,"remaining_time":0.9587771464},
{"learn":[7.342615397],"iteration":377,"passed_time":0.5818879628,"remaining_time":0.9574981822},
{"learn":[7.337305251],"iteration":378,"passed_time":0.5835532851,"remaining_time":0.9561651453},
{"learn":[7.333788514],"iteration":379,"passed_time":0.5853780639,"remaining_time":0.9550905253},
{"learn":[7.329568036],"iteration":380,"passed_time":0.5873162414,"remaining_time":0.9541962033},
{"learn":[7.328794857],"iteration":381,"passed_time":0.5890078191,"remaining_time":0.9528974664},
{"learn":[7.32515038],"iteration":382,"passed_time":0.5908558296,"remaining_time":0.9518486864},
{"learn":[7.321914344],"iteration":383,"passed_time":0.5924745046,"remaining_time":0.9504278511},
{"learn":[7.321096116],"iteration":384,"passed_time":0.5941039474,"remaining_time":0.9490231887},
{"learn":[7.320727302],"iteration":385,"passed_time":0.595767813,"remaining_time":0.947672117},
{"learn":[7.320086142],"iteration":386,"passed_time":0.5973714399,"remaining_time":0.946224012},
{"learn":[7.313581265],"iteration":387,"passed_time":0.5992702638,"remaining_time":0.9452407254},
{"learn":[7.313310157],"iteration":388,"passed_time":0.6010488076,"remaining_time":0.9440638083},
{"learn":[7.309086495],"iteration":389,"passed_time":0.602651163,"remaining_time":0.9426082293},
{"learn":[7.30892082],"iteration":390,"passed_time":0.6042556451,"remaining_time":0.9411552119},
{"learn":[7.308138506],"iteration":391,"passed_time":0.6058351627,"remaining_time":0.9396627014},
{"learn":[7.307592692],"iteration":392,"passed_time":0.6074966565,"remaining_time":0.9382963626},
{"learn":[7.306106947],"iteration":393,"passed_time":0.6091881044,"remaining_time":0.9369745971},
{"learn":[7.305821817],"iteration":394,"passed_time":0.6107611222,"remaining_time":0.9354695669},
{"learn":[7.305552516],"iteration":395,"passed_time":0.6123414887,"remaining_time":0.9339754019},
{"learn":[7.301103046],"iteration":396,"passed_time":0.6141131373,"remaining_time":0.9327713395},
{"learn":[7.299174165],"iteration":397,"passed_time":0.6157503824,"remaining_time":0.9313611312},
{"learn":[7.298025318],"iteration":398,"passed_time":0.6175567788,"remaining_time":0.9302045716},
{"learn":[7.294018964],"iteration":399,"passed_time":0.6191083721,"remaining_time":0.9286625581},
{"learn":[7.291659983],"iteration":400,"passed_time":0.6207487128,"remaining_time":0.9272530648},
{"learn":[7.291375792],"iteration":401,"passed_time":0.6224151227,"remaining_time":0.9258812024},
{"learn":[7.290341836],"iteration":402,"passed_time":0.6240203733,"remaining_time":0.9244172775},
{"learn":[7.284066498],"iteration":403,"passed_time":0.62591599,"remaining_time":0.923381015},
{"learn":[7.279194448],"iteration":404,"passed_time":0.6277970179,"remaining_time":0.9223190757},
{"learn":[7.277401241],"iteration":405,"passed_time":0.6294995809,"remaining_time":0.9209919976},
{"learn":[7.27712202],"iteration":406,"passed_time":0.6312200652,"remaining_time":0.9196891859},
{"learn":[7.274421932],"iteration":407,"passed_time":0.6328704643,"remaining_time":0.9182826345},
{"learn":[7.269920311],"iteration":408,"passed_time":0.6345851849,"remaining_time":0.9169678344},
{"learn":[7.265091277],"iteration":409,"passed_time":0.6362191578,"remaining_time":0.9155348856},
{"learn":[7.260998178],"iteration":410,"passed_time":0.6380643114,"remaining_time":0.9144035996},
{"learn":[7.258259047],"iteration":411,"passed_time":0.6398923007,"remaining_time":0.9132443515},
{"learn":[7.254563382],"iteration":412,"passed_time":0.6415682179,"remaining_time":0.9118657237},
{"learn":[7.254019956],"iteration":413,"passed_time":0.6431813526,"remaining_time":0.9103967938},
{"learn":[7.249345637],"iteration":414,"passed_time":0.6450645191,"remaining_time":0.9093078161},
{"learn":[7.247711722],"iteration":415,"passed_time":0.6468634508,"remaining_time":0.9080967675},
{"learn":[7.24414013],"iteration":416,"passed_time":0.6487127348,"remaining_time":0.9069532959},
{"learn":[7.243233199],"iteration":417,"passed_time":0.6504502269,"remaining_time":0.9056507944},
{"learn":[7.239010365],"iteration":418,"passed_time":0.6523071388,"remaining_time":0.9045118083},
{"learn":[7.23799754],"iteration":419,"passed_time":0.6544275336,"remaining_time":0.9037332607},
{"learn":[7.237433975],"iteration":420,"passed_time":0.656547374,"remaining_time":0.9029475761},
{"learn":[7.236999813],"iteration":421,"passed_time":0.6587150645,"remaining_time":0.9022211073},
{"learn":[7.235498068],"iteration":422,"passed_time":0.6610369843,"remaining_time":0.9016982032},
{"learn":[7.234452825],"iteration":423,"passed_time":0.6632419188,"remaining_time":0.9010078897},
{"learn":[7.23077085],"iteration":424,"passed_time":0.6651021971,"remaining_time":0.899844149},
{"learn":[7.223255044],"iteration":425,"passed_time":0.6668734609,"remaining_time":0.8985571985},
{"learn":[7.222734518],"iteration":426,"passed_time":0.6686911519,"remaining_time":0.8973302812},
{"learn":[7.221531213],"iteration":427,"passed_time":0.6704467911,"remaining_time":0.8960176741},
{"learn":[7.22051688],"iteration":428,"passed_time":0.6720996248,"remaining_time":0.8945661673},
{"learn":[7.217320331],"iteration":429,"passed_time":0.6738942253,"remaining_time":0.8933016475},
{"learn":[7.215092377],"iteration":430,"passed_time":0.6756870371,"remaining_time":0.8920323065},
{"learn":[7.214860079],"iteration":431,"passed_time":0.6774184078,"remaining_time":0.8906797584},
{"learn":[7.209716116],"iteration":432,"passed_time":0.6792736436,"remaining_time":0.8894876581},
{"learn":[7.204496677],"iteration":433,"passed_time":0.6811330463,"remaining_time":0.8882979359},
{"learn":[7.199212288],"iteration":434,"passed_time":0.682976809,"remaining_time":0.8870848209},
{"learn":[7.198897733],"iteration":435,"passed_time":0.6845906408,"remaining_time":0.8855713794},
{"learn":[7.194448216],"iteration":436,"passed_time":0.6864143849,"remaining_time":0.8843279146},
{"learn":[7.19085809],"iteration":437,"passed_time":0.6883710876,"remaining_time":0.8832524},
{"learn":[7.188379877],"iteration":438,"passed_time":0.690243815,"remaining_time":0.8820655585},
{"learn":[7.184662831],"iteration":439,"passed_time":0.6920524537,"remaining_time":0.8807940319},
{"learn":[7.181524649],"iteration":440,"passed_time":0.6939094028,"remaining_time":0.8795813065},
{"learn":[7.176950494],"iteration":441,"passed_time":0.6956699943,"remaining_time":0.87824402},
{"learn":[7.174413366],"iteration":442,"passed_time":0.6973329482,"remaining_time":0.8767820591},
{"learn":[7.17024042],"iteration":443,"passed_time":0.6989710009,"remaining_time":0.8752880102},
{"learn":[7.169829304],"iteration":444,"passed_time":0.7005118948,"remaining_time":0.8736721385},
{"learn":[7.168880661],"iteration":445,"passed_time":0.7017987077,"remaining_time":0.8717409956},
{"learn":[7.168768119],"iteration":446,"passed_time":0.7034217082,"remaining_time":0.8702286457},
{"learn":[7.16798514],"iteration":447,"passed_time":0.705059166,"remaining_time":0.8687336152},
{"learn":[7.164996091],"iteration":448,"passed_time":0.7069172699,"remaining_time":0.867508721},
{"learn":[7.16180178],"iteration":449,"passed_time":0.7085351846,"remaining_time":0.8659874478},
{"learn":[7.161425492],"iteration":450,"passed_time":0.7101004286,"remaining_time":0.8644016304},
{"learn":[7.158180422],"iteration":451,"passed_time":0.7117076948,"remaining_time":0.8628668512},
{"learn":[7.157788837],"iteration":452,"passed_time":0.7133084986,"remaining_time":0.8613239487},
{"learn":[7.154395583],"iteration":453,"passed_time":0.7148756096,"remaining_time":0.8597402705},
{"learn":[7.150368922],"iteration":454,"passed_time":0.7164805538,"remaining_time":0.858201982},
{"learn":[7.146196949],"iteration":455,"passed_time":0.7181946315,"remaining_time":0.8567935955},
{"learn":[7.143135226],"iteration":456,"passed_time":0.7198491975,"remaining_time":0.8553131603},
{"learn":[7.13992186],"iteration":457,"passed_time":0.7215192897,"remaining_time":0.8538503384},
{"learn":[7.139266208],"iteration":458,"passed_time":0.7231561987,"remaining_time":0.8523475021},
{"learn":[7.139015185],"iteration":459,"passed_time":0.724997142,"remaining_time":0.8510836015},
{"learn":[7.135700665],"iteration":460,"passed_time":0.7269344979,"remaining_time":0.8499299227},
{"learn":[7.133268236],"iteration":461,"passed_time":0.7286497855,"remaining_time":0.8485142523},
{"learn":[7.129676355],"iteration":462,"passed_time":0.7304497254,"remaining_time":0.8471954699},
{"learn":[7.128120134],"iteration":463,"passed_time":0.7322347951,"remaining_time":0.8458574357},
{"learn":[7.126468485],"iteration":464,"passed_time":0.7343576687,"remaining_time":0.844906135},
{"learn":[7.12626726],"iteration":465,"passed_time":0.736080524,"remaining_time":0.8434914159},
{"learn":[7.123649666],"iteration":466,"passed_time":0.7381082127,"remaining_time":0.842423292},
{"learn":[7.117830661],"iteration":467,"passed_time":0.7399441634,"remaining_time":0.8411331089},
{"learn":[7.117686203],"iteration":468,"passed_time":0.7416768957,"remaining_time":0.8397237348},
{"learn":[7.113771586],"iteration":469,"passed_time":0.7433360787,"remaining_time":0.8382300462},
{"learn":[7.110676165],"iteration":470,"passed_time":0.7452859812,"remaining_time":0.8370621742},
{"learn":[7.110013398],"iteration":471,"passed_time":0.7471228313,"remaining_time":0.8357645231},
{"learn":[7.108103769],"iteration":472,"passed_time":0.7487546878,"remaining_time":0.8342361955},
{"learn":[7.106656741],"iteration":473,"passed_time":0.7504626163,"remaining_time":0.8327918485},
{"learn":[7.103201157],"iteration":474,"passed_time":0.7523705807,"remaining_time":0.8315674839},
{"learn":[7.09780083],"iteration":475,"passed_time":0.7545950241,"remaining_time":0.83068864},
{"learn":[7.097152472],"iteration":476,"passed_time":0.7566643732,"remaining_time":0.8296341031},
{"learn":[7.097033138],"iteration":477,"passed_time":0.7586762769,"remaining_time":0.8285125869},
{"learn":[7.093578117],"iteration":478,"passed_time":0.7605935029,"remaining_time":0.8272843738},
{"learn":[7.090369691],"iteration":479,"passed_time":0.7626987824,"remaining_time":0.8262570143},
{"learn":[7.086647471],"iteration":480,"passed_time":0.7645368669,"remaining_time":0.8249368689},
{"learn":[7.083887976],"iteration":481,"passed_time":0.7665907295,"remaining_time":0.8238464687},
{"learn":[7.07969001],"iteration":482,"passed_time":0.7686904929,"remaining_time":0.8228012108},
{"learn":[7.076401233],"iteration":483,"passed_time":0.7703629144,"remaining_time":0.8212959996},
{"learn":[7.069811346],"iteration":484,"passed_time":0.7720567693,"remaining_time":0.8198128581},
{"learn":[7.069088719],"iteration":485,"passed_time":0.7738234306,"remaining_time":0.8184058504},
{"learn":[7.067044674],"iteration":486,"passed_time":0.7755129436,"remaining_time":0.8169160987},
{"learn":[7.06264585],"iteration":487,"passed_time":0.7773286153,"remaining_time":0.8155578915},
{"learn":[7.056154597],"iteration":488,"passed_time":0.7791301333,"remaining_time":0.8141830227},
{"learn":[7.049413787],"iteration":489,"passed_time":0.7809662859,"remaining_time":0.8128424608},
{"learn":[7.047475195],"iteration":490,"passed_time":0.7829735562,"remaining_time":0.8116772711},
{"learn":[7.041695101],"iteration":491,"passed_time":0.7851555731,"remaining_time":0.8106890877},
{"learn":[7.035936253],"iteration":492,"passed_time":0.7870580017,"remaining_time":0.8094085332},
{"learn":[7.030248122],"iteration":493,"passed_time":0.7891795275,"remaining_time":0.8083498804},
{"learn":[7.027693208],"iteration":494,"passed_time":0.7915522952,"remaining_time":0.8075432507},
{"learn":[7.023504988],"iteration":495,"passed_time":0.7934236015,"remaining_time":0.8062207564},
{"learn":[7.023362945],"iteration":496,"passed_time":0.7954334381,"remaining_time":0.8050362562},
{"learn":[7.019598515],"iteration":497,"passed_time":0.7973788026,"remaining_time":0.8037834516},
{"learn":[7.016745028],"iteration":498,"passed_time":0.7997982221,"remaining_time":0.8030038262},
{"learn":[7.015808769],"iteration":499,"passed_time":0.8021443534,"remaining_time":0.8021443534},
{"learn":[7.015078914],"iteration":500,"passed_time":0.8044118069,"remaining_time":0.8012005821},
{"learn":[7.011607301],"iteration":501,"passed_time":0.8065864471,"remaining_time":0.8001594635},
{"learn":[7.009450146],"iteration":502,"passed_time":0.8089413073,"remaining_time":0.799291908},
{"learn":[7.007931942],"iteration":503,"passed_time":0.8113299644,"remaining_time":0.798451711},
{"learn":[7.007252442],"iteration":504,"passed_time":0.8135762964,"remaining_time":0.7974658747},
{"learn":[7.005459233],"iteration":505,"passed_time":0.8161212504,"remaining_time":0.7967665963},
{"learn":[7.002468297],"iteration":506,"passed_time":0.8183713343,"remaining_time":0.7957733093},
{"learn":[6.999521858],"iteration":507,"passed_time":0.8207917766,"remaining_time":0.7949400671},
{"learn":[6.998293477],"iteration":508,"passed_time":0.8228345658,"remaining_time":0.7937362904},
{"learn":[6.996836261],"iteration":509,"passed_time":0.8245615206,"remaining_time":0.7922257747},
{"learn":[6.994568095],"iteration":510,"passed_time":0.826346324,"remaining_time":0.79076977},
{"learn":[6.991237768],"iteration":511,"passed_time":0.8280853153,"remaining_time":0.7892688161},
{"learn":[6.987457633],"iteration":512,"passed_time":0.8299886931,"remaining_time":0.7879229893},
{"learn":[6.985044267],"iteration":513,"passed_time":0.8320866699,"remaining_time":0.7867589914},
{"learn":[6.984323951],"iteration":514,"passed_time":0.8342677178,"remaining_time":0.7856695984},
{"learn":[6.982557357],"iteration":515,"passed_time":0.8360365925,"remaining_time":0.7841893619},
{"learn":[6.976429352],"iteration":516,"passed_time":0.8379299412,"remaining_time":0.7828242971},
{"learn":[6.976275016],"iteration":517,"passed_time":0.8396759231,"remaining_time":0.7813200674},
{"learn":[6.976128817],"iteration":518,"passed_time":0.8413799365,"remaining_time":0.7797760105},
{"learn":[6.974835576],"iteration":519,"passed_time":0.8431095712,"remaining_time":0.7782549888},
{"learn":[6.970730227],"iteration":520,"passed_time":0.8449924184,"remaining_time":0.7768740276},
{"learn":[6.969321701],"iteration":521,"passed_time":0.8468504123,"remaining_time":0.7754683852},
{"learn":[6.965771438],"iteration":522,"passed_time":0.8487671702,"remaining_time":0.7741146084},
{"learn":[6.96324345],"iteration":523,"passed_time":0.8505306217,"remaining_time":0.7726194197},
{"learn":[6.963046144],"iteration":524,"passed_time":0.8521639424,"remaining_time":0.7710054717},
{"learn":[6.962756514],"iteration":525,"passed_time":0.8540320995,"remaining_time":0.7696030707},
{"learn":[6.957875911],"iteration":526,"passed_time":0.8560317293,"remaining_time":0.7683169031},
{"learn":[6.955704619],"iteration":527,"passed_time":0.8577753019,"remaining_time":0.7667991335},
{"learn":[6.954261853],"iteration":528,"passed_time":0.8597914171,"remaining_time":0.765523171},
{"learn":[6.950146531],"iteration":529,"passed_time":0.8617833442,"remaining_time":0.7642229656},
{"learn":[6.946634799],"iteration":530,"passed_time":0.8636382045,"remaining_time":0.7627990921},
{"learn":[6.944462473],"iteration":531,"passed_time":0.865374222,"remaining_time":0.7612690525},
{"learn":[6.944080612],"iteration":532,"passed_time":0.8671835489,"remaining_time":0.7598024716},
{"learn":[6.940380367],"iteration":533,"passed_time":0.8689610386,"remaining_time":0.758306824},
{"learn":[6.939162525],"iteration":534,"passed_time":0.8707352609,"remaining_time":0.7568072829},
{"learn":[6.938787046],"iteration":535,"passed_time":0.8724440222,"remaining_time":0.7552500491},
{"learn":[6.937388776],"iteration":536,"passed_time":0.8743028977,"remaining_time":0.753821679},
{"learn":[6.9336722],"iteration":537,"passed_time":0.8761374872,"remaining_time":0.7523708533},
{"learn":[6.927844895],"iteration":538,"passed_time":0.8780794914,"remaining_time":0.7510104741},
{"learn":[6.925560179],"iteration":539,"passed_time":0.8798227844,"remaining_time":0.7494786682},
{"learn":[6.922768675],"iteration":540,"passed_time":0.8813951099,"remaining_time":0.7478010267},
{"learn":[6.918494257],"iteration":541,"passed_time":0.882932662,"remaining_time":0.7460943896},
{"learn":[6.916015184],"iteration":542,"passed_time":0.8845109385,"remaining_time":0.7444226499},
{"learn":[6.913054261],"iteration":543,"passed_time":0.8861972075,"remaining_time":0.7428417769},
{"learn":[6.912200368],"iteration":544,"passed_time":0.887652602,"remaining_time":0.7410677687},
{"learn":[6.910461103],"iteration":545,"passed_time":0.8890625256,"remaining_time":0.7392571184},
{"learn":[6.909321569],"iteration":546,"passed_time":0.8905569462,"remaining_time":0.7375179097},
{"learn":[6.902965365],"iteration":547,"passed_time":0.8920760003,"remaining_time":0.7357999127},
{"learn":[6.902663581],"iteration":548,"passed_time":0.8935599152,"remaining_time":0.7340537737},
{"learn":[6.902462905],"iteration":549,"passed_time":0.8949689427,"remaining_time":0.7322473168},
{"learn":[6.898984242],"iteration":550,"passed_time":0.8964194815,"remaining_time":0.7304761292},
{"learn":[6.895430512],"iteration":551,"passed_time":0.8978866986,"remaining_time":0.7287196394},
{"learn":[6.890495683],"iteration":552,"passed_time":0.8993691478,"remaining_time":0.7269765083},
{"learn":[6.8902748],"iteration":553,"passed_time":0.9007507555,"remaining_time":0.7251531353},
{"learn":[6.886287901],"iteration":554,"passed_time":0.9022121041,"remaining_time":0.7233952907},
{"learn":[6.883604457],"iteration":555,"passed_time":0.9037036432,"remaining_time":0.7216626216},
{"learn":[6.879637285],"iteration":556,"passed_time":0.9051836199,"remaining_time":0.7199216223},
{"learn":[6.878381608],"iteration":557,"passed_time":0.906646478,"remaining_time":0.7181679987},
{"learn":[6.875993453],"iteration":558,"passed_time":0.9081323018,"remaining_time":0.7164335332},
{"learn":[6.875339155],"iteration":559,"passed_time":0.9096203838,"remaining_time":0.7147017301},
{"learn":[6.872803714],"iteration":560,"passed_time":0.9110954758,"remaining_time":0.7129606308},
{"learn":[6.871186613],"iteration":561,"passed_time":0.9125042668,"remaining_time":0.7111688058},
{"learn":[6.865699963],"iteration":562,"passed_time":0.9139658251,"remaining_time":0.7094192994},
{"learn":[6.862277553],"iteration":563,"passed_time":0.9153909503,"remaining_time":0.7076426495},
{"learn":[6.859115438],"iteration":564,"passed_time":0.916916276,"remaining_time":0.7059443895},
{"learn":[6.852516203],"iteration":565,"passed_time":0.9183989148,"remaining_time":0.7042140089},
{"learn":[6.850793248],"iteration":566,"passed_time":0.9198305592,"remaining_time":0.7024455593},
{"learn":[6.844544936],"iteration":567,"passed_time":0.921291339,"remaining_time":0.700700455},
{"learn":[6.8392846],"iteration":568,"passed_time":0.922756967,"remaining_time":0.6989600225},
{"learn":[6.835272788],"iteration":569,"passed_time":0.9245166514,"remaining_time":0.6974423861},
{"learn":[6.832608715],"iteration":570,"passed_time":0.9259802308,"remaining_time":0.6957014343},
{"learn":[6.830139464],"iteration":571,"passed_time":0.9274876868,"remaining_time":0.6939942831},
{"learn":[6.826588593],"iteration":572,"passed_time":0.9289803703,"remaining_time":0.6922768205},
{"learn":[6.824642098],"iteration":573,"passed_time":0.9304392434,"remaining_time":0.6905350483},
{"learn":[6.82030599],"iteration":574,"passed_time":0.9320168073,"remaining_time":0.688881988},
{"learn":[6.814243812],"iteration":575,"passed_time":0.933761728,"remaining_time":0.6873523831},
{"learn":[6.810439887],"iteration":576,"passed_time":0.9353775933,"remaining_time":0.6857274211},
{"learn":[6.807761024],"iteration":577,"passed_time":0.9370685057,"remaining_time":0.6841572827},
{"learn":[6.805187663],"iteration":578,"passed_time":0.9387903746,"remaining_time":0.6826092361},
{"learn":[6.803311787],"iteration":579,"passed_time":0.9405789924,"remaining_time":0.6811089255},
{"learn":[6.802902087],"iteration":580,"passed_time":0.9421783919,"remaining_time":0.6794711639},
{"learn":[6.800845032],"iteration":581,"passed_time":0.9438298675,"remaining_time":0.6778709358},
{"learn":[6.7992404],"iteration":582,"passed_time":0.9453538807,"remaining_time":0.6761793624},
{"learn":[6.798814263],"iteration":583,"passed_time":0.9468628775,"remaining_time":0.6744776662},
{"learn":[6.795292896],"iteration":584,"passed_time":0.9483709545,"remaining_time":0.6727759762},
{"learn":[6.794652557],"iteration":585,"passed_time":0.9497864335,"remaining_time":0.6710095281},
{"learn":[6.788759241],"iteration":586,"passed_time":0.9514475195,"remaining_time":0.6694170793},
{"learn":[6.785020514],"iteration":587,"passed_time":0.9530011633,"remaining_time":0.6677491144},
{"learn":[6.780906211],"iteration":588,"passed_time":0.9547122844,"remaining_time":0.6661914243},
{"learn":[6.778310486],"iteration":589,"passed_time":0.9563038036,"remaining_time":0.6645501008},
{"learn":[6.774670019],"iteration":590,"passed_time":0.957791226,"remaining_time":0.662836906},
{"learn":[6.771334025],"iteration":591,"passed_time":0.9592659417,"remaining_time":0.6611157166},
{"learn":[6.76623632],"iteration":592,"passed_time":0.9607918816,"remaining_time":0.6594305157},
{"learn":[6.760976366],"iteration":593,"passed_time":0.9623396985,"remaining_time":0.657760804},
{"learn":[6.76075321],"iteration":594,"passed_time":0.9637123234,"remaining_time":0.6559722538},
{"learn":[6.760179982],"iteration":595,"passed_time":0.9651617683,"remaining_time":0.6542371718},
{"learn":[6.759354741],"iteration":596,"passed_time":0.9667690051,"remaining_time":0.6526095629},
{"learn":[6.754554596],"iteration":597,"passed_time":0.9684308641,"remaining_time":0.6510187414},
{"learn":[6.750737864],"iteration":598,"passed_time":0.9701733469,"remaining_time":0.6494816563},
{"learn":[6.748790797],"iteration":599,"passed_time":0.9718626862,"remaining_time":0.6479084575},
{"learn":[6.747207193],"iteration":600,"passed_time":0.9734711046,"remaining_time":0.6462811493},
{"learn":[6.744462787],"iteration":601,"passed_time":0.9750083176,"remaining_time":0.6446068279},
{"learn":[6.740939713],"iteration":602,"passed_time":0.9765500934,"remaining_time":0.6429359653},
{"learn":[6.734504056],"iteration":603,"passed_time":0.9782824089,"remaining_time":0.6413904535},
{"learn":[6.730765213],"iteration":604,"passed_time":0.9798690333,"remaining_time":0.6397492035},
{"learn":[6.728065407],"iteration":605,"passed_time":0.9815437574,"remaining_time":0.6381654132},
{"learn":[6.728000124],"iteration":606,"passed_time":0.9831026205,"remaining_time":0.6365063095},
{"learn":[6.725034082],"iteration":607,"passed_time":0.9848601165,"remaining_time":0.6349756014},
{"learn":[6.722885584],"iteration":608,"passed_time":0.986777074,"remaining_time":0.6335465287},
{"learn":[6.721941341],"iteration":609,"passed_time":0.988698568,"remaining_time":0.6321187566},
{"learn":[6.719531265],"iteration":610,"passed_time":0.9905318707,"remaining_time":0.6306332205},
{"learn":[6.716968251],"iteration":611,"passed_time":0.9922724157,"remaining_time":0.6290877407},
{"learn":[6.714745811],"iteration":612,"passed_time":0.9943241029,"remaining_time":0.6277380552},
{"learn":[6.712088801],"iteration":613,"passed_time":0.9961330781,"remaining_time":0.6262334986},
{"learn":[6.710889946],"iteration":614,"passed_time":0.9979856121,"remaining_time":0.6247552206},
{"learn":[6.708176897],"iteration":615,"passed_time":0.9997530467,"remaining_time":0.6232226785},
{"learn":[6.707620041],"iteration":616,"passed_time":1.001425861,"remaining_time":0.6216306399},
{"learn":[6.704230578],"iteration":617,"passed_time":1.00313988,"remaining_time":0.6200638092},
{"learn":[6.701647965],"iteration":618,"passed_time":1.004871098,"remaining_time":0.6185070895},
{"learn":[6.69846927],"iteration":619,"passed_time":1.006521139,"remaining_time":0.6169000528},
{"learn":[6.69611812],"iteration":620,"passed_time":1.008196642,"remaining_time":0.6153084177},
{"learn":[6.695845386],"iteration":621,"passed_time":1.009762074,"remaining_time":0.6136496208},
{"learn":[6.691273386],"iteration":622,"passed_time":1.011463335,"remaining_time":0.6120733183},
{"learn":[6.686339787],"iteration":623,"passed_time":1.013017767,"remaining_time":0.6104081417},
{"learn":[6.684718302],"iteration":624,"passed_time":1.014518731,"remaining_time":0.6087112388},
{"learn":[6.679302589],"iteration":625,"passed_time":1.016195343,"remaining_time":0.6071199017},
{"learn":[6.676592224],"iteration":626,"passed_time":1.018005764,"remaining_time":0.6056078948},
{"learn":[6.673347024],"iteration":627,"passed_time":1.019784797,"remaining_time":0.6040763447},
{"learn":[6.670383098],"iteration":628,"passed_time":1.021538025,"remaining_time":0.6025287874},
{"learn":[6.669592199],"iteration":629,"passed_time":1.023318634,"remaining_time":0.6009966583},
{"learn":[6.667169536],"iteration":630,"passed_time":1.024964813,"remaining_time":0.5993851281},
{"learn":[6.665424597],"iteration":631,"passed_time":1.026656032,"remaining_time":0.5977997149},
{"learn":[6.662264796],"iteration":632,"passed_time":1.028341842,"remaining_time":0.5962108307},
{"learn":[6.661947444],"iteration":633,"passed_time":1.029876239,"remaining_time":0.5945342323},
{"learn":[6.65930492],"iteration":634,"passed_time":1.031613485,"remaining_time":0.5929746805},
{"learn":[6.656839447],"iteration":635,"passed_time":1.033589298,"remaining_time":0.5915511076},
{"learn":[6.65584407],"iteration":636,"passed_time":1.035212463,"remaining_time":0.5899248417},
{"learn":[6.652037543],"iteration":637,"passed_time":1.036782663,"remaining_time":0.5882685332},
{"learn":[6.650882557],"iteration":638,"passed_time":1.038257973,"remaining_time":0.5865588863},
{"learn":[6.648411176],"iteration":639,"passed_time":1.039770023,"remaining_time":0.5848706381},
{"learn":[6.644613175],"iteration":640,"passed_time":1.041288341,"remaining_time":0.5831864497},
{"learn":[6.640672451],"iteration":641,"passed_time":1.043199267,"remaining_time":0.5817217095},
{"learn":[6.637481518],"iteration":642,"passed_time":1.044875916,"remaining_time":0.5801255086},
{"learn":[6.635720518],"iteration":643,"passed_time":1.046483929,"remaining_time":0.5784911159},
{"learn":[6.635265863],"iteration":644,"passed_time":1.04831694,"remaining_time":0.5769806416},
{"learn":[6.632366261],"iteration":645,"passed_time":1.050203893,"remaining_time":0.5754987275},
{"learn":[6.630032904],"iteration":646,"passed_time":1.051993999,"remaining_time":0.5739627226},
{"learn":[6.625842137],"iteration":647,"passed_time":1.053788427,"remaining_time":0.5724282816},
{"learn":[6.624387453],"iteration":648,"passed_time":1.055481759,"remaining_time":0.5708383627},
{"learn":[6.62159092],"iteration":649,"passed_time":1.057209628,"remaining_time":0.5692667229},
{"learn":[6.61711593],"iteration":650,"passed_time":1.058774823,"remaining_time":0.5676073938},
{"learn":[6.61693096],"iteration":651,"passed_time":1.060357918,"remaining_time":0.5659579072},
{"learn":[6.6149049],"iteration":652,"passed_time":1.061949637,"remaining_time":0.5643132067},
{"learn":[6.611664989],"iteration":653,"passed_time":1.063656703,"remaining_time":0.5627296931},
{"learn":[6.608280632],"iteration":654,"passed_time":1.065598199,"remaining_time":0.5612692804},
{"learn":[6.607591418],"iteration":655,"passed_time":1.067248902,"remaining_time":0.5596549118},
{"learn":[6.60575783],"iteration":656,"passed_time":1.06891276,"remaining_time":0.5580473009},
{"learn":[6.604549956],"iteration":657,"passed_time":1.070483431,"remaining_time":0.5563910844},
{"learn":[6.598195882],"iteration":658,"passed_time":1.072127933,"remaining_time":0.5547733311},
{"learn":[6.595328445],"iteration":659,"passed_time":1.073756315,"remaining_time":0.5531471924},
{"learn":[6.588889851],"iteration":660,"passed_time":1.075489646,"remaining_time":0.5515748716},
{"learn":[6.585521453],"iteration":661,"passed_time":1.077128356,"remaining_time":0.5499537526},
{"learn":[6.583212239],"iteration":662,"passed_time":1.078963189,"remaining_time":0.5484322697},
{"learn":[6.577930333],"iteration":663,"passed_time":1.08067776,"remaining_time":0.5468489869},
{"learn":[6.57475678],"iteration":664,"passed_time":1.082444137,"remaining_time":0.5452914072},
{"learn":[6.574278046],"iteration":665,"passed_time":1.084251814,"remaining_time":0.5437539125},
{"learn":[6.572601302],"iteration":666,"passed_time":1.085926394,"remaining_time":0.5421491591},
{"learn":[6.568220161],"iteration":667,"passed_time":1.087674692,"remaining_time":0.5405808349},
{"learn":[6.56359069],"iteration":668,"passed_time":1.089343295,"remaining_time":0.5389725423},
{"learn":[6.561402963],"iteration":669,"passed_time":1.09119141,"remaining_time":0.5374524857},
{"learn":[6.559079983],"iteration":670,"passed_time":1.092997322,"remaining_time":0.5359107583},
{"learn":[6.559005021],"iteration":671,"passed_time":1.094726528,"remaining_time":0.5343308054},
{"learn":[6.558921803],"iteration":672,"passed_time":1.096752753,"remaining_time":0.5328947256},
{"learn":[6.555873678],"iteration":673,"passed_time":1.098537323,"remaining_time":0.5313400108},
{"learn":[6.551806084],"iteration":674,"passed_time":1.100341284,"remaining_time":0.5297939517},
{"learn":[6.548447542],"iteration":675,"passed_time":1.102011453,"remaining_time":0.5281830042},
{"learn":[6.547492369],"iteration":676,"passed_time":1.103613521,"remaining_time":0.5265393906},
{"learn":[6.54504203],"iteration":677,"passed_time":1.105485339,"remaining_time":0.5250240104},
{"learn":[6.544681175],"iteration":678,"passed_time":1.106963611,"remaining_time":0.5233215304},
{"learn":[6.542574951],"iteration":679,"passed_time":1.108529131,"remaining_time":0.5216607675},
{"learn":[6.536820661],"iteration":680,"passed_time":1.110417747,"remaining_time":0.5201516319},
{"learn":[6.536572562],"iteration":681,"passed_time":1.112325908,"remaining_time":0.5186504966},
{"learn":[6.536520339],"iteration":682,"passed_time":1.114074222,"remaining_time":0.51707398},
{"learn":[6.533612422],"iteration":683,"passed_time":1.115815473,"remaining_time":0.5154936982},
{"learn":[6.532864429],"iteration":684,"passed_time":1.117504871,"remaining_time":0.5138891013},
{"learn":[6.530905887],"iteration":685,"passed_time":1.119373632,"remaining_time":0.5123663565},
{"learn":[6.528592125],"iteration":686,"passed_time":1.121241736,"remaining_time":0.5108423048},
{"learn":[6.528026112],"iteration":687,"passed_time":1.122861887,"remaining_time":0.5092048094},
{"learn":[6.527039165],"iteration":688,"passed_time":1.124462932,"remaining_time":0.5075587399},
{"learn":[6.524729535],"iteration":689,"passed_time":1.12619292,"remaining_time":0.5059707321},
{"learn":[6.522549229],"iteration":690,"passed_time":1.127902194,"remaining_time":0.5043730505},
{"learn":[6.517822022],"iteration":691,"passed_time":1.12949657,"remaining_time":0.5027239067},
{"learn":[6.51528889],"iteration":692,"passed_time":1.131004194,"remaining_time":0.5010364902},
{"learn":[6.511158243],"iteration":693,"passed_time":1.132600638,"remaining_time":0.499388754},
{"learn":[6.510749703],"iteration":694,"passed_time":1.134048166,"remaining_time":0.4976758138},
{"learn":[6.510480201],"iteration":695,"passed_time":1.135452509,"remaining_time":0.4959447739},
{"learn":[6.506799537],"iteration":696,"passed_time":1.136890571,"remaining_time":0.4942293301},
{"learn":[6.504837527],"iteration":697,"passed_time":1.138406487,"remaining_time":0.4925483656},
{"learn":[6.502459082],"iteration":698,"passed_time":1.139896871,"remaining_time":0.4908568786},
{"learn":[6.50051943],"iteration":699,"passed_time":1.141377772,"remaining_time":0.4891619022},
{"learn":[6.493165334],"iteration":700,"passed_time":1.142921447,"remaining_time":0.4874943118},
{"learn":[6.491407413],"iteration":701,"passed_time":1.144376114,"remaining_time":0.4857892906},
{"learn":[6.488977152],"iteration":702,"passed_time":1.145818194,"remaining_time":0.4840796639},
{"learn":[6.485436104],"iteration":703,"passed_time":1.147401146,"remaining_time":0.4824300273},
{"learn":[6.482515424],"iteration":704,"passed_time":1.148878775,"remaining_time":0.4807365087},
{"learn":[6.476560243],"iteration":705,"passed_time":1.150358171,"remaining_time":0.4790443375},
{"learn":[6.476299404],"iteration":706,"passed_time":1.151789837,"remaining_time":0.4773329876},
{"learn":[6.475748269],"iteration":707,"passed_time":1.153258242,"remaining_time":0.4756375802},
{"learn":[6.474298662],"iteration":708,"passed_time":1.15475499,"remaining_time":0.4739544457},
{"learn":[6.471496046],"iteration":709,"passed_time":1.156216313,"remaining_time":0.4722573673},
{"learn":[6.46788187],"iteration":710,"passed_time":1.157740242,"remaining_time":0.4705863992},
{"learn":[6.466116108],"iteration":711,"passed_time":1.159203806,"remaining_time":0.4688914272},
{"learn":[6.465396996],"iteration":712,"passed_time":1.160604472,"remaining_time":0.4671717859},
{"learn":[6.463627049],"iteration":713,"passed_time":1.16203887,"remaining_time":0.46546655},
{"learn":[6.461521523],"iteration":714,"passed_time":1.163507342,"remaining_time":0.4637756538},
{"learn":[6.46052164],"iteration":715,"passed_time":1.164943235,"remaining_time":0.4620724565},
{"learn":[6.46024601],"iteration":716,"passed_time":1.166348996,"remaining_time":0.4603581115},
{"learn":[6.459154586],"iteration":717,"passed_time":1.167851762,"remaining_time":0.4586827256},
{"learn":[6.456886442],"iteration":718,"passed_time":1.169298297,"remaining_time":0.4569858434},
{"learn":[6.453623988],"iteration":719,"passed_time":1.170753756,"remaining_time":0.4552931273},
{"learn":[6.451379381],"iteration":720,"passed_time":1.172254212,"remaining_time":0.4536184817},
{"learn":[6.450018591],"iteration":721,"passed_time":1.173778198,"remaining_time":0.4519533782},
{"learn":[6.449695018],"iteration":722,"passed_time":1.175251646,"remaining_time":0.4502693028},
{"learn":[6.447745979],"iteration":723,"passed_time":1.176818211,"remaining_time":0.4486213069},
{"learn":[6.446652559],"iteration":724,"passed_time":1.178299982,"remaining_time":0.4469413724},
{"learn":[6.446477425],"iteration":725,"passed_time":1.179982951,"remaining_time":0.4453379182},
{"learn":[6.44607137],"iteration":726,"passed_time":1.181515279,"remaining_time":0.4436776769},
{"learn":[6.438785863],"iteration":727,"passed_time":1.183055532,"remaining_time":0.4420207481},
{"learn":[6.438048126],"iteration":728,"passed_time":1.184547278,"remaining_time":0.4403461075},
{"learn":[6.437253072],"iteration":729,"passed_time":1.186093302,"remaining_time":0.4386920432},
{"learn":[6.435806261],"iteration":730,"passed_time":1.187844359,"remaining_time":0.4371137243},
{"learn":[6.435262319],"iteration":731,"passed_time":1.189513615,"remaining_time":0.4355049846},
{"learn":[6.432689771],"iteration":732,"passed_time":1.191229314,"remaining_time":0.433912997},
{"learn":[6.430002586],"iteration":733,"passed_time":1.192807275,"remaining_time":0.4322707565},
{"learn":[6.42793635],"iteration":734,"passed_time":1.194480033,"remaining_time":0.4306628689},
{"learn":[6.426601198],"iteration":735,"passed_time":1.196174239,"remaining_time":0.4290624986},
{"learn":[6.425971062],"iteration":736,"passed_time":1.19780497,"remaining_time":0.4274392226},
{"learn":[6.421667206],"iteration":737,"passed_time":1.19955379,"remaining_time":0.4258578496},
{"learn":[6.418450861],"iteration":738,"passed_time":1.201433785,"remaining_time":0.4243223518},
{"learn":[6.416818705],"iteration":739,"passed_time":1.202994533,"remaining_time":0.4226737548},
{"learn":[6.413194573],"iteration":740,"passed_time":1.204761445,"remaining_time":0.421097455},
{"learn":[6.411083395],"iteration":741,"passed_time":1.206474361,"remaining_time":0.4195018669},
{"learn":[6.409812236],"iteration":742,"passed_time":1.207979629,"remaining_time":0.4178341381},
{"learn":[6.404084101],"iteration":743,"passed_time":1.209447126,"remaining_time":0.4161538499},
{"learn":[6.404007967],"iteration":744,"passed_time":1.210860269,"remaining_time":0.4144555283},
{"learn":[6.400968548],"iteration":745,"passed_time":1.212546789,"remaining_time":0.4128510514},
{"learn":[6.400879764],"iteration":746,"passed_time":1.214094354,"remaining_time":0.4111992927},
{"learn":[6.397614105],"iteration":747,"passed_time":1.215691445,"remaining_time":0.4095644974},
{"learn":[6.393258561],"iteration":748,"passed_time":1.217231904,"remaining_time":0.4079108251},
{"learn":[6.39229128],"iteration":749,"passed_time":1.218777458,"remaining_time":0.4062591526},
{"learn":[6.390513528],"iteration":750,"passed_time":1.22031226,"remaining_time":0.4046041981},
{"learn":[6.388497613],"iteration":751,"passed_time":1.221847726,"remaining_time":0.4029497821},
{"learn":[6.386681303],"iteration":752,"passed_time":1.223377399,"remaining_time":0.4012937817},
{"learn":[6.386015213],"iteration":753,"passed_time":1.224816112,"remaining_time":0.3996084398},
{"learn":[6.3826004],"iteration":754,"passed_time":1.226270361,"remaining_time":0.3979287926},
{"learn":[6.380928314],"iteration":755,"passed_time":1.227876549,"remaining_time":0.3962987803},
{"learn":[6.376975551],"iteration":756,"passed_time":1.229420313,"remaining_time":0.3946487927},
{"learn":[6.37244265],"iteration":757,"passed_time":1.23088837,"remaining_time":0.3929749149},
{"learn":[6.371192082],"iteration":758,"passed_time":1.232382553,"remaining_time":0.3913098752},
{"learn":[6.369130679],"iteration":759,"passed_time":1.233844731,"remaining_time":0.3896351784},
{"learn":[6.36867308],"iteration":760,"passed_time":1.235276594,"remaining_time":0.3879515189},
{"learn":[6.367832471],"iteration":761,"passed_time":1.236789421,"remaining_time":0.3862938086},
{"learn":[6.365028046],"iteration":762,"passed_time":1.238279279,"remaining_time":0.3846293434},
{"learn":[6.364602397],"iteration":763,"passed_time":1.239726027,"remaining_time":0.3829520189},
{"learn":[6.359787496],"iteration":764,"passed_time":1.241212876,"remaining_time":0.3812876156},
{"learn":[6.354404769],"iteration":765,"passed_time":1.242680114,"remaining_time":0.3796176848},
{"learn":[6.353929628],"iteration":766,"passed_time":1.244913579,"remaining_time":0.378181048},
{"learn":[6.351023126],"iteration":767,"passed_time":1.246642617,"remaining_time":0.3765899573},
{"learn":[6.348216444],"iteration":768,"passed_time":1.248424907,"remaining_time":0.375014504},
{"learn":[6.345619938],"iteration":769,"passed_time":1.250385797,"remaining_time":0.3734918613},
{"learn":[6.342176423],"iteration":770,"passed_time":1.252392143,"remaining_time":0.3719815834},
{"learn":[6.341389123],"iteration":771,"passed_time":1.254868305,"remaining_time":0.370608774},
{"learn":[6.33848174],"iteration":772,"passed_time":1.256778471,"remaining_time":0.3690668989},
{"learn":[6.337479266],"iteration":773,"passed_time":1.258494259,"remaining_time":0.3674673159},
{"learn":[6.337316147],"iteration":774,"passed_time":1.26013607,"remaining_time":0.3658459559},
{"learn":[6.337243545],"iteration":775,"passed_time":1.261729196,"remaining_time":0.3642104895},
{"learn":[6.334998351],"iteration":776,"passed_time":1.263423599,"remaining_time":0.362604199},
{"learn":[6.332803773],"iteration":777,"passed_time":1.265079661,"remaining_time":0.3609867413},
{"learn":[6.331058739],"iteration":778,"passed_time":1.266862323,"remaining_time":0.3594051006},
{"learn":[6.329752885],"iteration":779,"passed_time":1.268553301,"remaining_time":0.3577970849},
{"learn":[6.328291479],"iteration":780,"passed_time":1.270254719,"remaining_time":0.3561917842},
{"learn":[6.323304202],"iteration":781,"passed_time":1.272051788,"remaining_time":0.3546129025},
{"learn":[6.323105331],"iteration":782,"passed_time":1.273701458,"remaining_time":0.3529926135},
{"learn":[6.323047979],"iteration":783,"passed_time":1.275382706,"remaining_time":0.3513809496},
{"learn":[6.321497616],"iteration":784,"passed_time":1.277188766,"remaining_time":0.3498032925},
{"learn":[6.318390674],"iteration":785,"passed_time":1.27890114,"remaining_time":0.348199547},
{"learn":[6.315097156],"iteration":786,"passed_time":1.280594012,"remaining_time":0.3465902473},
{"learn":[6.312448551],"iteration":787,"passed_time":1.2822542,"remaining_time":0.3449719422},
{"learn":[6.308955841],"iteration":788,"passed_time":1.283981002,"remaining_time":0.3433713454},
{"learn":[6.30728638],"iteration":789,"passed_time":1.285930173,"remaining_time":0.3418295396},
{"learn":[6.30628024],"iteration":790,"passed_time":1.287794734,"remaining_time":0.3402643482},
{"learn":[6.304854848],"iteration":791,"passed_time":1.289659253,"remaining_time":0.3386983897},
{"learn":[6.304157935],"iteration":792,"passed_time":1.291611366,"remaining_time":0.3371545432},
{"learn":[6.300047969],"iteration":793,"passed_time":1.293427198,"remaining_time":0.3355743109},
{"learn":[6.296946997],"iteration":794,"passed_time":1.295215582,"remaining_time":0.3339864078},
{"learn":[6.291350142],"iteration":795,"passed_time":1.297261614,"remaining_time":0.3324640316},
{"learn":[6.28967046],"iteration":796,"passed_time":1.299305366,"remaining_time":0.3309397607},
{"learn":[6.289413375],"iteration":797,"passed_time":1.301045468,"remaining_time":0.3293373239},
{"learn":[6.287808345],"iteration":798,"passed_time":1.302733908,"remaining_time":0.3277215464},
{"learn":[6.285016512],"iteration":799,"passed_time":1.304469485,"remaining_time":0.3261173712},
{"learn":[6.284946552],"iteration":800,"passed_time":1.306130395,"remaining_time":0.3244943178},
{"learn":[6.281392384],"iteration":801,"passed_time":1.308046439,"remaining_time":0.3229341581},
{"learn":[6.276912983],"iteration":802,"passed_time":1.310080678,"remaining_time":0.3214021092},
{"learn":[6.274486406],"iteration":803,"passed_time":1.312055307,"remaining_time":0.3198542789},
{"learn":[6.270511026],"iteration":804,"passed_time":1.313861618,"remaining_time":0.3182646156},
{"learn":[6.265926539],"iteration":805,"passed_time":1.315713448,"remaining_time":0.3166853708},
{"learn":[6.265702258],"iteration":806,"passed_time":1.31752555,"remaining_time":0.3150959493},
{"learn":[6.261515186],"iteration":807,"passed_time":1.319449635,"remaining_time":0.3135325865},
{"learn":[6.259525185],"iteration":808,"passed_time":1.321499878,"remaining_time":0.3119981171},
{"learn":[6.258955308],"iteration":809,"passed_time":1.323611813,"remaining_time":0.310476845},
{"learn":[6.25498764],"iteration":810,"passed_time":1.325297156,"remaining_time":0.3088547009},
{"learn":[6.252703508],"iteration":811,"passed_time":1.327149003,"remaining_time":0.3072709515},
{"learn":[6.252576554],"iteration":812,"passed_time":1.328818365,"remaining_time":0.3056445685},
{"learn":[6.252296087],"iteration":813,"passed_time":1.330983258,"remaining_time":0.3041313095},
{"learn":[6.248695586],"iteration":814,"passed_time":1.333035876,"remaining_time":0.3025909657},
{"learn":[6.246655164],"iteration":815,"passed_time":1.335395677,"remaining_time":0.301118633},
{"learn":[6.245562167],"iteration":816,"passed_time":1.337803563,"remaining_time":0.2996548984},
{"learn":[6.241366758],"iteration":817,"passed_time":1.339994499,"remaining_time":0.2981405855},
{"learn":[6.240071175],"iteration":818,"passed_time":1.342249692,"remaining_time":0.2966388208},
{"learn":[6.239252438],"iteration":819,"passed_time":1.344223628,"remaining_time":0.2950734793},
{"learn":[6.238823721],"iteration":820,"passed_time":1.346124783,"remaining_time":0.2934912741},
{"learn":[6.237441052],"iteration":821,"passed_time":1.347977925,"remaining_time":0.2918978961},
{"learn":[6.235384384],"iteration":822,"passed_time":1.350004061,"remaining_time":0.2903410921},
{"learn":[6.233375007],"iteration":823,"passed_time":1.351824939,"remaining_time":0.2887393073},
{"learn":[6.2307155],"iteration":824,"passed_time":1.353691146,"remaining_time":0.2871466067},
{"learn":[6.228814424],"iteration":825,"passed_time":1.355611839,"remaining_time":0.2855647215},
{"learn":[6.228265273],"iteration":826,"passed_time":1.357569622,"remaining_time":0.2839897758},
{"learn":[6.223766855],"iteration":827,"passed_time":1.359494411,"remaining_time":0.2824070516},
{"learn":[6.22267024],"iteration":828,"passed_time":1.361258301,"remaining_time":0.2807903129},
{"learn":[6.21788839],"iteration":829,"passed_time":1.362944269,"remaining_time":0.2791572599},
{"learn":[6.213137055],"iteration":830,"passed_time":1.364763588,"remaining_time":0.2775511989},
{"learn":[6.210695969],"iteration":831,"passed_time":1.36653583,"remaining_time":0.2759351195},
{"learn":[6.210113813],"iteration":832,"passed_time":1.368402109,"remaining_time":0.2743375177},
{"learn":[6.209081128],"iteration":833,"passed_time":1.370331781,"remaining_time":0.2727518893},
{"learn":[6.207242111],"iteration":834,"passed_time":1.372208836,"remaining_time":0.2711550395},
{"learn":[6.20386916],"iteration":835,"passed_time":1.373913176,"remaining_time":0.2695236373},
{"learn":[6.202511314],"iteration":836,"passed_time":1.375670413,"remaining_time":0.2679023624},
{"learn":[6.199920371],"iteration":837,"passed_time":1.377437372,"remaining_time":0.2662826422},
{"learn":[6.199420294],"iteration":838,"passed_time":1.379319094,"remaining_time":0.2646845938},
{"learn":[6.199148274],"iteration":839,"passed_time":1.381085219,"remaining_time":0.2630638512},
{"learn":[6.195089434],"iteration":840,"passed_time":1.383032521,"remaining_time":0.2614770164},
{"learn":[6.193277426],"iteration":841,"passed_time":1.385080736,"remaining_time":0.2599082616},
{"learn":[6.193031884],"iteration":842,"passed_time":1.387144452,"remaining_time":0.2583412562},
{"learn":[6.188300253],"iteration":843,"passed_time":1.389176894,"remaining_time":0.2567672933},
{"learn":[6.185610319],"iteration":844,"passed_time":1.391268471,"remaining_time":0.2552030923},
{"learn":[6.179512388],"iteration":845,"passed_time":1.393252015,"remaining_time":0.2536179792},
{"learn":[6.177669016],"iteration":846,"passed_time":1.395280395,"remaining_time":0.2520400242},
{"learn":[6.172425871],"iteration":847,"passed_time":1.397139016,"remaining_time":0.2504305783},
{"learn":[6.171252463],"iteration":848,"passed_time":1.398962319,"remaining_time":0.2488142641},
{"learn":[6.168814153],"iteration":849,"passed_time":1.400919439,"remaining_time":0.2472210775},
{"learn":[6.165592421],"iteration":850,"passed_time":1.402791471,"remaining_time":0.2456121378},
{"learn":[6.164323208],"iteration":851,"passed_time":1.404538631,"remaining_time":0.243980889},
{"learn":[6.162821032],"iteration":852,"passed_time":1.406404685,"remaining_time":0.2423698577},
{"learn":[6.158619792],"iteration":853,"passed_time":1.408216901,"remaining_time":0.2407490252},
{"learn":[6.15610394],"iteration":854,"passed_time":1.410087712,"remaining_time":0.2391376822},
{"learn":[6.15466209],"iteration":855,"passed_time":1.411859519,"remaining_time":0.237509078},
{"learn":[6.152690221],"iteration":856,"passed_time":1.413665372,"remaining_time":0.2358858205},
{"learn":[6.151251267],"iteration":857,"passed_time":1.415435437,"remaining_time":0.2342562146},
{"learn":[6.148247967],"iteration":858,"passed_time":1.417223887,"remaining_time":0.2326292993},
{"learn":[6.145076258],"iteration":859,"passed_time":1.419218848,"remaining_time":0.2310356265},
{"learn":[6.142529901],"iteration":860,"passed_time":1.420830369,"remaining_time":0.2293791188},
{"learn":[6.142191595],"iteration":861,"passed_time":1.422455008,"remaining_time":0.2277248157},
{"learn":[6.140262771],"iteration":862,"passed_time":1.424091905,"remaining_time":0.2260725273},
{"learn":[6.136939501],"iteration":863,"passed_time":1.425732328,"remaining_time":0.2244208295},
{"learn":[6.133007401],"iteration":864,"passed_time":1.427329743,"remaining_time":0.2227624455},
{"learn":[6.132942022],"iteration":865,"passed_time":1.429194877,"remaining_time":0.2211456276},
{"learn":[6.130766305],"iteration":866,"passed_time":1.431165829,"remaining_time":0.2195444698},
{"learn":[6.13020853],"iteration":867,"passed_time":1.433832485,"remaining_time":0.218048258},
{"learn":[6.126709654],"iteration":868,"passed_time":1.435773212,"remaining_time":0.2164399204},
{"learn":[6.126410371],"iteration":869,"passed_time":1.437466303,"remaining_time":0.2147938154},
{"learn":[6.12615154],"iteration":870,"passed_time":1.43910147,"remaining_time":0.2131390237},
{"learn":[6.126065979],"iteration":871,"passed_time":1.44151979,"remaining_time":0.2115992352},
{"learn":[6.125780932],"iteration":872,"passed_time":1.443628005,"remaining_time":0.2100123215},
{"learn":[6.123162194],"iteration":873,"passed_time":1.445435037,"remaining_time":0.2083807949},
{"learn":[6.119197418],"iteration":874,"passed_time":1.447396677,"remaining_time":0.2067709538},
{"learn":[6.116913034],"iteration":875,"passed_time":1.449417239,"remaining_time":0.2051686502},
{"learn":[6.114761355],"iteration":876,"passed_time":1.451424099,"remaining_time":0.2035634711},
{"learn":[6.113320576],"iteration":877,"passed_time":1.453354956,"remaining_time":0.2019468162},
{"learn":[6.109736225],"iteration":878,"passed_time":1.455405837,"remaining_time":0.2003459685},
{"learn":[6.109387385],"iteration":879,"passed_time":1.457156527,"remaining_time":0.1987031627},
{"learn":[6.107420073],"iteration":880,"passed_time":1.459062703,"remaining_time":0.1970811142},
{"learn":[6.103301203],"iteration":881,"passed_time":1.460880951,"remaining_time":0.1954466579},
{"learn":[6.10066772],"iteration":882,"passed_time":1.462760437,"remaining_time":0.1938198994},
{"learn":[6.099347242],"iteration":883,"passed_time":1.464794484,"remaining_time":0.1922128508},
{"learn":[6.099235434],"iteration":884,"passed_time":1.466696065,"remaining_time":0.1905876243},
{"learn":[6.09753894],"iteration":885,"passed_time":1.468699104,"remaining_time":0.1889748282},
{"learn":[6.093073878],"iteration":886,"passed_time":1.470518639,"remaining_time":0.1873377747},
{"learn":[6.092865483],"iteration":887,"passed_time":1.472211535,"remaining_time":0.1856843378},
{"learn":[6.091938729],"iteration":888,"passed_time":1.473947241,"remaining_time":0.1840361572},
{"learn":[6.087174832],"iteration":889,"passed_time":1.475909822,"remaining_time":0.1824158207},
{"learn":[6.086373739],"iteration":890,"passed_time":1.477758192,"remaining_time":0.180780744},
{"learn":[6.086204079],"iteration":891,"passed_time":1.479606923,"remaining_time":0.1791452328},
{"learn":[6.084441184],"iteration":892,"passed_time":1.48156967,"remaining_time":0.1775229056},
{"learn":[6.082719717],"iteration":893,"passed_time":1.48338223,"remaining_time":0.1758820093},
{"learn":[6.08012998],"iteration":894,"passed_time":1.485363685,"remaining_time":0.1742605441},
{"learn":[6.076400493],"iteration":895,"passed_time":1.487070231,"remaining_time":0.1726063661},
{"learn":[6.072241143],"iteration":896,"passed_time":1.488790902,"remaining_time":0.1709536933},
{"learn":[6.072176852],"iteration":897,"passed_time":1.490354648,"remaining_time":0.1692830447},
{"learn":[6.069795746],"iteration":898,"passed_time":1.492212927,"remaining_time":0.1676457237},
{"learn":[6.066731439],"iteration":899,"passed_time":1.494426825,"remaining_time":0.166047425},
{"learn":[6.061915918],"iteration":900,"passed_time":1.49657696,"remaining_time":0.1644407536},
{"learn":[6.060894541],"iteration":901,"passed_time":1.49851046,"remaining_time":0.1628093404},
{"learn":[6.058039288],"iteration":902,"passed_time":1.500276764,"remaining_time":0.161159298},
{"learn":[6.055594921],"iteration":903,"passed_time":1.501964071,"remaining_time":0.1595006093},
{"learn":[6.052796774],"iteration":904,"passed_time":1.503672151,"remaining_time":0.157844038},
{"learn":[6.049959392],"iteration":905,"passed_time":1.505538851,"remaining_time":0.1562038101},
{"learn":[6.04828721],"iteration":906,"passed_time":1.507232,"remaining_time":0.1545452878},
{"learn":[6.042921407],"iteration":907,"passed_time":1.50905838,"remaining_time":0.1529001883},
{"learn":[6.040929677],"iteration":908,"passed_time":1.510915484,"remaining_time":0.1512577658},
{"learn":[6.038816901],"iteration":909,"passed_time":1.512529801,"remaining_time":0.1495908594},
{"learn":[6.034348493],"iteration":910,"passed_time":1.51411019,"remaining_time":0.147920754},
{"learn":[6.030473169],"iteration":911,"passed_time":1.515825741,"remaining_time":0.1462638873},
{"learn":[6.027959216],"iteration":912,"passed_time":1.517591227,"remaining_time":0.1446116503},
{"learn":[6.025417645],"iteration":913,"passed_time":1.519224203,"remaining_time":0.1429466975},
{"learn":[6.023063138],"iteration":914,"passed_time":1.52079108,"remaining_time":0.1412756741},
{"learn":[6.021588872],"iteration":915,"passed_time":1.522361769,"remaining_time":0.1396052277},
{"learn":[6.020767647],"iteration":916,"passed_time":1.524178936,"remaining_time":0.1379573083},
{"learn":[6.020476619],"iteration":917,"passed_time":1.525932439,"remaining_time":0.1363033334},
{"learn":[6.013477786],"iteration":918,"passed_time":1.527586302,"remaining_time":0.1346403596},
{"learn":[6.00875322],"iteration":919,"passed_time":1.529118582,"remaining_time":0.1329668332},
{"learn":[6.005337551],"iteration":920,"passed_time":1.530724719,"remaining_time":0.1312999487},
{"learn":[6.003715444],"iteration":921,"passed_time":1.532316273,"remaining_time":0.1296319624},
{"learn":[6.002309597],"iteration":922,"passed_time":1.533979424,"remaining_time":0.1279701144},
{"learn":[6.000888461],"iteration":923,"passed_time":1.535538605,"remaining_time":0.1262997121},
{"learn":[5.998409048],"iteration":924,"passed_time":1.53707007,"remaining_time":0.124627303},
{"learn":[5.998023433],"iteration":925,"passed_time":1.538563363,"remaining_time":0.1229521478},
{"learn":[5.997693132],"iteration":926,"passed_time":1.540378064,"remaining_time":0.1213026954},
{"learn":[5.996234303],"iteration":927,"passed_time":1.542212127,"remaining_time":0.1196543892},
{"learn":[5.993411147],"iteration":928,"passed_time":1.543717502,"remaining_time":0.1179805626},
{"learn":[5.992300492],"iteration":929,"passed_time":1.545175085,"remaining_time":0.116303501},
{"learn":[5.988246159],"iteration":930,"passed_time":1.546727326,"remaining_time":0.1146339264},
{"learn":[5.984216977],"iteration":931,"passed_time":1.548244769,"remaining_time":0.1129620647},
{"learn":[5.981395557],"iteration":932,"passed_time":1.549708475,"remaining_time":0.1112866751},
{"learn":[5.980069175],"iteration":933,"passed_time":1.551161425,"remaining_time":0.1096109786},
{"learn":[5.978033843],"iteration":934,"passed_time":1.552621412,"remaining_time":0.1079362479},
{"learn":[5.975984641],"iteration":935,"passed_time":1.554131035,"remaining_time":0.1062653699},
{"learn":[5.975859412],"iteration":936,"passed_time":1.555591736,"remaining_time":0.1045915468},
{"learn":[5.973810427],"iteration":937,"passed_time":1.557057315,"remaining_time":0.1029185006},
{"learn":[5.972183313],"iteration":938,"passed_time":1.55858063,"remaining_time":0.1012496469},
{"learn":[5.968642113],"iteration":939,"passed_time":1.560042385,"remaining_time":0.0995771735},
{"learn":[5.963443481],"iteration":940,"passed_time":1.561539137,"remaining_time":0.09790734225},
{"learn":[5.963340899],"iteration":941,"passed_time":1.562910178,"remaining_time":0.09623013837},
{"learn":[5.961607795],"iteration":942,"passed_time":1.564360137,"remaining_time":0.09455835399},
{"learn":[5.957988537],"iteration":943,"passed_time":1.565781372,"remaining_time":0.09288533561},
{"learn":[5.954983525],"iteration":944,"passed_time":1.567195146,"remaining_time":0.09121241593},
{"learn":[5.952775096],"iteration":945,"passed_time":1.568650493,"remaining_time":0.08954241713},
{"learn":[5.950138957],"iteration":946,"passed_time":1.570129542,"remaining_time":0.08787419824},
{"learn":[5.949000435],"iteration":947,"passed_time":1.571799921,"remaining_time":0.08621687328},
{"learn":[5.944968733],"iteration":948,"passed_time":1.573413007,"remaining_time":0.08455644189},
{"learn":[5.944560847],"iteration":949,"passed_time":1.575165472,"remaining_time":0.08290344587},
{"learn":[5.943299391],"iteration":950,"passed_time":1.576806245,"remaining_time":0.08124448582},
{"learn":[5.941709056],"iteration":951,"passed_time":1.578360718,"remaining_time":0.07958121267},
{"learn":[5.940328673],"iteration":952,"passed_time":1.579919131,"remaining_time":0.07791836216},
{"learn":[5.938285156],"iteration":953,"passed_time":1.581423049,"remaining_time":0.07625310297},
{"learn":[5.932998589],"iteration":954,"passed_time":1.582906131,"remaining_time":0.07458719991},
{"learn":[5.932507651],"iteration":955,"passed_time":1.584312387,"remaining_time":0.07291814335},
{"learn":[5.929992638],"iteration":956,"passed_time":1.58583549,"remaining_time":0.07125488616},
{"learn":[5.929646764],"iteration":957,"passed_time":1.587333868,"remaining_time":0.06959083763},
{"learn":[5.928110572],"iteration":958,"passed_time":1.588876176,"remaining_time":0.06792901274},
{"learn":[5.927201781],"iteration":959,"passed_time":1.590407476,"remaining_time":0.06626697816},
{"learn":[5.925407674],"iteration":960,"passed_time":1.591910906,"remaining_time":0.06460408464},
{"learn":[5.923154762],"iteration":961,"passed_time":1.593434427,"remaining_time":0.06294231624},
{"learn":[5.920646765],"iteration":962,"passed_time":1.594923062,"remaining_time":0.0612794946},
{"learn":[5.920551967],"iteration":963,"passed_time":1.596348062,"remaining_time":0.05961465791},
{"learn":[5.92034114],"iteration":964,"passed_time":1.598139294,"remaining_time":0.05796360134},
{"learn":[5.920279843],"iteration":965,"passed_time":1.599559263,"remaining_time":0.05629918731},
{"learn":[5.919628726],"iteration":966,"passed_time":1.601140186,"remaining_time":0.05464077161},
{"learn":[5.915339365],"iteration":967,"passed_time":1.602992468,"remaining_time":0.05299148653},
{"learn":[5.912937027],"iteration":968,"passed_time":1.604729375,"remaining_time":0.05133809147},
{"learn":[5.912767576],"iteration":969,"passed_time":1.606130761,"remaining_time":0.04967414726},
{"learn":[5.912676504],"iteration":970,"passed_time":1.607584661,"remaining_time":0.04801231221},
{"learn":[5.910279147],"iteration":971,"passed_time":1.609298555,"remaining_time":0.04635839459},
{"learn":[5.905766219],"iteration":972,"passed_time":1.610791769,"remaining_time":0.04469822997},
{"learn":[5.903713617],"iteration":973,"passed_time":1.612284704,"remaining_time":0.04303840071},
{"learn":[5.902848103],"iteration":974,"passed_time":1.613750868,"remaining_time":0.04137822738},
{"learn":[5.901292871],"iteration":975,"passed_time":1.615272883,"remaining_time":0.03971982499},
{"learn":[5.897887948],"iteration":976,"passed_time":1.616944942,"remaining_time":0.03806523406},
{"learn":[5.896023765],"iteration":977,"passed_time":1.618806368,"remaining_time":0.03641486717},
{"learn":[5.892950326],"iteration":978,"passed_time":1.620386003,"remaining_time":0.03475802458},
{"learn":[5.892879002],"iteration":979,"passed_time":1.621818064,"remaining_time":0.03309832783},
{"learn":[5.889526062],"iteration":980,"passed_time":1.623342102,"remaining_time":0.0314408766},
{"learn":[5.887081147],"iteration":981,"passed_time":1.625136817,"remaining_time":0.02978865855},
{"learn":[5.886905984],"iteration":982,"passed_time":1.626660326,"remaining_time":0.02813146036},
{"learn":[5.886852248],"iteration":983,"passed_time":1.628199681,"remaining_time":0.02647479156},
{"learn":[5.885022167],"iteration":984,"passed_time":1.629893655,"remaining_time":0.02482071555},
{"learn":[5.881989567],"iteration":985,"passed_time":1.631522492,"remaining_time":0.02316563376},
{"learn":[5.879352274],"iteration":986,"passed_time":1.633267571,"remaining_time":0.02151213619},
{"learn":[5.876583016],"iteration":987,"passed_time":1.634847218,"remaining_time":0.01985644394},
{"learn":[5.87466086],"iteration":988,"passed_time":1.636560922,"remaining_time":0.01820239651},
{"learn":[5.870514394],"iteration":989,"passed_time":1.638185561,"remaining_time":0.0165473289},
{"learn":[5.867430544],"iteration":990,"passed_time":1.639780778,"remaining_time":0.0148920555},
{"learn":[5.866797069],"iteration":991,"passed_time":1.641244955,"remaining_time":0.01323584642},
{"learn":[5.863421998],"iteration":992,"passed_time":1.642723158,"remaining_time":0.01158012297},
{"learn":[5.862972296],"iteration":993,"passed_time":1.644158138,"remaining_time":0.009924495804},
{"learn":[5.862381535],"iteration":994,"passed_time":1.645665254,"remaining_time":0.008269674643},
{"learn":[5.860833985],"iteration":995,"passed_time":1.647203695,"remaining_time":0.006615275882},
{"learn":[5.857846249],"iteration":996,"passed_time":1.648981536,"remaining_time":0.004961830099},
{"learn":[5.853942521],"iteration":997,"passed_time":1.650937554,"remaining_time":0.003308492091},
{"learn":[5.853304711],"iteration":998,"passed_time":1.652567641,"remaining_time":0.001654221863},
{"learn":[5.853092527],"iteration":999,"passed_time":1.654142696,"remaining_time":0}
]}