{
"meta":{"test_sets":[],"test_metrics":[],"learn_metrics":[{"best_value":"Min","name":"MultiClass"}],"launch_mode":"Train","parameters":"","iteration_count":1000,"learn_sets":["learn"],"name":"experiment"},
"iterations":[
{"learn":[1.60207531],"iteration":0,"passed_time":0.001137795172,"remaining_time":1.136657377},
{"learn":[1.59455871],"iteration":1,"passed_time":0.002037341768,"remaining_time":1.016633542},
{"learn":[1.586359079],"iteration":2,"passed_time":0.002926757228,"remaining_time":0.9726589853},
{"learn":[1.576420815],"iteration":3,"passed_time":0.003772866523,"remaining_time":0.9394437643},
{"learn":[1.567950428],"iteration":4,"passed_time":0.004665839663,"remaining_time":0.9285020929},
{"learn":[1.558886059],"iteration":5,"passed_time":0.005550670875,"remaining_time":0.9195611416},
{"learn":[1.550017876],"iteration":6,"passed_time":0.006490643149,"remaining_time":0.9207440924},
{"learn":[1.541760249],"iteration":7,"passed_time":0.007370175752,"remaining_time":0.9139017933},
{"learn":[1.534287283],"iteration":8,"passed_time":0.008289539352,"remaining_time":0.9127703887},
{"learn":[1.526188819],"iteration":9,"passed_time":0.009192387172,"remaining_time":0.91004633},
{"learn":[1.517527359],"iteration":10,"passed_time":0.01007628027,"remaining_time":0.9059491992},
{"learn":[1.510151431],"iteration":11,"passed_time":0.01093273776,"remaining_time":0.9001287426},
{"learn":[1.502403844],"iteration":12,"passed_time":0.011886914,"remaining_time":0.9024910857},
{"learn":[1.493488195],"iteration":13,"passed_time":0.01276176572,"remaining_time":0.8987929283},
{"learn":[1.48666525],"iteration":14,"passed_time":0.0137020108,"remaining_time":0.8997653759},
{"learn":[1.479417588],"iteration":15,"passed_time":0.01457189173,"remaining_time":0.8961713413},
{"learn":[1.472897084],"iteration":16,"passed_time":0.01548225483,"remaining_time":0.8952386176},
{"learn":[1.46655494],"iteration":17,"passed_time":0.01635060966,"remaining_time":0.8920165937},
{"learn":[1.460242178],"iteration":18,"passed_time":0.01724162481,"remaining_time":0.8902123127},
{"learn":[1.45345263],"iteration":19,"passed_time":0.01811716116,"remaining_time":0.8877408968},
{"learn":[1.448174041],"iteration":20,"passed_time":0.01905981916,"remaining_time":0.8885506171},
{"learn":[1.442447296],"iteration":21,"passed_time":0.01999430847,"remaining_time":0.8888378949},
{"learn":[1.435051021],"iteration":22,"passed_time":0.02095282811,"remaining_time":0.8900396984},
{"learn":[1.428742578],"iteration":23,"passed_time":0.02184468622,"remaining_time":0.888350573},
{"learn":[1.420148781],"iteration":24,"passed_time":0.0224172489,"remaining_time":0.8742727071},
{"learn":[1.413284579],"iteration":25,"passed_time":0.02331939648,"remaining_time":0.8735804683},
{"learn":[1.407334211],"iteration":26,"passed_time":0.02421649225,"remaining_time":0.8726906281},
{"learn":[1.401290863],"iteration":27,"passed_time":0.02510922306,"remaining_time":0.8716487433},
{"learn":[1.394034927],"iteration":28,"passed_time":0.02571664371,"remaining_time":0.861064174},
{"learn":[1.388765044],"iteration":29,"passed_time":0.02662609621,"remaining_time":0.8609104441},
{"learn":[1.383677433],"iteration":30,"passed_time":0.02758614938,"remaining_time":0.862289637},
{"learn":[1.377474275],"iteration":31,"passed_time":0.02858938977,"remaining_time":0.8648290406},
{"learn":[1.372993704],"iteration":32,"passed_time":0.02952548547,"remaining_time":0.8651861954},
{"learn":[1.368074637],"iteration":33,"passed_time":0.03040334776,"remaining_time":0.8638127629},
{"learn":[1.361353672],"iteration":34,"passed_time":0.0310240469,"remaining_time":0.8553772932},
{"learn":[1.35473033],"iteration":35,"passed_time":0.03185143712,"remaining_time":0.8529107052},
{"learn":[1.349984414],"iteration":36,"passed_time":0.03276021837,"remaining_time":0.8526510891},
{"learn":[1.344275555],"iteration":37,"passed_time":0.03364761489,"remaining_time":0.8518159349},
{"learn":[1.33938148],"iteration":38,"passed_time":0.03454180713,"remaining_time":0.8511455551},
{"learn":[1.333912269],"iteration":39,"passed_time":0.03541166576,"remaining_time":0.8498799782},
{"learn":[1.328751294],"iteration":40,"passed_time":0.03632388203,"remaining_time":0.8496244603},
{"learn":[1.324010488],"iteration":41,"passed_time":0.03722757653,"remaining_time":0.8491432932},
{"learn":[1.318542133],"iteration":42,"passed_time":0.03814206077,"remaining_time":0.8488826084},
{"learn":[1.314707736],"iteration":43,"passed_time":0.03906173584,"remaining_time":0.8487049877},
{"learn":[1.310570558],"iteration":44,"passed_time":0.03999620434,"remaining_time":0.8488083365},
{"learn":[1.306590016],"iteration":45,"passed_time":0.04088032937,"remaining_time":0.8478224829},
{"learn":[1.300998632],"iteration":46,"passed_time":0.04174495183,"remaining_time":0.8464455126},
{"learn":[1.29721587],"iteration":47,"passed_time":0.04265515362,"remaining_time":0.8459938802},
{"learn":[1.291863377],"iteration":48,"passed_time":0.04352775968,"remaining_time":0.8447938664},
{"learn":[1.286761969],"iteration":49,"passed_time":0.04437767939,"remaining_time":0.8431759084},
{"learn":[1.282170416],"iteration":50,"passed_time":0.04524752613,"remaining_time":0.8419588685},
{"learn":[1.278844756],"iteration":51,"passed_time":0.04619303934,"remaining_time":0.8421346403},
{"learn":[1.27450141],"iteration":52,"passed_time":0.04709419232,"remaining_time":0.8414754741},
{"learn":[1.270851207],"iteration":53,"passed_time":0.04801491031,"remaining_time":0.8411500954},
{"learn":[1.267039043],"iteration":54,"passed_time":0.04890829824,"remaining_time":0.8403334879},
{"learn":[1.262684314],"iteration":55,"passed_time":0.04979611103,"remaining_time":0.8394201574},
{"learn":[1.259442375],"iteration":56,"passed_time":0.05072056882,"remaining_time":0.8391139718},
{"learn":[1.255883289],"iteration":57,"passed_time":0.0516278537,"remaining_time":0.8385075549},
{"learn":[1.25353197],"iteration":58,"passed_time":0.05255978514,"remaining_time":0.8382840308},
{"learn":[1.249853928],"iteration":59,"passed_time":0.05347870571,"remaining_time":0.8378330561},
{"learn":[1.246228464],"iteration":60,"passed_time":0.054384938,"remaining_time":0.8371714227},
{"learn":[1.242813793],"iteration":61,"passed_time":0.05528604415,"remaining_time":0.8364243454},
{"learn":[1.239326394],"iteration":62,"passed_time":0.05619230172,"remaining_time":0.8357489955},
{"learn":[1.235736654],"iteration":63,"passed_time":0.05709003603,"remaining_time":0.8349417769},
{"learn":[1.233282306],"iteration":64,"passed_time":0.05807092905,"remaining_time":0.8353279794},
{"learn":[1.230491529],"iteration":65,"passed_time":0.05906658355,"remaining_time":0.835881652},
{"learn":[1.225963925],"iteration":66,"passed_time":0.06000525198,"remaining_time":0.8355955239},
{"learn":[1.222747927],"iteration":67,"passed_time":0.0609324007,"remaining_time":0.8351323155},
{"learn":[1.219433565],"iteration":68,"passed_time":0.06184585689,"remaining_time":0.8344709096},
{"learn":[1.215712888],"iteration":69,"passed_time":0.06273543886,"remaining_time":0.8334851163},
{"learn":[1.21328352],"iteration":70,"passed_time":0.06364202648,"remaining_time":0.8327245437},
{"learn":[1.210005874],"iteration":71,"passed_time":0.0645569887,"remaining_time":0.8320678543},
{"learn":[1.206439076],"iteration":72,"passed_time":0.06547440695,"remaining_time":0.8314352772},
{"learn":[1.203108734],"iteration":73,"passed_time":0.06639957538,"remaining_time":0.8308919838},
{"learn":[1.2000592],"iteration":74,"passed_time":0.06731557234,"remaining_time":0.8302253922},
{"learn":[1.196895985],"iteration":75,"passed_time":0.0682347672,"remaining_time":0.829591117},
{"learn":[1.19329326],"iteration":76,"passed_time":0.06913386481,"remaining_time":0.8287085353},
{"learn":[1.189844777],"iteration":77,"passed_time":0.07006208321,"remaining_time":0.8281697528},
{"learn":[1.186892835],"iteration":78,"passed_time":0.07096773347,"remaining_time":0.8273580066},
{"learn":[1.183436601],"iteration":79,"passed_time":0.07182869418,"remaining_time":0.8260299831},
{"learn":[1.180497526],"iteration":80,"passed_time":0.07272309307,"remaining_time":0.8250928707},
{"learn":[1.1775577],"iteration":81,"passed_time":0.07364644029,"remaining_time":0.8244808803},
{"learn":[1.174102775],"iteration":82,"passed_time":0.07440092037,"remaining_time":0.8219957106},
{"learn":[1.171053954],"iteration":83,"passed_time":0.07530735561,"remaining_time":0.8212087826},
{"learn":[1.168349801],"iteration":84,"passed_time":0.0762863516,"remaining_time":0.8212001378},
{"learn":[1.166113979],"iteration":85,"passed_time":0.07721423475,"remaining_time":0.8206257042},
{"learn":[1.163258043],"iteration":86,"passed_time":0.0781227142,"remaining_time":0.819839518},
{"learn":[1.160662157],"iteration":87,"passed_time":0.07905710539,"remaining_time":0.8193190922},
{"learn":[1.15820953],"iteration":88,"passed_time":0.08000091336,"remaining_time":0.8188857536},
{"learn":[1.155014556],"iteration":89,"passed_time":0.08087658276,"remaining_time":0.8177521146},
{"learn":[1.152200656],"iteration":90,"passed_time":0.08181750058,"remaining_time":0.8172759124},
{"learn":[1.149335026],"iteration":91,"passed_time":0.08271809084,"remaining_time":0.8163915922},
{"learn":[1.146560264],"iteration":92,"passed_time":0.08362675167,"remaining_time":0.8155856319},
{"learn":[1.143907898],"iteration":93,"passed_time":0.08454089397,"remaining_time":0.8148303185},
{"learn":[1.140874551],"iteration":94,"passed_time":0.08542560699,"remaining_time":0.8137913087},
{"learn":[1.138048453],"iteration":95,"passed_time":0.08632867038,"remaining_time":0.8129283127},
{"learn":[1.135592903],"iteration":96,"passed_time":0.08722870759,"remaining_time":0.8120363191},
{"learn":[1.133334518],"iteration":97,"passed_time":0.08813894804,"remaining_time":0.8112380727},
{"learn":[1.130933814],"iteration":98,"passed_time":0.08907107944,"remaining_time":0.8106367937},
{"learn":[1.128193987],"iteration":99,"passed_time":0.0900357451,"remaining_time":0.8103217059},
{"learn":[1.126103035],"iteration":100,"passed_time":0.09102424633,"remaining_time":0.8102059153},
{"learn":[1.123908037],"iteration":101,"passed_time":0.09196496864,"remaining_time":0.809652371},
{"learn":[1.121604575],"iteration":102,"passed_time":0.09289804856,"remaining_time":0.809024753},
{"learn":[1.119795504],"iteration":103,"passed_time":0.09386305765,"remaining_time":0.8086663429},
{"learn":[1.11757916],"iteration":104,"passed_time":0.0947703128,"remaining_time":0.8078040948},
{"learn":[1.115189271],"iteration":105,"passed_time":0.09566108711,"remaining_time":0.8068019988},
{"learn":[1.11243578],"iteration":106,"passed_time":0.09655636836,"remaining_time":0.8058395976},
{"learn":[1.110549524],"iteration":107,"passed_time":0.0975009561,"remaining_time":0.8052856744},
{"learn":[1.108277698],"iteration":108,"passed_time":0.09843517409,"remaining_time":0.8046398175},
{"learn":[1.105668166],"iteration":109,"passed_time":0.09935459864,"remaining_time":0.8038690254},
{"learn":[1.103762041],"iteration":110,"passed_time":0.1002827159,"remaining_time":0.8031651755},
{"learn":[1.100951202],"iteration":111,"passed_time":0.1011246863,"remaining_time":0.8017742982},
{"learn":[1.098126894],"iteration":112,"passed_time":0.1017482101,"remaining_time":0.7986784283},
{"learn":[1.095802292],"iteration":113,"passed_time":0.1026598035,"remaining_time":0.7978647885},
{"learn":[1.093608154],"iteration":114,"passed_time":0.1035915,"remaining_time":0.7972041524},
{"learn":[1.091909142],"iteration":115,"passed_time":0.1045078389,"remaining_time":0.7964218071},
{"learn":[1.089589145],"iteration":116,"passed_time":0.1054174327,"remaining_time":0.7955862654},
{"learn":[1.087649477],"iteration":117,"passed_time":0.106362908,"remaining_time":0.7950176681},
{"learn":[1.086113381],"iteration":118,"passed_time":0.1073577797,"remaining_time":0.7948084364},
{"learn":[1.08413353],"iteration":119,"passed_time":0.1082433699,"remaining_time":0.7937847125},
{"learn":[1.082155355],"iteration":120,"passed_time":0.1091468927,"remaining_time":0.7928935427},
{"learn":[1.079907767],"iteration":121,"passed_time":0.1100250872,"remaining_time":0.7918198902},
{"learn":[1.078216689],"iteration":122,"passed_time":0.1109361446,"remaining_time":0.7909837305},
{"learn":[1.076353753],"iteration":123,"passed_time":0.1118382751,"remaining_time":0.7900832985},
{"learn":[1.074412254],"iteration":124,"passed_time":0.1127621613,"remaining_time":0.7893351289},
{"learn":[1.072404477],"iteration":125,"passed_time":0.1136687035,"remaining_time":0.7884638643},
{"learn":[1.070428439],"iteration":126,"passed_time":0.1146020407,"remaining_time":0.7877762323},
{"learn":[1.068379526],"iteration":127,"passed_time":0.1154917096,"remaining_time":0.7867872717},
{"learn":[1.066051429],"iteration":128,"passed_time":0.1163769088,"remaining_time":0.7857696709},
{"learn":[1.064444765],"iteration":129,"passed_time":0.1172909403,"remaining_time":0.7849470622},
{"learn":[1.062733027],"iteration":130,"passed_time":0.118179686,"remaining_time":0.7839553218},
{"learn":[1.06099784],"iteration":131,"passed_time":0.1190952883,"remaining_time":0.7831417441},
{"learn":[1.059322921],"iteration":132,"passed_time":0.1200212595,"remaining_time":0.7823942256},
{"learn":[1.057275106],"iteration":133,"passed_time":0.1209132774,"remaining_time":0.781424614},
{"learn":[1.055735703],"iteration":134,"passed_time":0.1218514255,"remaining_time":0.7807517266},
{"learn":[1.054003024],"iteration":135,"passed_time":0.122766943,"remaining_time":0.7799311675},
{"learn":[1.052114769],"iteration":136,"passed_time":0.1236437565,"remaining_time":0.7788654148},
{"learn":[1.050242926],"iteration":137,"passed_time":0.1245174619,"remaining_time":0.7777829869},
{"learn":[1.048417025],"iteration":138,"passed_time":0.1254034476,"remaining_time":0.7767796285},
{"learn":[1.046791562],"iteration":139,"passed_time":0.1263005582,"remaining_time":0.7758462861},
{"learn":[1.045255979],"iteration":140,"passed_time":0.1272023713,"remaining_time":0.7749421059},
{"learn":[1.043788646],"iteration":141,"passed_time":0.1281367588,"remaining_time":0.7742347818},
{"learn":[1.042281297],"iteration":142,"passed_time":0.1290380797,"remaining_time":0.7733261142},
{"learn":[1.041005425],"iteration":143,"passed_time":0.1299443871,"remaining_time":0.77244719},
{"learn":[1.039909579],"iteration":144,"passed_time":0.1308641633,"remaining_time":0.7716473075},
{"learn":[1.038350669],"iteration":145,"passed_time":0.1317666602,"remaining_time":0.7707447112},
{"learn":[1.037206321],"iteration":146,"passed_time":0.1327003133,"remaining_time":0.7700229062},
{"learn":[1.035772563],"iteration":147,"passed_time":0.1336097702,"remaining_time":0.7691589475},
{"learn":[1.034142468],"iteration":148,"passed_time":0.1344931735,"remaining_time":0.7681455746},
{"learn":[1.032669588],"iteration":149,"passed_time":0.1353796125,"remaining_time":0.7671511377},
{"learn":[1.031311447],"iteration":150,"passed_time":0.1363076689,"remaining_time":0.7663921251},
{"learn":[1.030144949],"iteration":151,"passed_time":0.1372346883,"remaining_time":0.765625103},
{"learn":[1.028727889],"iteration":152,"passed_time":0.1381095586,"remaining_time":0.7645672948},
{"learn":[1.027525926],"iteration":153,"passed_time":0.139032879,"remaining_time":0.7637780238},
{"learn":[1.025874967],"iteration":154,"passed_time":0.1399145495,"remaining_time":0.7627599635},
{"learn":[1.024399395],"iteration":155,"passed_time":0.1408092784,"remaining_time":0.7618143013},
{"learn":[1.02347907],"iteration":156,"passed_time":0.1417285982,"remaining_time":0.7610013266},
{"learn":[1.022308592],"iteration":157,"passed_time":0.14258661,"remaining_time":0.7598602889},
{"learn":[1.020969359],"iteration":158,"passed_time":0.1434817129,"remaining_time":0.758918997},
{"learn":[1.019222929],"iteration":159,"passed_time":0.1443573146,"remaining_time":0.7578759018},
{"learn":[1.017765216],"iteration":160,"passed_time":0.1452589374,"remaining_time":0.7569704875},
{"learn":[1.016343294],"iteration":161,"passed_time":0.1461941634,"remaining_time":0.7562389439},
{"learn":[1.015243596],"iteration":162,"passed_time":0.1471176697,"remaining_time":0.755444721},
{"learn":[1.014185272],"iteration":163,"passed_time":0.1480086164,"remaining_time":0.7544829472},
{"learn":[1.012797188],"iteration":164,"passed_time":0.1489101931,"remaining_time":0.7535758259},
{"learn":[1.011342395],"iteration":165,"passed_time":0.149806498,"remaining_time":0.752642285},
{"learn":[1.010342425],"iteration":166,"passed_time":0.1507319095,"remaining_time":0.7518543748},
{"learn":[1.009375953],"iteration":167,"passed_time":0.1516763969,"remaining_time":0.7511592988},
{"learn":[1.008191119],"iteration":168,"passed_time":0.1525687463,"remaining_time":0.7502049006},
{"learn":[1.006886348],"iteration":169,"passed_time":0.1534816101,"remaining_time":0.7493513904},
{"learn":[1.005896065],"iteration":170,"passed_time":0.1544113932,"remaining_time":0.7485792105},
{"learn":[1.004568187],"iteration":171,"passed_time":0.1553129565,"remaining_time":0.7476693489},
{"learn":[1.003141188],"iteration":172,"passed_time":0.1562454232,"remaining_time":0.746907312},
{"learn":[1.002076681],"iteration":173,"passed_time":0.1571951304,"remaining_time":0.7462251592},
{"learn":[1.000706376],"iteration":174,"passed_time":0.1581080454,"remaining_time":0.7453664999},
{"learn":[0.999444565],"iteration":175,"passed_time":0.1589970528,"remaining_time":0.7443952926},
{"learn":[0.9982473708],"iteration":176,"passed_time":0.1599230865,"remaining_time":0.7435971761},
{"learn":[0.9969312648],"iteration":177,"passed_time":0.1608239941,"remaining_time":0.742681591},
{"learn":[0.9961835554],"iteration":178,"passed_time":0.1617533127,"remaining_time":0.741896479},
{"learn":[0.995291478],"iteration":179,"passed_time":0.1626944743,"remaining_time":0.7411637165},
{"learn":[0.9939849294],"iteration":180,"passed_time":0.1635539327,"remaining_time":0.7400589554},
{"learn":[0.9929002296],"iteration":181,"passed_time":0.1644487397,"remaining_time":0.7391157643},
{"learn":[0.9917344094],"iteration":182,"passed_time":0.1653988558,"remaining_time":0.7384200283},
{"learn":[0.9906728549],"iteration":183,"passed_time":0.1662771923,"remaining_time":0.7374032008},
{"learn":[0.9897542068],"iteration":184,"passed_time":0.1671893952,"remaining_time":0.7365370655},
{"learn":[0.9889778745],"iteration":185,"passed_time":0.1680903995,"remaining_time":0.7356214259},
{"learn":[0.9873913737],"iteration":186,"passed_time":0.1689548718,"remaining_time":0.7345471166},
{"learn":[0.9863322484],"iteration":187,"passed_time":0.1698898198,"remaining_time":0.7337794345},
{"learn":[0.985439869],"iteration":188,"passed_time":0.1707972645,"remaining_time":0.7328919657},
{"learn":[0.9847009571],"iteration":189,"passed_time":0.1717164757,"remaining_time":0.7320544491},
{"learn":[0.9837216596],"iteration":190,"passed_time":0.1726352454,"remaining_time":0.7312142069},
{"learn":[0.9822826744],"iteration":191,"passed_time":0.173482437,"remaining_time":0.7300719224},
{"learn":[0.9815520105],"iteration":192,"passed_time":0.174409556,"remaining_time":0.7292668999},
{"learn":[0.980631997],"iteration":193,"passed_time":0.1753112836,"remaining_time":0.7283551266},
{"learn":[0.9797215266],"iteration":194,"passed_time":0.1761892945,"remaining_time":0.7273455492},
{"learn":[0.9789240469],"iteration":195,"passed_time":0.1770997766,"remaining_time":0.7264705121},
{"learn":[0.9778630475],"iteration":196,"passed_time":0.1780019821,"remaining_time":0.725561379},
{"learn":[0.976703584],"iteration":197,"passed_time":0.178924308,"remaining_time":0.7247338132},
{"learn":[0.975899377],"iteration":198,"passed_time":0.1798927365,"remaining_time":0.724090864},
{"learn":[0.9745342786],"iteration":199,"passed_time":0.1807628932,"remaining_time":0.7230515728},
{"learn":[0.9736284456],"iteration":200,"passed_time":0.1817049744,"remaining_time":0.7222998733},
{"learn":[0.9728409277],"iteration":201,"passed_time":0.1826703529,"remaining_time":0.7216383249},
{"learn":[0.9718193995],"iteration":202,"passed_time":0.183589101,"remaining_time":0.7207907069},
{"learn":[0.9709206467],"iteration":203,"passed_time":0.1845171306,"remaining_time":0.7199786077},
{"learn":[0.9698796243],"iteration":204,"passed_time":0.1854302196,"remaining_time":0.7191074369},
{"learn":[0.968960022],"iteration":205,"passed_time":0.1873668562,"remaining_time":0.7221809894},
{"learn":[0.9677474265],"iteration":206,"passed_time":0.1883551508,"remaining_time":0.7215731138},
{"learn":[0.9668015944],"iteration":207,"passed_time":0.1892475456,"remaining_time":0.7205964235},
{"learn":[0.9658223459],"iteration":208,"passed_time":0.1901369447,"remaining_time":0.7196092021},
{"learn":[0.96505678],"iteration":209,"passed_time":0.1910815064,"remaining_time":0.7188304289},
{"learn":[0.9638094126],"iteration":210,"passed_time":0.1917005925,"remaining_time":0.7168330212},
{"learn":[0.9628425505],"iteration":211,"passed_time":0.1926070775,"remaining_time":0.715916873},
{"learn":[0.9618906241],"iteration":212,"passed_time":0.193488693,"remaining_time":0.7149089267},
{"learn":[0.9608529896],"iteration":213,"passed_time":0.1943959095,"remaining_time":0.7139961909},
{"learn":[0.9601030803],"iteration":214,"passed_time":0.19530301,"remaining_time":0.7130830831},
{"learn":[0.9594162031],"iteration":215,"passed_time":0.1962249233,"remaining_time":0.7122237957},
{"learn":[0.9586644653],"iteration":216,"passed_time":0.1971577973,"remaining_time":0.7114034807},
{"learn":[0.9578893745],"iteration":217,"passed_time":0.1980623764,"remaining_time":0.7104806346},
{"learn":[0.9570265487],"iteration":218,"passed_time":0.1989600475,"remaining_time":0.7095333202},
{"learn":[0.9562370139],"iteration":219,"passed_time":0.1998795962,"remaining_time":0.708664023},
{"learn":[0.9552461453],"iteration":220,"passed_time":0.2008108259,"remaining_time":0.7078354453},
{"learn":[0.9543961802],"iteration":221,"passed_time":0.2017937071,"remaining_time":0.7071869554},
{"learn":[0.9536342257],"iteration":222,"passed_time":0.2027204135,"remaining_time":0.7063397367},
{"learn":[0.952827269],"iteration":223,"passed_time":0.2036479168,"remaining_time":0.7054945688},
{"learn":[0.9522258156],"iteration":224,"passed_time":0.2045828491,"remaining_time":0.7046742581},
{"learn":[0.9515426161],"iteration":225,"passed_time":0.2055041908,"remaining_time":0.7038063879},
{"learn":[0.9508150002],"iteration":226,"passed_time":0.2064037203,"remaining_time":0.70286377},
{"learn":[0.949978731],"iteration":227,"passed_time":0.2073360078,"remaining_time":0.7020324474},
{"learn":[0.9493657878],"iteration":228,"passed_time":0.2082334187,"remaining_time":0.7010828203},
{"learn":[0.9486485574],"iteration":229,"passed_time":0.2093478838,"remaining_time":0.7008603067},
{"learn":[0.9479367962],"iteration":230,"passed_time":0.2102891503,"remaining_time":0.7000534916},
{"learn":[0.9473152851],"iteration":231,"passed_time":0.2111906006,"remaining_time":0.6991137123},
{"learn":[0.9465052802],"iteration":232,"passed_time":0.2121677784,"remaining_time":0.698423545},
{"learn":[0.945869636],"iteration":233,"passed_time":0.213134315,"remaining_time":0.6976960911},
{"learn":[0.9452215108],"iteration":234,"passed_time":0.2141040786,"remaining_time":0.6969771069},
{"learn":[0.9443643054],"iteration":235,"passed_time":0.2150272251,"remaining_time":0.6961050847},
{"learn":[0.9437178483],"iteration":236,"passed_time":0.2159867141,"remaining_time":0.6953496322},
{"learn":[0.9429536504],"iteration":237,"passed_time":0.2168885063,"remaining_time":0.6944077388},
{"learn":[0.9420781718],"iteration":238,"passed_time":0.2178069697,"remaining_time":0.6935192635},
{"learn":[0.9413567186],"iteration":239,"passed_time":0.2187326102,"remaining_time":0.6926532656},
{"learn":[0.9406962291],"iteration":240,"passed_time":0.2196272849,"remaining_time":0.6916892499},
{"learn":[0.9399841867],"iteration":241,"passed_time":0.2205808761,"remaining_time":0.6909103474},
{"learn":[0.9393826177],"iteration":242,"passed_time":0.2215088871,"remaining_time":0.690050319},
{"learn":[0.9387458359],"iteration":243,"passed_time":0.2224419373,"remaining_time":0.6892053466},
{"learn":[0.9381376328],"iteration":244,"passed_time":0.2233491746,"remaining_time":0.6882801094},
{"learn":[0.9374528785],"iteration":245,"passed_time":0.224252881,"remaining_time":0.6873441962},
{"learn":[0.9367250207],"iteration":246,"passed_time":0.2251732407,"remaining_time":0.6864593126},
{"learn":[0.9361567001],"iteration":247,"passed_time":0.2261128078,"remaining_time":0.685632385},
{"learn":[0.9355009972],"iteration":248,"passed_time":0.2269942389,"remaining_time":0.6846292106},
{"learn":[0.9349543854],"iteration":249,"passed_time":0.2279153821,"remaining_time":0.6837461464},
{"learn":[0.933944674],"iteration":250,"passed_time":0.2284902693,"remaining_time":0.6818295286},
{"learn":[0.9331018545],"iteration":251,"passed_time":0.2292083452,"remaining_time":0.6803485802},
{"learn":[0.9325415131],"iteration":252,"passed_time":0.2301690436,"remaining_time":0.679590022},
{"learn":[0.931980131],"iteration":253,"passed_time":0.2310582948,"remaining_time":0.6786200311},
{"learn":[0.9312544538],"iteration":254,"passed_time":0.2319573627,"remaining_time":0.6776793536},
{"learn":[0.9305706181],"iteration":255,"passed_time":0.2328140246,"remaining_time":0.6766157589},
{"learn":[0.9299341128],"iteration":256,"passed_time":0.2337625439,"remaining_time":0.675819339},
{"learn":[0.9294301478],"iteration":257,"passed_time":0.2347090279,"remaining_time":0.6750158865},
{"learn":[0.9288308094],"iteration":258,"passed_time":0.2356460387,"remaining_time":0.6741842265},
{"learn":[0.9281957204],"iteration":259,"passed_time":0.2365497272,"remaining_time":0.673256916},
{"learn":[0.9274308725],"iteration":260,"passed_time":0.2374365588,"remaining_time":0.6722820573},
{"learn":[0.9268162046],"iteration":261,"passed_time":0.23838741,"remaining_time":0.6714882008},
{"learn":[0.9262884388],"iteration":262,"passed_time":0.239370713,"remaining_time":0.6707840893},
{"learn":[0.9257939274],"iteration":263,"passed_time":0.240320476,"remaining_time":0.6699843572},
{"learn":[0.9251673134],"iteration":264,"passed_time":0.2412601658,"remaining_time":0.6691555541},
{"learn":[0.9246248236],"iteration":265,"passed_time":0.2422065234,"remaining_time":0.6683443165},
{"learn":[0.9240979681],"iteration":266,"passed_time":0.2431572037,"remaining_time":0.6675439337},
{"learn":[0.9234339769],"iteration":267,"passed_time":0.2440825869,"remaining_time":0.6666733344},
{"learn":[0.9228455687],"iteration":268,"passed_time":0.2449983802,"remaining_time":0.6657762674},
{"learn":[0.9221715656],"iteration":269,"passed_time":0.245925106,"remaining_time":0.6649086198},
{"learn":[0.921582311],"iteration":270,"passed_time":0.2468189667,"remaining_time":0.663952128},
{"learn":[0.9211602106],"iteration":271,"passed_time":0.2477259505,"remaining_time":0.6630312204},
{"learn":[0.9206534761],"iteration":272,"passed_time":0.248668668,"remaining_time":0.6622055736},
{"learn":[0.9202896936],"iteration":273,"passed_time":0.249598767,"remaining_time":0.6613456382},
{"learn":[0.9198243922],"iteration":274,"passed_time":0.2505300703,"remaining_time":0.6604883673},
{"learn":[0.9192256331],"iteration":275,"passed_time":0.251444953,"remaining_time":0.6595874855},
{"learn":[0.9186487265],"iteration":276,"passed_time":0.252374699,"remaining_time":0.6587252974},
{"learn":[0.9181327268],"iteration":277,"passed_time":0.2533058209,"remaining_time":0.6578661969},
{"learn":[0.9177817592],"iteration":278,"passed_time":0.2542887783,"remaining_time":0.6571405345},
{"learn":[0.917227818],"iteration":279,"passed_time":0.255231628,"remaining_time":0.6563099007},
{"learn":[0.9167126917],"iteration":280,"passed_time":0.2561138211,"remaining_time":0.6553232647},
{"learn":[0.9162138312],"iteration":281,"passed_time":0.2570402822,"remaining_time":0.6544500803},
{"learn":[0.9156930155],"iteration":282,"passed_time":0.2579343421,"remaining_time":0.6534944287},
{"learn":[0.915168268],"iteration":283,"passed_time":0.2588423109,"remaining_time":0.6525742768},
{"learn":[0.9146647184],"iteration":284,"passed_time":0.2597916152,"remaining_time":0.6517579119},
{"learn":[0.9141045446],"iteration":285,"passed_time":0.2607214965,"remaining_time":0.6508921276},
{"learn":[0.9135035331],"iteration":286,"passed_time":0.2616059939,"remaining_time":0.6499131487},
{"learn":[0.9129889528],"iteration":287,"passed_time":0.2624998398,"remaining_time":0.6489579372},
{"learn":[0.9124395595],"iteration":288,"passed_time":0.2634098587,"remaining_time":0.6480429396},
{"learn":[0.9120078799],"iteration":289,"passed_time":0.2643406298,"remaining_time":0.6471787832},
{"learn":[0.9114630742],"iteration":290,"passed_time":0.2653133556,"remaining_time":0.6464163887},
{"learn":[0.9110239513],"iteration":291,"passed_time":0.2662638351,"remaining_time":0.645598614},
{"learn":[0.9105850161],"iteration":292,"passed_time":0.267210815,"remaining_time":0.6447714887},
{"learn":[0.910209589],"iteration":293,"passed_time":0.2681424654,"remaining_time":0.6439067368},
{"learn":[0.9097170349],"iteration":294,"passed_time":0.269049479,"remaining_time":0.6429826532},
{"learn":[0.909261722],"iteration":295,"passed_time":0.2699803564,"remaining_time":0.6421154422},
{"learn":[0.9086609294],"iteration":296,"passed_time":0.2708644048,"remaining_time":0.6411369583},
{"learn":[0.9083105852],"iteration":297,"passed_time":0.2717861962,"remaining_time":0.6402480193},
{"learn":[0.9079815461],"iteration":298,"passed_time":0.2727001854,"remaining_time":0.6393405684},
{"learn":[0.9076756394],"iteration":299,"passed_time":0.2736425275,"remaining_time":0.6384992308},
{"learn":[0.9069944231],"iteration":300,"passed_time":0.2742715923,"remaining_time":0.636929711},
{"learn":[0.9065325329],"iteration":301,"passed_time":0.2751716243,"remaining_time":0.6359926946},
{"learn":[0.9060581121],"iteration":302,"passed_time":0.2760664298,"remaining_time":0.6350438996},
{"learn":[0.9057210822],"iteration":303,"passed_time":0.2769863271,"remaining_time":0.6341529068},
{"learn":[0.9052058771],"iteration":304,"passed_time":0.277892135,"remaining_time":0.633229619},
{"learn":[0.9047962107],"iteration":305,"passed_time":0.2788280879,"remaining_time":0.6323748138},
{"learn":[0.9042368951],"iteration":306,"passed_time":0.2797229626,"remaining_time":0.6314267526},
{"learn":[0.903845159],"iteration":307,"passed_time":0.2806312094,"remaining_time":0.6305090808},
{"learn":[0.9033221413],"iteration":308,"passed_time":0.281485352,"remaining_time":0.6294704798},
{"learn":[0.9029164111],"iteration":309,"passed_time":0.2824043217,"remaining_time":0.6285773611},
{"learn":[0.9024666592],"iteration":310,"passed_time":0.2833454714,"remaining_time":0.6277332148},
{"learn":[0.9020872949],"iteration":311,"passed_time":0.2842396897,"remaining_time":0.6267849567},
{"learn":[0.9015761706],"iteration":312,"passed_time":0.2851459859,"remaining_time":0.6258635537},
{"learn":[0.9012704156],"iteration":313,"passed_time":0.2860874835,"remaining_time":0.6250191519},
{"learn":[0.9008591776],"iteration":314,"passed_time":0.2870005101,"remaining_time":0.6241122203},
{"learn":[0.9005186899],"iteration":315,"passed_time":0.2879517002,"remaining_time":0.6232878575},
{"learn":[0.9001537804],"iteration":316,"passed_time":0.2888573431,"remaining_time":0.6223645593},
{"learn":[0.8997152699],"iteration":317,"passed_time":0.2897581853,"remaining_time":0.6214310767},
{"learn":[0.8992918597],"iteration":318,"passed_time":0.2906919149,"remaining_time":0.6205680065},
{"learn":[0.8988505284],"iteration":319,"passed_time":0.2915901257,"remaining_time":0.6196290172},
{"learn":[0.8985218426],"iteration":320,"passed_time":0.2925062424,"remaining_time":0.6187281575},
{"learn":[0.8980976589],"iteration":321,"passed_time":0.2934142855,"remaining_time":0.6178102036},
{"learn":[0.8976653066],"iteration":322,"passed_time":0.2942986781,"remaining_time":0.6168427402},
{"learn":[0.8972497725],"iteration":323,"passed_time":0.2951862092,"remaining_time":0.6158823376},
{"learn":[0.8969538318],"iteration":324,"passed_time":0.2961228066,"remaining_time":0.6150242907},
{"learn":[0.896644104],"iteration":325,"passed_time":0.2970842833,"remaining_time":0.6142171992},
{"learn":[0.8962963702],"iteration":326,"passed_time":0.2980598577,"remaining_time":0.613438178},
{"learn":[0.8959327487],"iteration":327,"passed_time":0.2989937374,"remaining_time":0.6125725352},
{"learn":[0.8954519935],"iteration":328,"passed_time":0.2999101187,"remaining_time":0.6116707892},
{"learn":[0.8950852833],"iteration":329,"passed_time":0.3008355763,"remaining_time":0.6107873822},
{"learn":[0.8947934129],"iteration":330,"passed_time":0.3018068779,"remaining_time":0.6099963785},
{"learn":[0.8944015216],"iteration":331,"passed_time":0.302787591,"remaining_time":0.6092232252},
{"learn":[0.8940771663],"iteration":332,"passed_time":0.3037408797,"remaining_time":0.6083938941},
{"learn":[0.8937332426],"iteration":333,"passed_time":0.3047397469,"remaining_time":0.6076547049},
{"learn":[0.8934263831],"iteration":334,"passed_time":0.3056851739,"remaining_time":0.6068078825},
{"learn":[0.8931218525],"iteration":335,"passed_time":0.306684899,"remaining_time":0.6060677766},
{"learn":[0.8927535354],"iteration":336,"passed_time":0.307627467,"remaining_time":0.6052136815},
{"learn":[0.8924542499],"iteration":337,"passed_time":0.3085619028,"remaining_time":0.6043431351},
{"learn":[0.8921237832],"iteration":338,"passed_time":0.3095105493,"remaining_time":0.6034999206},
{"learn":[0.891694189],"iteration":339,"passed_time":0.3104571351,"remaining_time":0.6026520859},
{"learn":[0.8913821382],"iteration":340,"passed_time":0.3114683733,"remaining_time":0.6019286158},
{"learn":[0.8909978121],"iteration":341,"passed_time":0.3124419472,"remaining_time":0.6011309979},
{"learn":[0.8905790226],"iteration":342,"passed_time":0.3133822748,"remaining_time":0.6002686722},
{"learn":[0.8902794427],"iteration":343,"passed_time":0.3143668081,"remaining_time":0.5994901921},
{"learn":[0.8899248628],"iteration":344,"passed_time":0.3153905174,"remaining_time":0.5987848953},
{"learn":[0.8895834184],"iteration":345,"passed_time":0.3163141716,"remaining_time":0.5978886365},
{"learn":[0.889296425],"iteration":346,"passed_time":0.3172717182,"remaining_time":0.5970559999},
{"learn":[0.8888971788],"iteration":347,"passed_time":0.3182370239,"remaining_time":0.5962371827},
{"learn":[0.8886308975],"iteration":348,"passed_time":0.3191808467,"remaining_time":0.5953774533},
{"learn":[0.888246609],"iteration":349,"passed_time":0.3201820169,"remaining_time":0.5946237456},
{"learn":[0.8878938575],"iteration":350,"passed_time":0.3211090385,"remaining_time":0.593731527},
{"learn":[0.8874198287],"iteration":351,"passed_time":0.3220393814,"remaining_time":0.5928452248},
{"learn":[0.8869748639],"iteration":352,"passed_time":0.3229730196,"remaining_time":0.5919647129},
{"learn":[0.8866647438],"iteration":353,"passed_time":0.3239433533,"remaining_time":0.591150865},
{"learn":[0.8863447262],"iteration":354,"passed_time":0.3249105218,"remaining_time":0.5903303847},
{"learn":[0.8860324331],"iteration":355,"passed_time":0.325830179,"remaining_time":0.5894231328},
{"learn":[0.8857497203],"iteration":356,"passed_time":0.3267707319,"remaining_time":0.588553447},
{"learn":[0.8853861389],"iteration":357,"passed_time":0.3277368656,"remaining_time":0.5877292395},
{"learn":[0.8850213028],"iteration":358,"passed_time":0.3286430964,"remaining_time":0.5867972836},
{"learn":[0.8845920413],"iteration":359,"passed_time":0.329578118,"remaining_time":0.5859166542},
{"learn":[0.8843652266],"iteration":360,"passed_time":0.3305253773,"remaining_time":0.5850573854},
{"learn":[0.8840289089],"iteration":361,"passed_time":0.3315114545,"remaining_time":0.5842660441},
{"learn":[0.8836605982],"iteration":362,"passed_time":0.3324934239,"remaining_time":0.5834664216},
{"learn":[0.8833733531],"iteration":363,"passed_time":0.333445654,"remaining_time":0.5826138351},
{"learn":[0.8831492086],"iteration":364,"passed_time":0.3344135131,"remaining_time":0.5817878927},
{"learn":[0.8828468096],"iteration":365,"passed_time":0.33534571,"remaining_time":0.5808993992},
{"learn":[0.8826042993],"iteration":366,"passed_time":0.3362893432,"remaining_time":0.5800303931},
{"learn":[0.8823535203],"iteration":367,"passed_time":0.3372327386,"remaining_time":0.5791605729},
{"learn":[0.8820405313],"iteration":368,"passed_time":0.3381942451,"remaining_time":0.5783213242},
{"learn":[0.8817000453],"iteration":369,"passed_time":0.3391174139,"remaining_time":0.5774161371},
{"learn":[0.8813343152],"iteration":370,"passed_time":0.3401021939,"remaining_time":0.5766153099},
{"learn":[0.8810028878],"iteration":371,"passed_time":0.3410058624,"remaining_time":0.5756765634},
{"learn":[0.8806900248],"iteration":372,"passed_time":0.3419142303,"remaining_time":0.5747459046},
{"learn":[0.8803446508],"iteration":373,"passed_time":0.3428511155,"remaining_time":0.573863097},
{"learn":[0.8800687396],"iteration":374,"passed_time":0.3437988706,"remaining_time":0.5729981177},
{"learn":[0.8797890662],"iteration":375,"passed_time":0.3448084117,"remaining_time":0.5722352364},
{"learn":[0.8794609862],"iteration":376,"passed_time":0.3458240236,"remaining_time":0.5714810789},
{"learn":[0.8792160103],"iteration":377,"passed_time":0.3467588066,"remaining_time":0.5705925336},
{"learn":[0.8790336904],"iteration":378,"passed_time":0.3477377022,"remaining_time":0.569776024},
{"learn":[0.8786853299],"iteration":379,"passed_time":0.3486822424,"remaining_time":0.568902606},
{"learn":[0.8783786674],"iteration":380,"passed_time":0.3496248707,"remaining_time":0.5680257085},
{"learn":[0.8780030074],"iteration":381,"passed_time":0.3505659245,"remaining_time":0.5671459198},
{"learn":[0.8777746674],"iteration":382,"passed_time":0.3515202308,"remaining_time":0.5662871604},
{"learn":[0.8775111778],"iteration":383,"passed_time":0.3524633765,"remaining_time":0.5654099998},
{"learn":[0.8772744134],"iteration":384,"passed_time":0.3533923159,"remaining_time":0.5645098034},
{"learn":[0.8770399523],"iteration":385,"passed_time":0.3543455362,"remaining_time":0.5636480809},
{"learn":[0.8768291235],"iteration":386,"passed_time":0.3552788659,"remaining_time":0.5627543793},
{"learn":[0.8765391455],"iteration":387,"passed_time":0.3562376487,"remaining_time":0.5619006211},
{"learn":[0.8762451282],"iteration":388,"passed_time":0.3571786289,"remaining_time":0.5610183606},
{"learn":[0.8759761148],"iteration":389,"passed_time":0.3581125719,"remaining_time":0.5601247919},
{"learn":[0.8757190523],"iteration":390,"passed_time":0.3590636907,"remaining_time":0.5592577689},
{"learn":[0.8754319654],"iteration":391,"passed_time":0.3600190548,"remaining_time":0.5583969013},
{"learn":[0.8751896108],"iteration":392,"passed_time":0.360985874,"remaining_time":0.5575532455},
{"learn":[0.8749402356],"iteration":393,"passed_time":0.3619480003,"remaining_time":0.5567017467},
{"learn":[0.8747245488],"iteration":394,"passed_time":0.3629307175,"remaining_time":0.5558812256},
{"learn":[0.8745004747],"iteration":395,"passed_time":0.3638673983,"remaining_time":0.5549896681},
{"learn":[0.8742294727],"iteration":396,"passed_time":0.3648376837,"remaining_time":0.5541489251},
{"learn":[0.8739931012],"iteration":397,"passed_time":0.365778319,"remaining_time":0.5532626835},
{"learn":[0.8737746563],"iteration":398,"passed_time":0.3666915544,"remaining_time":0.5523348978},
{"learn":[0.8734855517],"iteration":399,"passed_time":0.3676253138,"remaining_time":0.5514379706},
{"learn":[0.8732995504],"iteration":400,"passed_time":0.368574259,"remaining_time":0.550563544},
{"learn":[0.8730537186],"iteration":401,"passed_time":0.3695168137,"remaining_time":0.5496792403},
{"learn":[0.8728038722],"iteration":402,"passed_time":0.3704648878,"remaining_time":0.5488028238},
{"learn":[0.8726013294],"iteration":403,"passed_time":0.371394891,"remaining_time":0.5478993936},
{"learn":[0.8724015314],"iteration":404,"passed_time":0.3723498871,"remaining_time":0.5470325502},
{"learn":[0.8721344727],"iteration":405,"passed_time":0.3732638919,"remaining_time":0.5461052999},
{"learn":[0.8719128307],"iteration":406,"passed_time":0.3742252132,"remaining_time":0.5452470551},
{"learn":[0.871746167],"iteration":407,"passed_time":0.3752074353,"remaining_time":0.5444186317},
{"learn":[0.8714928526],"iteration":408,"passed_time":0.3761488497,"remaining_time":0.5435304894},
{"learn":[0.8712624943],"iteration":409,"passed_time":0.3771252403,"remaining_time":0.5426924189},
{"learn":[0.8710069762],"iteration":410,"passed_time":0.3780760439,"remaining_time":0.541817007},
{"learn":[0.8707231481],"iteration":411,"passed_time":0.3790395945,"remaining_time":0.5409594213},
{"learn":[0.8705318284],"iteration":412,"passed_time":0.3799873921,"remaining_time":0.5400789326},
{"learn":[0.8702817514],"iteration":413,"passed_time":0.3809319345,"remaining_time":0.5391935111},
{"learn":[0.8700473731],"iteration":414,"passed_time":0.3818546506,"remaining_time":0.5382770376},
{"learn":[0.8698015],"iteration":415,"passed_time":0.3828047666,"remaining_time":0.5373989993},
{"learn":[0.8696396017],"iteration":416,"passed_time":0.3837305424,"remaining_time":0.5364865856},
{"learn":[0.8694068649],"iteration":417,"passed_time":0.3846656524,"remaining_time":0.5355871045},
{"learn":[0.8691625129],"iteration":418,"passed_time":0.3856297278,"remaining_time":0.5347276178},
{"learn":[0.8689300887],"iteration":419,"passed_time":0.3865785334,"remaining_time":0.5338465461},
{"learn":[0.8687512623],"iteration":420,"passed_time":0.3875493726,"remaining_time":0.5329954554},
{"learn":[0.8684739042],"iteration":421,"passed_time":0.3884966825,"remaining_time":0.5321115698},
{"learn":[0.868312528],"iteration":422,"passed_time":0.3894309584,"remaining_time":0.5312096052},
{"learn":[0.8681270321],"iteration":423,"passed_time":0.3904071869,"remaining_time":0.5303644803},
{"learn":[0.8678738532],"iteration":424,"passed_time":0.3913680124,"remaining_time":0.5294978992},
{"learn":[0.867678763],"iteration":425,"passed_time":0.3922950444,"remaining_time":0.5285853416},
{"learn":[0.8674879008],"iteration":426,"passed_time":0.3932255397,"remaining_time":0.5276773636},
{"learn":[0.8671839191],"iteration":427,"passed_time":0.3942431565,"remaining_time":0.5268857139},
{"learn":[0.8669356149],"iteration":428,"passed_time":0.3951652549,"remaining_time":0.5259658754},
{"learn":[0.8667637772],"iteration":429,"passed_time":0.3961261332,"remaining_time":0.5250974324},
{"learn":[0.8665309542],"iteration":430,"passed_time":0.3970820742,"remaining_time":0.5242220422},
{"learn":[0.8663843454],"iteration":431,"passed_time":0.3980472869,"remaining_time":0.5233584699},
{"learn":[0.8661769253],"iteration":432,"passed_time":0.3989970573,"remaining_time":0.5224742067},
{"learn":[0.8659760922],"iteration":433,"passed_time":0.3999686183,"remaining_time":0.5216180598},
{"learn":[0.8657804967],"iteration":434,"passed_time":0.4009171696,"remaining_time":0.5207314962},
{"learn":[0.8655587666],"iteration":435,"passed_time":0.4019148081,"remaining_time":0.5199081463},
{"learn":[0.8653436709],"iteration":436,"passed_time":0.4028385099,"remaining_time":0.5189887439},
{"learn":[0.8651605387],"iteration":437,"passed_time":0.4038071532,"remaining_time":0.5181269866},
{"learn":[0.8650131886],"iteration":438,"passed_time":0.404771642,"remaining_time":0.5172594332},
{"learn":[0.8648503772],"iteration":439,"passed_time":0.4057144955,"remaining_time":0.5163639033},
{"learn":[0.8646802849],"iteration":440,"passed_time":0.406681195,"remaining_time":0.5154983854},
{"learn":[0.8645016428],"iteration":441,"passed_time":0.4076359168,"remaining_time":0.5146172886},
{"learn":[0.8643113499],"iteration":442,"passed_time":0.4085837084,"remaining_time":0.5137271458},
{"learn":[0.8641409226],"iteration":443,"passed_time":0.4095419693,"remaining_time":0.5128498535},
{"learn":[0.8639244401],"iteration":444,"passed_time":0.4104726735,"remaining_time":0.5119378288},
{"learn":[0.8636922412],"iteration":445,"passed_time":0.4114518665,"remaining_time":0.5110859508},
{"learn":[0.8635173831],"iteration":446,"passed_time":0.412402265,"remaining_time":0.5101978804},
{"learn":[0.863358265],"iteration":447,"passed_time":0.4133542684,"remaining_time":0.5093115093},
{"learn":[0.8631843161],"iteration":448,"passed_time":0.4143154649,"remaining_time":0.5084361273},
{"learn":[0.8629285371],"iteration":449,"passed_time":0.4152528272,"remaining_time":0.5075312333},
{"learn":[0.8627659329],"iteration":450,"passed_time":0.4161979071,"remaining_time":0.5066355898},
{"learn":[0.8625889495],"iteration":451,"passed_time":0.4171709407,"remaining_time":0.5057736183},
{"learn":[0.8624598261],"iteration":452,"passed_time":0.4181225776,"remaining_time":0.50488532},
{"learn":[0.8622353871],"iteration":453,"passed_time":0.4190334343,"remaining_time":0.5039476985},
{"learn":[0.8620197039],"iteration":454,"passed_time":0.4199834797,"remaining_time":0.503057135},
{"learn":[0.8618875624],"iteration":455,"passed_time":0.4209364287,"remaining_time":0.5021697746},
{"learn":[0.8617273279],"iteration":456,"passed_time":0.4218605616,"remaining_time":0.5012478883},
{"learn":[0.861567458],"iteration":457,"passed_time":0.4228173723,"remaining_time":0.5003646633},
{"learn":[0.8613725136],"iteration":458,"passed_time":0.423850378,"remaining_time":0.4995709248},
{"learn":[0.8611801605],"iteration":459,"passed_time":0.4248065553,"remaining_time":0.4986859562},
{"learn":[0.8609752522],"iteration":460,"passed_time":0.4257340794,"remaining_time":0.4977671774},
{"learn":[0.8608054216],"iteration":461,"passed_time":0.4266977861,"remaining_time":0.4968904955},
{"learn":[0.860589925],"iteration":462,"passed_time":0.4276045603,"remaining_time":0.4959474058},
{"learn":[0.8604516557],"iteration":463,"passed_time":0.428566958,"remaining_time":0.4950687274},
{"learn":[0.8602742283],"iteration":464,"passed_time":0.4295298783,"remaining_time":0.4941902901},
{"learn":[0.8600589494],"iteration":465,"passed_time":0.4304885161,"remaining_time":0.4933065829},
{"learn":[0.8598829142],"iteration":466,"passed_time":0.4314327203,"remaining_time":0.4924060812},
{"learn":[0.8596655426],"iteration":467,"passed_time":0.4323428455,"remaining_time":0.4914666535},
{"learn":[0.8595356444],"iteration":468,"passed_time":0.4332996584,"remaining_time":0.4905802103},
{"learn":[0.8593533817],"iteration":469,"passed_time":0.4342299961,"remaining_time":0.4896636127},
{"learn":[0.8592105369],"iteration":470,"passed_time":0.435177616,"remaining_time":0.488766367},
{"learn":[0.8590444167],"iteration":471,"passed_time":0.436123547,"remaining_time":0.4878670187},
{"learn":[0.8588472266],"iteration":472,"passed_time":0.4370347597,"remaining_time":0.4869287915},
{"learn":[0.8587354641],"iteration":473,"passed_time":0.4380077101,"remaining_time":0.4860591888},
{"learn":[0.8585448031],"iteration":474,"passed_time":0.438975555,"remaining_time":0.4851835082},
{"learn":[0.8584050711],"iteration":475,"passed_time":0.439913915,"remaining_time":0.484274982},
{"learn":[0.8582138281],"iteration":476,"passed_time":0.4408166327,"remaining_time":0.4833272514},
{"learn":[0.8580150702],"iteration":477,"passed_time":0.4417785874,"remaining_time":0.4824443988},
{"learn":[0.8577969256],"iteration":478,"passed_time":0.4426833449,"remaining_time":0.4814990035},
{"learn":[0.8576076214],"iteration":479,"passed_time":0.4436329859,"remaining_time":0.4806024014},
{"learn":[0.857428766],"iteration":480,"passed_time":0.4445811291,"remaining_time":0.4797039626},
{"learn":[0.8572663523],"iteration":481,"passed_time":0.4455182737,"remaining_time":0.4787934974},
{"learn":[0.8571144613],"iteration":482,"passed_time":0.446446084,"remaining_time":0.4778729304},
{"learn":[0.8569827768],"iteration":483,"passed_time":0.447406827,"remaining_time":0.4769874436},
{"learn":[0.8567953543],"iteration":484,"passed_time":0.4483456366,"remaining_time":0.4760783564},
{"learn":[0.8566813809],"iteration":485,"passed_time":0.4493016541,"remaining_time":0.4751873462},
{"learn":[0.8565422588],"iteration":486,"passed_time":0.4502599262,"remaining_time":0.4742984439},
{"learn":[0.8564129039],"iteration":487,"passed_time":0.4512671651,"remaining_time":0.4734606323},
{"learn":[0.8562409676],"iteration":488,"passed_time":0.4522123312,"remaining_time":0.4725572622},
{"learn":[0.8560997484],"iteration":489,"passed_time":0.4531419984,"remaining_time":0.4716375902},
{"learn":[0.855917323],"iteration":490,"passed_time":0.4540944998,"remaining_time":0.4707415487},
{"learn":[0.8557786306],"iteration":491,"passed_time":0.4550223354,"remaining_time":0.4698198097},
{"learn":[0.8556104675],"iteration":492,"passed_time":0.4559906115,"remaining_time":0.468939635},
{"learn":[0.8554538423],"iteration":493,"passed_time":0.4569687728,"remaining_time":0.4680692288},
{"learn":[0.8553377463],"iteration":494,"passed_time":0.4579337276,"remaining_time":0.467184914},
{"learn":[0.8551814595],"iteration":495,"passed_time":0.4588666276,"remaining_time":0.4662677022},
{"learn":[0.8549960024],"iteration":496,"passed_time":0.4598134439,"remaining_time":0.4653645117},
{"learn":[0.8548396471],"iteration":497,"passed_time":0.4607474954,"remaining_time":0.4644482785},
{"learn":[0.8547344986],"iteration":498,"passed_time":0.4617195128,"remaining_time":0.463570092},
{"learn":[0.8545574086],"iteration":499,"passed_time":0.4626533383,"remaining_time":0.4626533383},
{"learn":[0.8544445161],"iteration":500,"passed_time":0.4636279537,"remaining_time":0.4617771435},
{"learn":[0.8542888318],"iteration":501,"passed_time":0.4645772967,"remaining_time":0.4608754856},
{"learn":[0.8541091073],"iteration":502,"passed_time":0.4655462745,"remaining_time":0.4599930387},
{"learn":[0.8539601019],"iteration":503,"passed_time":0.466512134,"remaining_time":0.4591071795},
{"learn":[0.8537825541],"iteration":504,"passed_time":0.4674463706,"remaining_time":0.4581900068},
{"learn":[0.8536054051],"iteration":505,"passed_time":0.4683902343,"remaining_time":0.4572821655},
{"learn":[0.8534301239],"iteration":506,"passed_time":0.4693215592,"remaining_time":0.4563619895},
{"learn":[0.8533006189],"iteration":507,"passed_time":0.4702810192,"remaining_time":0.4554690185},
{"learn":[0.8531745351],"iteration":508,"passed_time":0.4712298581,"remaining_time":0.4545655409},
{"learn":[0.8530133443],"iteration":509,"passed_time":0.4721744005,"remaining_time":0.4536577574},
{"learn":[0.8528790454],"iteration":510,"passed_time":0.4731475932,"remaining_time":0.4527772467},
{"learn":[0.8526793928],"iteration":511,"passed_time":0.4740898185,"remaining_time":0.4518668583},
{"learn":[0.8525155042],"iteration":512,"passed_time":0.475061248,"remaining_time":0.4509840697},
{"learn":[0.8523080724],"iteration":513,"passed_time":0.4760375545,"remaining_time":0.4501055476},
{"learn":[0.8521796549],"iteration":514,"passed_time":0.4769620948,"remaining_time":0.4491778951},
{"learn":[0.8520188773],"iteration":515,"passed_time":0.4778982254,"remaining_time":0.4482611262},
{"learn":[0.851875027],"iteration":516,"passed_time":0.4788469001,"remaining_time":0.4473560015},
{"learn":[0.8517150046],"iteration":517,"passed_time":0.4797955057,"remaining_time":0.4464506443},
{"learn":[0.8515496071],"iteration":518,"passed_time":0.4807428327,"remaining_time":0.4455439355},
{"learn":[0.8514213496],"iteration":519,"passed_time":0.4816564457,"remaining_time":0.4446059499},
{"learn":[0.8513054026],"iteration":520,"passed_time":0.4826049442,"remaining_time":0.4437001311},
{"learn":[0.8511744925],"iteration":521,"passed_time":0.4835093442,"remaining_time":0.4427537673},
{"learn":[0.8510678387],"iteration":522,"passed_time":0.4844440498,"remaining_time":0.4418352041},
{"learn":[0.8509630883],"iteration":523,"passed_time":0.4853755092,"remaining_time":0.4409136305},
{"learn":[0.8508115266],"iteration":524,"passed_time":0.486282774,"remaining_time":0.4399701289},
{"learn":[0.8506859259],"iteration":525,"passed_time":0.4871813989,"remaining_time":0.4390189792},
{"learn":[0.8505381978],"iteration":526,"passed_time":0.4881296127,"remaining_time":0.4381125366},
{"learn":[0.8504229254],"iteration":527,"passed_time":0.4890380772,"remaining_time":0.4371704024},
{"learn":[0.8502998329],"iteration":528,"passed_time":0.4899453495,"remaining_time":0.4362273339},
{"learn":[0.8501506304],"iteration":529,"passed_time":0.4908203833,"remaining_time":0.4352558116},
{"learn":[0.8500140389],"iteration":530,"passed_time":0.4917504304,"remaining_time":0.4343332427},
{"learn":[0.8498474722],"iteration":531,"passed_time":0.4926440361,"remaining_time":0.4333785882},
{"learn":[0.8497203415],"iteration":532,"passed_time":0.4935827224,"remaining_time":0.4324636611},
{"learn":[0.849554174],"iteration":533,"passed_time":0.4944794814,"remaining_time":0.4315120568},
{"learn":[0.8494141424],"iteration":534,"passed_time":0.4954014586,"remaining_time":0.4305825762},
{"learn":[0.8492699357],"iteration":535,"passed_time":0.496342818,"remaining_time":0.4296699022},
{"learn":[0.8491164478],"iteration":536,"passed_time":0.4972433837,"remaining_time":0.4287219491},
{"learn":[0.8489977994],"iteration":537,"passed_time":0.4981308144,"remaining_time":0.4277628927},
{"learn":[0.8488347789],"iteration":538,"passed_time":0.4990497313,"remaining_time":0.4268310318},
{"learn":[0.8486891804],"iteration":539,"passed_time":0.4999516574,"remaining_time":0.4258847452},
{"learn":[0.8485494097],"iteration":540,"passed_time":0.5008436508,"remaining_time":0.4249301954},
{"learn":[0.8484103246],"iteration":541,"passed_time":0.5017686772,"remaining_time":0.42400379},
{"learn":[0.8482649044],"iteration":542,"passed_time":0.5026527673,"remaining_time":0.4230429368},
{"learn":[0.8480927633],"iteration":543,"passed_time":0.5035315499,"remaining_time":0.4220779168},
{"learn":[0.8479690734],"iteration":544,"passed_time":0.5044754128,"remaining_time":0.4211675465},
{"learn":[0.8478521698],"iteration":545,"passed_time":0.5054545679,"remaining_time":0.420286399},
{"learn":[0.8477164535],"iteration":546,"passed_time":0.5063691079,"remaining_time":0.4193513819},
{"learn":[0.8475505818],"iteration":547,"passed_time":0.507270214,"remaining_time":0.418405359},
{"learn":[0.84741558],"iteration":548,"passed_time":0.5082214652,"remaining_time":0.4175006936},
{"learn":[0.8472923514],"iteration":549,"passed_time":0.5091754972,"remaining_time":0.4165981341},
{"learn":[0.8471675055],"iteration":550,"passed_time":0.5101418733,"remaining_time":0.4157054467},
{"learn":[0.8470491028],"iteration":551,"passed_time":0.5110669102,"remaining_time":0.4147789416},
{"learn":[0.8468889605],"iteration":552,"passed_time":0.5120023696,"remaining_time":0.4138608665},
{"learn":[0.8467350504],"iteration":553,"passed_time":0.5129266898,"remaining_time":0.4129337611},
{"learn":[0.8465737189],"iteration":554,"passed_time":0.5138244197,"remaining_time":0.4119853455},
{"learn":[0.8464591732],"iteration":555,"passed_time":0.5147786576,"remaining_time":0.4110822374},
{"learn":[0.8463528299],"iteration":556,"passed_time":0.5156895351,"remaining_time":0.4101444597},
{"learn":[0.8462702373],"iteration":557,"passed_time":0.516592099,"remaining_time":0.4092001931},
{"learn":[0.8461162306],"iteration":558,"passed_time":0.517488884,"remaining_time":0.4082515167},
{"learn":[0.84599546],"iteration":559,"passed_time":0.5183997199,"remaining_time":0.4073140656},
{"learn":[0.8458959979],"iteration":560,"passed_time":0.5193077704,"remaining_time":0.4063745298},
{"learn":[0.8457670157],"iteration":561,"passed_time":0.520220788,"remaining_time":0.4054389772},
{"learn":[0.8456104601],"iteration":562,"passed_time":0.5211426092,"remaining_time":0.4045103378},
{"learn":[0.8454915365],"iteration":563,"passed_time":0.5220485976,"remaining_time":0.4035694833},
{"learn":[0.8453794261],"iteration":564,"passed_time":0.5229580992,"remaining_time":0.4026314569},
{"learn":[0.8452074222],"iteration":565,"passed_time":0.5238712484,"remaining_time":0.4016963283},
{"learn":[0.8451157828],"iteration":566,"passed_time":0.5247925863,"remaining_time":0.4007675306},
{"learn":[0.8449835163],"iteration":567,"passed_time":0.5257038794,"remaining_time":0.3998311195},
{"learn":[0.8448639802],"iteration":568,"passed_time":0.5266481289,"remaining_time":0.3989197602},
{"learn":[0.8447063464],"iteration":569,"passed_time":0.52754136,"remaining_time":0.3979697979},
{"learn":[0.8445802179],"iteration":570,"passed_time":0.5284013945,"remaining_time":0.3969950932},
{"learn":[0.8444695561],"iteration":571,"passed_time":0.529316793,"remaining_time":0.3960622158},
{"learn":[0.8442822206],"iteration":572,"passed_time":0.5302193643,"remaining_time":0.3951198404},
{"learn":[0.844188596],"iteration":573,"passed_time":0.5311396036,"remaining_time":0.3941907162},
{"learn":[0.8440441795],"iteration":574,"passed_time":0.5320335408,"remaining_time":0.3932421824},
{"learn":[0.8438857521],"iteration":575,"passed_time":0.5329313346,"remaining_time":0.3922966769},
{"learn":[0.8437718201],"iteration":576,"passed_time":0.5338358661,"remaining_time":0.3913562762},
{"learn":[0.843634189],"iteration":577,"passed_time":0.5347507652,"remaining_time":0.390423569},
{"learn":[0.8435187073],"iteration":578,"passed_time":0.5356455744,"remaining_time":0.3894763157},
{"learn":[0.8434053428],"iteration":579,"passed_time":0.5366098067,"remaining_time":0.3885795152},
{"learn":[0.8432776868],"iteration":580,"passed_time":0.53755463,"remaining_time":0.3876684854},
{"learn":[0.8431454857],"iteration":581,"passed_time":0.5384801003,"remaining_time":0.3867434397},
{"learn":[0.8430209348],"iteration":582,"passed_time":0.5394191188,"remaining_time":0.3858280833},
{"learn":[0.8429201388],"iteration":583,"passed_time":0.5403513372,"remaining_time":0.3849078018},
{"learn":[0.842833267],"iteration":584,"passed_time":0.5413174688,"remaining_time":0.3840115377},
{"learn":[0.842750511],"iteration":585,"passed_time":0.5422465606,"remaining_time":0.383088867},
{"learn":[0.8426259408],"iteration":586,"passed_time":0.5432368912,"remaining_time":0.3822092608},
{"learn":[0.8425142359],"iteration":587,"passed_time":0.5442073067,"remaining_time":0.3813153237},
{"learn":[0.8424029424],"iteration":588,"passed_time":0.5451310234,"remaining_time":0.3803885409},
{"learn":[0.8422457565],"iteration":589,"passed_time":0.5460504212,"remaining_time":0.3794587672},
{"learn":[0.8421515895],"iteration":590,"passed_time":0.5469878779,"remaining_time":0.3785415264},
{"learn":[0.8420178871],"iteration":591,"passed_time":0.5479293994,"remaining_time":0.3776270185},
{"learn":[0.8419012358],"iteration":592,"passed_time":0.5488516576,"remaining_time":0.3766991984},
{"learn":[0.8417943207],"iteration":593,"passed_time":0.5498332107,"remaining_time":0.3758119251},
{"learn":[0.8416708664],"iteration":594,"passed_time":0.550761719,"remaining_time":0.3748882289},
{"learn":[0.8415314456],"iteration":595,"passed_time":0.5516925793,"remaining_time":0.3739661108},
{"learn":[0.8414403105],"iteration":596,"passed_time":0.5526521708,"remaining_time":0.3730633582},
{"learn":[0.8413009013],"iteration":597,"passed_time":0.5535942869,"remaining_time":0.3721486678},
{"learn":[0.841206069],"iteration":598,"passed_time":0.5545112651,"remaining_time":0.3712170573},
{"learn":[0.8410633169],"iteration":599,"passed_time":0.5554313854,"remaining_time":0.3702875903},
{"learn":[0.8409610404],"iteration":600,"passed_time":0.5563607694,"remaining_time":0.3693643045},
{"learn":[0.840864608],"iteration":601,"passed_time":0.5573233574,"remaining_time":0.3684629506},
{"learn":[0.8407537376],"iteration":602,"passed_time":0.5582720916,"remaining_time":0.3675522725},
{"learn":[0.8406306343],"iteration":603,"passed_time":0.5592205232,"remaining_time":0.3666412702},
{"learn":[0.8405390522],"iteration":604,"passed_time":0.5601698535,"remaining_time":0.3657307308},
{"learn":[0.8404379541],"iteration":605,"passed_time":0.5610978593,"remaining_time":0.3648061989},
{"learn":[0.8403502257],"iteration":606,"passed_time":0.5620534219,"remaining_time":0.3638994972},
{"learn":[0.8402469503],"iteration":607,"passed_time":0.5629884293,"remaining_time":0.3629793821},
{"learn":[0.8401429602],"iteration":608,"passed_time":0.5639181262,"remaining_time":0.3620558085},
{"learn":[0.8400326934],"iteration":609,"passed_time":0.5648485435,"remaining_time":0.3611326753},
{"learn":[0.8399489161],"iteration":610,"passed_time":0.5658043395,"remaining_time":0.360225676},
{"learn":[0.8398348537],"iteration":611,"passed_time":0.5667481972,"remaining_time":0.3593109486},
{"learn":[0.8397160265],"iteration":612,"passed_time":0.5677028656,"remaining_time":0.358402951},
{"learn":[0.8396018367],"iteration":613,"passed_time":0.5686656952,"remaining_time":0.3574999321},
{"learn":[0.8394872222],"iteration":614,"passed_time":0.5696051642,"remaining_time":0.3565820946},
{"learn":[0.8393774408],"iteration":615,"passed_time":0.570507989,"remaining_time":0.3556413438},
{"learn":[0.8392665418],"iteration":616,"passed_time":0.5714499363,"remaining_time":0.354725001},
{"learn":[0.8391515173],"iteration":617,"passed_time":0.5723384553,"remaining_time":0.35377555},
{"learn":[0.8390295261],"iteration":618,"passed_time":0.573286574,"remaining_time":0.3528629801},
{"learn":[0.838910119],"iteration":619,"passed_time":0.5742401503,"remaining_time":0.3519536405},
{"learn":[0.8387899244],"iteration":620,"passed_time":0.5751673065,"remaining_time":0.351028034},
{"learn":[0.8386894871],"iteration":621,"passed_time":0.5761035345,"remaining_time":0.3501079357},
{"learn":[0.8385799007],"iteration":622,"passed_time":0.5770732081,"remaining_time":0.3492080248},
{"learn":[0.8384860915],"iteration":623,"passed_time":0.5780039658,"remaining_time":0.3482844409},
{"learn":[0.8383847348],"iteration":624,"passed_time":0.5789428542,"remaining_time":0.3473657125},
{"learn":[0.8382970902],"iteration":625,"passed_time":0.5798715476,"remaining_time":0.3464408288},
{"learn":[0.8381634311],"iteration":626,"passed_time":0.5807716391,"remaining_time":0.3454989177},
{"learn":[0.8380667328],"iteration":627,"passed_time":0.581731392,"remaining_time":0.3445924806},
{"learn":[0.8379750635],"iteration":628,"passed_time":0.5826950236,"remaining_time":0.3436881618},
{"learn":[0.837839426],"iteration":629,"passed_time":0.5836292587,"remaining_time":0.34276639},
{"learn":[0.8377096021],"iteration":630,"passed_time":0.5845788455,"remaining_time":0.3418535562},
{"learn":[0.8376418708],"iteration":631,"passed_time":0.5855404248,"remaining_time":0.3409475891},
{"learn":[0.8375678586],"iteration":632,"passed_time":0.5864960758,"remaining_time":0.3400380092},
{"learn":[0.8374426035],"iteration":633,"passed_time":0.5874314943,"remaining_time":0.339116604},
{"learn":[0.8373179251],"iteration":634,"passed_time":0.5883812959,"remaining_time":0.3382034221},
{"learn":[0.8372312014],"iteration":635,"passed_time":0.589374846,"remaining_time":0.3373151634},
{"learn":[0.8370930997],"iteration":636,"passed_time":0.5902680042,"remaining_time":0.336369365},
{"learn":[0.8369906018],"iteration":637,"passed_time":0.5912286038,"remaining_time":0.3354619977},
{"learn":[0.8368899404],"iteration":638,"passed_time":0.5921728243,"remaining_time":0.3345452106},
{"learn":[0.8367896794],"iteration":639,"passed_time":0.5930985889,"remaining_time":0.3336179562},
{"learn":[0.8366832455],"iteration":640,"passed_time":0.5940460958,"remaining_time":0.3327028836},
{"learn":[0.8366179135],"iteration":641,"passed_time":0.5950612335,"remaining_time":0.331825423},
{"learn":[0.8364715261],"iteration":642,"passed_time":0.5959875675,"remaining_time":0.3308982295},
{"learn":[0.8363711611],"iteration":643,"passed_time":0.596927267,"remaining_time":0.3299784271},
{"learn":[0.8362533601],"iteration":644,"passed_time":0.5978519597,"remaining_time":0.3290503034},
{"learn":[0.8361728292],"iteration":645,"passed_time":0.5988037928,"remaining_time":0.328137063},
{"learn":[0.8360843502],"iteration":646,"passed_time":0.5997530459,"remaining_time":0.3272222955},
{"learn":[0.8359437633],"iteration":647,"passed_time":0.6009267954,"remaining_time":0.3264293704},
{"learn":[0.8358661278],"iteration":648,"passed_time":0.6019334538,"remaining_time":0.3255449034},
{"learn":[0.8357808404],"iteration":649,"passed_time":0.6028741114,"remaining_time":0.3246245215},
{"learn":[0.8356714792],"iteration":650,"passed_time":0.6038173723,"remaining_time":0.323705473},
{"learn":[0.8355619811],"iteration":651,"passed_time":0.6047629375,"remaining_time":0.3227875802},
{"learn":[0.8354779006],"iteration":652,"passed_time":0.6056995469,"remaining_time":0.3218648434},
{"learn":[0.8353919271],"iteration":653,"passed_time":0.6067359229,"remaining_time":0.3209948461},
{"learn":[0.8352737571],"iteration":654,"passed_time":0.6076697952,"remaining_time":0.3200703502},
{"learn":[0.835190655],"iteration":655,"passed_time":0.6086260417,"remaining_time":0.3191575585},
{"learn":[0.8350807062],"iteration":656,"passed_time":0.6095969433,"remaining_time":0.3182522855},
{"learn":[0.8349947011],"iteration":657,"passed_time":0.6106317353,"remaining_time":0.3173800205},
{"learn":[0.8348973835],"iteration":658,"passed_time":0.6115683781,"remaining_time":0.3164564749},
{"learn":[0.834788839],"iteration":659,"passed_time":0.6125498539,"remaining_time":0.3155559853},
{"learn":[0.8347127595],"iteration":660,"passed_time":0.6135041647,"remaining_time":0.314641319},
{"learn":[0.8346106369],"iteration":661,"passed_time":0.6145536036,"remaining_time":0.3137751028},
{"learn":[0.834509294],"iteration":662,"passed_time":0.6155334946,"remaining_time":0.3128729829},
{"learn":[0.8344074304],"iteration":663,"passed_time":0.6165231049,"remaining_time":0.3119755471},
{"learn":[0.8343306534],"iteration":664,"passed_time":0.6175151103,"remaining_time":0.3110790405},
{"learn":[0.8342166564],"iteration":665,"passed_time":0.6185025121,"remaining_time":0.3101799385},
{"learn":[0.8341524172],"iteration":666,"passed_time":0.6194704054,"remaining_time":0.3092708321},
{"learn":[0.8340494811],"iteration":667,"passed_time":0.6204378296,"remaining_time":0.3083613165},
{"learn":[0.8339250348],"iteration":668,"passed_time":0.6214952373,"remaining_time":0.3074961488},
{"learn":[0.8338291911],"iteration":669,"passed_time":0.6224898251,"remaining_time":0.3065994661},
{"learn":[0.8337529425],"iteration":670,"passed_time":0.623467466,"remaining_time":0.3056941823},
{"learn":[0.8336367539],"iteration":671,"passed_time":0.6244904208,"remaining_time":0.3048108006},
{"learn":[0.8335109467],"iteration":672,"passed_time":0.6253358819,"remaining_time":0.3038407628},
{"learn":[0.8334340221],"iteration":673,"passed_time":0.6262843744,"remaining_time":0.3029209289},
{"learn":[0.8333677234],"iteration":674,"passed_time":0.6272203029,"remaining_time":0.3019949606},
{"learn":[0.8333036283],"iteration":675,"passed_time":0.6281797078,"remaining_time":0.301080215},
{"learn":[0.8331933308],"iteration":676,"passed_time":0.6291388192,"remaining_time":0.3001651973},
{"learn":[0.8331188363],"iteration":677,"passed_time":0.6300621619,"remaining_time":0.2992330622},
{"learn":[0.8330136902],"iteration":678,"passed_time":0.6310181824,"remaining_time":0.2983164014},
{"learn":[0.832901327],"iteration":679,"passed_time":0.6320768984,"remaining_time":0.2974479522},
{"learn":[0.8328267827],"iteration":680,"passed_time":0.6330379625,"remaining_time":0.2965332012},
{"learn":[0.8327516022],"iteration":681,"passed_time":0.6339739579,"remaining_time":0.2956066255},
{"learn":[0.8326778414],"iteration":682,"passed_time":0.634946735,"remaining_time":0.2946970937},
{"learn":[0.8326030855],"iteration":683,"passed_time":0.6359250664,"remaining_time":0.293789943},
{"learn":[0.8325338282],"iteration":684,"passed_time":0.6368815351,"remaining_time":0.2928725308},
{"learn":[0.8324490887],"iteration":685,"passed_time":0.6378091172,"remaining_time":0.2919417825},
{"learn":[0.8323563277],"iteration":686,"passed_time":0.6387679833,"remaining_time":0.2910252966},
{"learn":[0.8322739633],"iteration":687,"passed_time":0.6397072679,"remaining_time":0.2900998076},
{"learn":[0.8321990083],"iteration":688,"passed_time":0.640664292,"remaining_time":0.2891822856},
{"learn":[0.8321116107],"iteration":689,"passed_time":0.64162425,"remaining_time":0.2882659674},
{"learn":[0.8320445927],"iteration":690,"passed_time":0.6425626218,"remaining_time":0.28733987},
{"learn":[0.8319739874],"iteration":691,"passed_time":0.643504894,"remaining_time":0.2864154731},
{"learn":[0.8318813297],"iteration":692,"passed_time":0.6444150155,"remaining_time":0.2854767818},
{"learn":[0.8318050669],"iteration":693,"passed_time":0.6453492305,"remaining_time":0.2845487962},
{"learn":[0.8317395244],"iteration":694,"passed_time":0.6463248435,"remaining_time":0.2836389601},
{"learn":[0.8316505845],"iteration":695,"passed_time":0.6473026078,"remaining_time":0.2827298747},
{"learn":[0.8315529119],"iteration":696,"passed_time":0.6483130342,"remaining_time":0.281834791},
{"learn":[0.8314749427],"iteration":697,"passed_time":0.6493023048,"remaining_time":0.2809302236},
{"learn":[0.8314184614],"iteration":698,"passed_time":0.650323874,"remaining_time":0.280039322},
{"learn":[0.8313474631],"iteration":699,"passed_time":0.6512987905,"remaining_time":0.2791280531},
{"learn":[0.8312658505],"iteration":700,"passed_time":0.6522693122,"remaining_time":0.278214728},
{"learn":[0.8311746456],"iteration":701,"passed_time":0.6532810135,"remaining_time":0.2773187208},
{"learn":[0.831071763],"iteration":702,"passed_time":0.6542756027,"remaining_time":0.2764151551},
{"learn":[0.8309513995],"iteration":703,"passed_time":0.6552649209,"remaining_time":0.2755091145},
{"learn":[0.8308659898],"iteration":704,"passed_time":0.6562678454,"remaining_time":0.274608531},
{"learn":[0.8307867887],"iteration":705,"passed_time":0.6572922594,"remaining_time":0.2737166066},
{"learn":[0.830694443],"iteration":706,"passed_time":0.6582889583,"remaining_time":0.2728128215},
{"learn":[0.830608143],"iteration":707,"passed_time":0.6592772737,"remaining_time":0.2719053163},
{"learn":[0.8305343658],"iteration":708,"passed_time":0.6602951774,"remaining_time":0.2710097273},
{"learn":[0.83044129],"iteration":709,"passed_time":0.6613049987,"remaining_time":0.2701104924},
{"learn":[0.830342752],"iteration":710,"passed_time":0.6622355869,"remaining_time":0.2691787407},
{"learn":[0.8302333762],"iteration":711,"passed_time":0.6632600671,"remaining_time":0.268284971},
{"learn":[0.8301622114],"iteration":712,"passed_time":0.6642543917,"remaining_time":0.2673786963},
{"learn":[0.8300648895],"iteration":713,"passed_time":0.6652286384,"remaining_time":0.2664641325},
{"learn":[0.8299850108],"iteration":714,"passed_time":0.6662463073,"remaining_time":0.2655667099},
{"learn":[0.8299108582],"iteration":715,"passed_time":0.6672277824,"remaining_time":0.2646545952},
{"learn":[0.8298065898],"iteration":716,"passed_time":0.6681739386,"remaining_time":0.2637283467},
{"learn":[0.8297083627],"iteration":717,"passed_time":0.6691713407,"remaining_time":0.26282217},
{"learn":[0.829629302],"iteration":718,"passed_time":0.6701620868,"remaining_time":0.2619131382},
{"learn":[0.8295569234],"iteration":719,"passed_time":0.6711505881,"remaining_time":0.2610030065},
{"learn":[0.8294614355],"iteration":720,"passed_time":0.6721047762,"remaining_time":0.2600793794},
{"learn":[0.8293667362],"iteration":721,"passed_time":0.6730886813,"remaining_time":0.25916711},
{"learn":[0.8292963762],"iteration":722,"passed_time":0.6740732688,"remaining_time":0.2582549038},
{"learn":[0.8292020217],"iteration":723,"passed_time":0.675064733,"remaining_time":0.2573451192},
{"learn":[0.82912768],"iteration":724,"passed_time":0.6760625187,"remaining_time":0.2564375071},
{"learn":[0.8290466643],"iteration":725,"passed_time":0.6770250955,"remaining_time":0.2555163584},
{"learn":[0.8289725609],"iteration":726,"passed_time":0.6779987312,"remaining_time":0.2545992484},
{"learn":[0.8288958919],"iteration":727,"passed_time":0.6789807459,"remaining_time":0.2536851139},
{"learn":[0.828842635],"iteration":728,"passed_time":0.6799901272,"remaining_time":0.2527809663},
{"learn":[0.82876049],"iteration":729,"passed_time":0.6809412653,"remaining_time":0.2518549885},
{"learn":[0.8286873398],"iteration":730,"passed_time":0.6819626658,"remaining_time":0.2509547977},
{"learn":[0.828613961],"iteration":731,"passed_time":0.6829179897,"remaining_time":0.2500300837},
{"learn":[0.8285291449],"iteration":732,"passed_time":0.6838502393,"remaining_time":0.2490968812},
{"learn":[0.8284621735],"iteration":733,"passed_time":0.6848936854,"remaining_time":0.2482039786},
{"learn":[0.8283836529],"iteration":734,"passed_time":0.6859058237,"remaining_time":0.2472993786},
{"learn":[0.8283198172],"iteration":735,"passed_time":0.6869083014,"remaining_time":0.2463910212},
{"learn":[0.8282559641],"iteration":736,"passed_time":0.6879021131,"remaining_time":0.2454793158},
{"learn":[0.8281638553],"iteration":737,"passed_time":0.6888944999,"remaining_time":0.2445668821},
{"learn":[0.828072589],"iteration":738,"passed_time":0.6898541717,"remaining_time":0.2436426777},
{"learn":[0.8279725449],"iteration":739,"passed_time":0.6908339854,"remaining_time":0.2427254543},
{"learn":[0.8279075213],"iteration":740,"passed_time":0.6918269958,"remaining_time":0.2418126746},
{"learn":[0.8278230468],"iteration":741,"passed_time":0.6928546515,"remaining_time":0.2409117252},
{"learn":[0.8277614703],"iteration":742,"passed_time":0.6938507624,"remaining_time":0.2399995235},
{"learn":[0.8277079457],"iteration":743,"passed_time":0.6948345531,"remaining_time":0.239082857},
{"learn":[0.8276389745],"iteration":744,"passed_time":0.6958228551,"remaining_time":0.2381675544},
{"learn":[0.8275504268],"iteration":745,"passed_time":0.6968068813,"remaining_time":0.2372506003},
{"learn":[0.8274850286],"iteration":746,"passed_time":0.6977955357,"remaining_time":0.2363350342},
{"learn":[0.8274093248],"iteration":747,"passed_time":0.69879599,"remaining_time":0.235423248},
{"learn":[0.827338856],"iteration":748,"passed_time":0.699788732,"remaining_time":0.2345086405},
{"learn":[0.8272766653],"iteration":749,"passed_time":0.7008560211,"remaining_time":0.2336186737},
{"learn":[0.8272169029],"iteration":750,"passed_time":0.701887236,"remaining_time":0.232716274},
{"learn":[0.8271353114],"iteration":751,"passed_time":0.7028811191,"remaining_time":0.2318012201},
{"learn":[0.8270605662],"iteration":752,"passed_time":0.7038622485,"remaining_time":0.2308817734},
{"learn":[0.8269957017],"iteration":753,"passed_time":0.7049102223,"remaining_time":0.2299839717},
{"learn":[0.8269331216],"iteration":754,"passed_time":0.7058969023,"remaining_time":0.2290658822},
{"learn":[0.826873716],"iteration":755,"passed_time":0.7068655204,"remaining_time":0.2281417817},
{"learn":[0.8267961006],"iteration":756,"passed_time":0.7078382625,"remaining_time":0.2272188874},
{"learn":[0.8267073604],"iteration":757,"passed_time":0.7088041139,"remaining_time":0.2262936617},
{"learn":[0.8266380268],"iteration":758,"passed_time":0.7098064258,"remaining_time":0.225379906},
{"learn":[0.8265551793],"iteration":759,"passed_time":0.7108009987,"remaining_time":0.2244634733},
{"learn":[0.8264984619],"iteration":760,"passed_time":0.7118335584,"remaining_time":0.2235587654},
{"learn":[0.826419808],"iteration":761,"passed_time":0.7128230839,"remaining_time":0.2226402808},
{"learn":[0.8263285715],"iteration":762,"passed_time":0.7138306982,"remaining_time":0.2217272287},
{"learn":[0.8262392531],"iteration":763,"passed_time":0.7148262301,"remaining_time":0.2208101967},
{"learn":[0.8261481627],"iteration":764,"passed_time":0.715791205,"remaining_time":0.2198835728},
{"learn":[0.8260585371],"iteration":765,"passed_time":0.7167432448,"remaining_time":0.2189528972},
{"learn":[0.826004695],"iteration":766,"passed_time":0.7176975244,"remaining_time":0.2180228464},
{"learn":[0.8259307653],"iteration":767,"passed_time":0.7186676663,"remaining_time":0.2170975242},
{"learn":[0.825841594],"iteration":768,"passed_time":0.7196652505,"remaining_time":0.2161803288},
{"learn":[0.8257685216],"iteration":769,"passed_time":0.7208974781,"remaining_time":0.2153330129},
{"learn":[0.8257028619],"iteration":770,"passed_time":0.7219057919,"remaining_time":0.2144181924},
{"learn":[0.825615079],"iteration":771,"passed_time":0.7229253964,"remaining_time":0.2135064642},
{"learn":[0.8255586511],"iteration":772,"passed_time":0.723905497,"remaining_time":0.2125828562},
{"learn":[0.8254943959],"iteration":773,"passed_time":0.7249207931,"remaining_time":0.2116693789},
{"learn":[0.8254223174],"iteration":774,"passed_time":0.7259391986,"remaining_time":0.2107565415},
{"learn":[0.8253605516],"iteration":775,"passed_time":0.7269463163,"remaining_time":0.2098401738},
{"learn":[0.8252992891],"iteration":776,"passed_time":0.7280038726,"remaining_time":0.2089380484},
{"learn":[0.8252491293],"iteration":777,"passed_time":0.7289896733,"remaining_time":0.2080150482},
{"learn":[0.8251848662],"iteration":778,"passed_time":0.7299592346,"remaining_time":0.2070872797},
{"learn":[0.8251184817],"iteration":779,"passed_time":0.7309530412,"remaining_time":0.2061662424},
{"learn":[0.8250371878],"iteration":780,"passed_time":0.731925095,"remaining_time":0.2052389191},
{"learn":[0.8249596081],"iteration":781,"passed_time":0.7328654716,"remaining_time":0.2043026507},
{"learn":[0.8249063689],"iteration":782,"passed_time":0.733850207,"remaining_time":0.2033786653},
{"learn":[0.8248228801],"iteration":783,"passed_time":0.7348139814,"remaining_time":0.20244875},
{"learn":[0.8247368805],"iteration":784,"passed_time":0.7357639622,"remaining_time":0.2015149705},
{"learn":[0.8246694325],"iteration":785,"passed_time":0.736750753,"remaining_time":0.2005911719},
{"learn":[0.824578158],"iteration":786,"passed_time":0.737704753,"remaining_time":0.1996583385},
{"learn":[0.8245181654],"iteration":787,"passed_time":0.738650713,"remaining_time":0.1987232883},
{"learn":[0.824457278],"iteration":788,"passed_time":0.739663869,"remaining_time":0.1978061804},
{"learn":[0.8243656495],"iteration":789,"passed_time":0.7406657341,"remaining_time":0.1968858281},
{"learn":[0.8243000921],"iteration":790,"passed_time":0.7416374721,"remaining_time":0.1959573093},
{"learn":[0.8242301345],"iteration":791,"passed_time":0.743500121,"remaining_time":0.1952626581},
{"learn":[0.8241573513],"iteration":792,"passed_time":0.7444758582,"remaining_time":0.1943335468},
{"learn":[0.8240883275],"iteration":793,"passed_time":0.7454939946,"remaining_time":0.1934153185},
{"learn":[0.8240006045],"iteration":794,"passed_time":0.7464285278,"remaining_time":0.1924752807},
{"learn":[0.8238987822],"iteration":795,"passed_time":0.7473811764,"remaining_time":0.1915398995},
{"learn":[0.823831146],"iteration":796,"passed_time":0.7483680096,"remaining_time":0.1906131819},
{"learn":[0.8237790787],"iteration":797,"passed_time":0.7493479466,"remaining_time":0.1896845679},
{"learn":[0.8236803962],"iteration":798,"passed_time":0.7503453302,"remaining_time":0.1887602145},
{"learn":[0.8236039697],"iteration":799,"passed_time":0.7513089492,"remaining_time":0.1878272373},
{"learn":[0.8235447164],"iteration":800,"passed_time":0.7522983974,"remaining_time":0.1869006006},
{"learn":[0.823485412],"iteration":801,"passed_time":0.7532754853,"remaining_time":0.1859707557},
{"learn":[0.8234085054],"iteration":802,"passed_time":0.7542570978,"remaining_time":0.1850419032},
{"learn":[0.8233287776],"iteration":803,"passed_time":0.7552216163,"remaining_time":0.1841087522},
{"learn":[0.8232525174],"iteration":804,"passed_time":0.7561793919,"remaining_time":0.18317389},
{"learn":[0.8231771996],"iteration":805,"passed_time":0.7571923791,"remaining_time":0.18225226},
{"learn":[0.8231149303],"iteration":806,"passed_time":0.7581694215,"remaining_time":0.1813218071},
{"learn":[0.823049081],"iteration":807,"passed_time":0.7592117823,"remaining_time":0.1804067601},
{"learn":[0.8229970379],"iteration":808,"passed_time":0.760190078,"remaining_time":0.1794762731},
{"learn":[0.8229336005],"iteration":809,"passed_time":0.7612320158,"remaining_time":0.1785605963},
{"learn":[0.8228688192],"iteration":810,"passed_time":0.7623814318,"remaining_time":0.1776696555},
{"learn":[0.8227643582],"iteration":811,"passed_time":0.7635740989,"remaining_time":0.1767880919},
{"learn":[0.8226823269],"iteration":812,"passed_time":0.7647713726,"remaining_time":0.1759068225},
{"learn":[0.8225991132],"iteration":813,"passed_time":0.7659809072,"remaining_time":0.1750275783},
{"learn":[0.8225188603],"iteration":814,"passed_time":0.7671549801,"remaining_time":0.174139474},
{"learn":[0.8224453666],"iteration":815,"passed_time":0.7682936353,"remaining_time":0.1732426825},
{"learn":[0.8223859249],"iteration":816,"passed_time":0.769538123,"remaining_time":0.1723690043},
{"learn":[0.822309776],"iteration":817,"passed_time":0.770738405,"remaining_time":0.171484584},
{"learn":[0.8222507328],"iteration":818,"passed_time":0.7718863863,"remaining_time":0.1705878339},
{"learn":[0.8221899992],"iteration":819,"passed_time":0.7730806844,"remaining_time":0.169700638},
{"learn":[0.8221149112],"iteration":820,"passed_time":0.7743089031,"remaining_time":0.1688200897},
{"learn":[0.8220390008],"iteration":821,"passed_time":0.7754655072,"remaining_time":0.1679231877},
{"learn":[0.8219809448],"iteration":822,"passed_time":0.7767690906,"remaining_time":0.1670572649},
{"learn":[0.821892795],"iteration":823,"passed_time":0.777999068,"remaining_time":0.1661745582},
{"learn":[0.8218300408],"iteration":824,"passed_time":0.779291394,"remaining_time":0.1653042351},
{"learn":[0.8217613812],"iteration":825,"passed_time":0.7806804115,"remaining_time":0.1644532586},
{"learn":[0.8217037434],"iteration":826,"passed_time":0.7818907652,"remaining_time":0.1635636063},
{"learn":[0.8216323266],"iteration":827,"passed_time":0.7830793461,"remaining_time":0.1626686564},
{"learn":[0.8215590447],"iteration":828,"passed_time":0.7842604155,"remaining_time":0.1617714488},
{"learn":[0.8214789945],"iteration":829,"passed_time":0.7854840239,"remaining_time":0.16088227},
{"learn":[0.82141016],"iteration":830,"passed_time":0.7866989009,"remaining_time":0.1599905105},
{"learn":[0.8213373926],"iteration":831,"passed_time":0.7878942753,"remaining_time":0.1590940364},
{"learn":[0.8212817214],"iteration":832,"passed_time":0.7890832711,"remaining_time":0.1581955657},
{"learn":[0.8212199527],"iteration":833,"passed_time":0.7902454697,"remaining_time":0.1572910647},
{"learn":[0.8211608861],"iteration":834,"passed_time":0.7914580616,"remaining_time":0.1563959044},
{"learn":[0.8211016838],"iteration":835,"passed_time":0.7926120775,"remaining_time":0.1554884937},
{"learn":[0.8210232039],"iteration":836,"passed_time":0.7937619187,"remaining_time":0.1545796807},
{"learn":[0.8209537483],"iteration":837,"passed_time":0.7948851843,"remaining_time":0.153665155},
{"learn":[0.8208643233],"iteration":838,"passed_time":0.7960739905,"remaining_time":0.1527627085},
{"learn":[0.8207963103],"iteration":839,"passed_time":0.7972272488,"remaining_time":0.1518528093},
{"learn":[0.8207274935],"iteration":840,"passed_time":0.7984357679,"remaining_time":0.150952779},
{"learn":[0.8206411128],"iteration":841,"passed_time":0.7995770546,"remaining_time":0.1500393998},
{"learn":[0.8205850027],"iteration":842,"passed_time":0.8007309701,"remaining_time":0.1491278319},
{"learn":[0.820520643],"iteration":843,"passed_time":0.8018871989,"remaining_time":0.1482161173},
{"learn":[0.8204463472],"iteration":844,"passed_time":0.8030697431,"remaining_time":0.1473086511},
{"learn":[0.8203636752],"iteration":845,"passed_time":0.8042177289,"remaining_time":0.1463942438},
{"learn":[0.8203048372],"iteration":846,"passed_time":0.8053805713,"remaining_time":0.1454819686},
{"learn":[0.8202370198],"iteration":847,"passed_time":0.8065683353,"remaining_time":0.1445735695},
{"learn":[0.820178819],"iteration":848,"passed_time":0.8077139483,"remaining_time":0.1436570155},
{"learn":[0.8201049159],"iteration":849,"passed_time":0.808910466,"remaining_time":0.1427489058},
{"learn":[0.8200206439],"iteration":850,"passed_time":0.8100726185,"remaining_time":0.1418341012},
{"learn":[0.8199665954],"iteration":851,"passed_time":0.8112549635,"remaining_time":0.1409222237},
{"learn":[0.8198937729],"iteration":852,"passed_time":0.8124234405,"remaining_time":0.1400073221},
{"learn":[0.8198326846],"iteration":853,"passed_time":0.8135800231,"remaining_time":0.1390897932},
{"learn":[0.8197409844],"iteration":854,"passed_time":0.8147888522,"remaining_time":0.1381805656},
{"learn":[0.8196497123],"iteration":855,"passed_time":0.8159686334,"remaining_time":0.1372657514},
{"learn":[0.8195818624],"iteration":856,"passed_time":0.8171311509,"remaining_time":0.1363474383},
{"learn":[0.819519793],"iteration":857,"passed_time":0.8182973689,"remaining_time":0.1354291683},
{"learn":[0.8194589021],"iteration":858,"passed_time":0.8194776994,"remaining_time":0.1345126375},
{"learn":[0.8193766277],"iteration":859,"passed_time":0.8206357947,"remaining_time":0.1335918736},
{"learn":[0.8193179214],"iteration":860,"passed_time":0.8217516781,"remaining_time":0.1326637436},
{"learn":[0.8192568261],"iteration":861,"passed_time":0.8229075501,"remaining_time":0.1317415799},
{"learn":[0.8191978004],"iteration":862,"passed_time":0.8240986852,"remaining_time":0.1308244726},
{"learn":[0.8191464251],"iteration":863,"passed_time":0.8252259523,"remaining_time":0.1298966777},
{"learn":[0.8190986543],"iteration":864,"passed_time":0.8264227896,"remaining_time":0.1289792793},
{"learn":[0.8190403856],"iteration":865,"passed_time":0.8276130386,"remaining_time":0.1280602161},
{"learn":[0.8189745999],"iteration":866,"passed_time":0.8287772072,"remaining_time":0.1271365266},
{"learn":[0.8188952642],"iteration":867,"passed_time":0.8299497786,"remaining_time":0.1262135608},
{"learn":[0.8188260194],"iteration":868,"passed_time":0.831127039,"remaining_time":0.1252907274},
{"learn":[0.8187691469],"iteration":869,"passed_time":0.8322703312,"remaining_time":0.1243622334},
{"learn":[0.8187003312],"iteration":870,"passed_time":0.8334439307,"remaining_time":0.1234377349},
{"learn":[0.8186097432],"iteration":871,"passed_time":0.8345867598,"remaining_time":0.1225081482},
{"learn":[0.8185522867],"iteration":872,"passed_time":0.8357503545,"remaining_time":0.121581094},
{"learn":[0.8184994131],"iteration":873,"passed_time":0.8368926269,"remaining_time":0.1206504245},
{"learn":[0.8184337543],"iteration":874,"passed_time":0.8380476901,"remaining_time":0.1197210986},
{"learn":[0.8183638804],"iteration":875,"passed_time":0.8393136874,"remaining_time":0.1188069603},
{"learn":[0.8182982309],"iteration":876,"passed_time":0.8404388418,"remaining_time":0.1178722663},
{"learn":[0.8182293639],"iteration":877,"passed_time":0.8415882615,"remaining_time":0.1169405101},
{"learn":[0.8181744438],"iteration":878,"passed_time":0.8427592466,"remaining_time":0.1160112273},
{"learn":[0.8181108155],"iteration":879,"passed_time":0.8438944207,"remaining_time":0.1150765119},
{"learn":[0.8180532428],"iteration":880,"passed_time":0.8450854971,"remaining_time":0.1141488923},
{"learn":[0.8180145986],"iteration":881,"passed_time":0.8462496233,"remaining_time":0.1132170698},
{"learn":[0.8179353781],"iteration":882,"passed_time":0.847364796,"remaining_time":0.1122782346},
{"learn":[0.8178770169],"iteration":883,"passed_time":0.8484664435,"remaining_time":0.1113372256},
{"learn":[0.8177983357],"iteration":884,"passed_time":0.8496610493,"remaining_time":0.110407933},
{"learn":[0.8177173477],"iteration":885,"passed_time":0.8508368676,"remaining_time":0.1094756241},
{"learn":[0.8176618065],"iteration":886,"passed_time":0.8519979728,"remaining_time":0.1085408917},
{"learn":[0.8175955068],"iteration":887,"passed_time":0.8531634132,"remaining_time":0.1076061963},
{"learn":[0.817516027],"iteration":888,"passed_time":0.8543411844,"remaining_time":0.1066725213},
{"learn":[0.8174484857],"iteration":889,"passed_time":0.8554784956,"remaining_time":0.1057332972},
{"learn":[0.8173707842],"iteration":890,"passed_time":0.8566077564,"remaining_time":0.1047926436},
{"learn":[0.8173034869],"iteration":891,"passed_time":0.8578434717,"remaining_time":0.1038644562},
{"learn":[0.8172575653],"iteration":892,"passed_time":0.858992742,"remaining_time":0.1029252222},
{"learn":[0.8171821033],"iteration":893,"passed_time":0.8601089346,"remaining_time":0.1019815963},
{"learn":[0.8171396939],"iteration":894,"passed_time":0.8611871978,"remaining_time":0.1010331349},
{"learn":[0.8170725162],"iteration":895,"passed_time":0.8622754478,"remaining_time":0.1000855431},
{"learn":[0.8170256251],"iteration":896,"passed_time":0.8633554489,"remaining_time":0.09913669034},
{"learn":[0.816958514],"iteration":897,"passed_time":0.864414298,"remaining_time":0.09818514297},
{"learn":[0.8168893169],"iteration":898,"passed_time":0.8655500043,"remaining_time":0.09724199158},
{"learn":[0.816838496],"iteration":899,"passed_time":0.8666268268,"remaining_time":0.09629186965},
{"learn":[0.8167925674],"iteration":900,"passed_time":0.8676906065,"remaining_time":0.09534003334},
{"learn":[0.8167352992],"iteration":901,"passed_time":0.8688070192,"remaining_time":0.09439366727},
{"learn":[0.8166807442],"iteration":902,"passed_time":0.8698402924,"remaining_time":0.09343799376},
{"learn":[0.8166326292],"iteration":903,"passed_time":0.870925303,"remaining_time":0.09248764279},
{"learn":[0.8165684125],"iteration":904,"passed_time":0.8720003586,"remaining_time":0.09153594924},
{"learn":[0.8165298415],"iteration":905,"passed_time":0.8730584412,"remaining_time":0.09058222237},
{"learn":[0.8164687071],"iteration":906,"passed_time":0.8741925612,"remaining_time":0.08963606196},
{"learn":[0.8163940173],"iteration":907,"passed_time":0.8753187534,"remaining_time":0.08868868427},
{"learn":[0.8163269695],"iteration":908,"passed_time":0.8763945152,"remaining_time":0.08773586456},
{"learn":[0.816257056],"iteration":909,"passed_time":0.877407686,"remaining_time":0.08677658433},
{"learn":[0.8161791852],"iteration":910,"passed_time":0.878492006,"remaining_time":0.0858241367},
{"learn":[0.8161209865],"iteration":911,"passed_time":0.8795954182,"remaining_time":0.0848732421},
{"learn":[0.8160612053],"iteration":912,"passed_time":0.8807085534,"remaining_time":0.08392293992},
{"learn":[0.816008961],"iteration":913,"passed_time":0.8818364516,"remaining_time":0.0829736705},
{"learn":[0.8159636727],"iteration":914,"passed_time":0.8829379734,"remaining_time":0.08202156037},
{"learn":[0.8159098222],"iteration":915,"passed_time":0.8840213776,"remaining_time":0.08106746257},
{"learn":[0.8158409277],"iteration":916,"passed_time":0.8850794535,"remaining_time":0.08011079023},
{"learn":[0.815759144],"iteration":917,"passed_time":0.8861204094,"remaining_time":0.07915236772},
{"learn":[0.8156833379],"iteration":918,"passed_time":0.8872055626,"remaining_time":0.07819766112},
{"learn":[0.8156264706],"iteration":919,"passed_time":0.8882440579,"remaining_time":0.07723861373},
{"learn":[0.8155795948],"iteration":920,"passed_time":0.8893301775,"remaining_time":0.07628347886},
{"learn":[0.8155171182],"iteration":921,"passed_time":0.8904151911,"remaining_time":0.07532796627},
{"learn":[0.8154582134],"iteration":922,"passed_time":0.8915081629,"remaining_time":0.07437283699},
{"learn":[0.8153950306],"iteration":923,"passed_time":0.8925225498,"remaining_time":0.07341094566},
{"learn":[0.8153236269],"iteration":924,"passed_time":0.8935729581,"remaining_time":0.07245186147},
{"learn":[0.8152612323],"iteration":925,"passed_time":0.8946196422,"remaining_time":0.07149228242},
{"learn":[0.8152142041],"iteration":926,"passed_time":0.8956939715,"remaining_time":0.07053469247},
{"learn":[0.8151536309],"iteration":927,"passed_time":0.8967630669,"remaining_time":0.06957644484},
{"learn":[0.8150931522],"iteration":928,"passed_time":0.8978820523,"remaining_time":0.06862177149},
{"learn":[0.8150482771],"iteration":929,"passed_time":0.8989286397,"remaining_time":0.06766129546},
{"learn":[0.8149950812],"iteration":930,"passed_time":0.8999869521,"remaining_time":0.06670150343},
{"learn":[0.8149512328],"iteration":931,"passed_time":0.9011277794,"remaining_time":0.06574752038},
{"learn":[0.8148960555],"iteration":932,"passed_time":0.9022070081,"remaining_time":0.06478871334},
{"learn":[0.8148386934],"iteration":933,"passed_time":0.9033191807,"remaining_time":0.06383197637},
{"learn":[0.8147733586],"iteration":934,"passed_time":0.904437903,"remaining_time":0.06287536224},
{"learn":[0.814721233],"iteration":935,"passed_time":0.9054517428,"remaining_time":0.06191123028},
{"learn":[0.8146583959],"iteration":936,"passed_time":0.9065760952,"remaining_time":0.06095442262},
{"learn":[0.8146003102],"iteration":937,"passed_time":0.9076147489,"remaining_time":0.05999159321},
{"learn":[0.8145233906],"iteration":938,"passed_time":0.9087516505,"remaining_time":0.05903498475},
{"learn":[0.8144684262],"iteration":939,"passed_time":0.9098568193,"remaining_time":0.05807596719},
{"learn":[0.8144165088],"iteration":940,"passed_time":0.9109227115,"remaining_time":0.05711417639},
{"learn":[0.8143417714],"iteration":941,"passed_time":0.9120632579,"remaining_time":0.0561567611},
{"learn":[0.8142961399],"iteration":942,"passed_time":0.9132882697,"remaining_time":0.05520406296},
{"learn":[0.8142377397],"iteration":943,"passed_time":0.9143276281,"remaining_time":0.05423977455},
{"learn":[0.8141841205],"iteration":944,"passed_time":0.9154496449,"remaining_time":0.05328013806},
{"learn":[0.8141272238],"iteration":945,"passed_time":0.916491289,"remaining_time":0.05231557041},
{"learn":[0.8140744825],"iteration":946,"passed_time":0.9175363258,"remaining_time":0.05135102985},
{"learn":[0.8140175395],"iteration":947,"passed_time":0.9188492375,"remaining_time":0.05040101303},
{"learn":[0.8139640405],"iteration":948,"passed_time":0.9200169258,"remaining_time":0.04944242699},
{"learn":[0.8139243543],"iteration":949,"passed_time":0.9211068328,"remaining_time":0.04847930699},
{"learn":[0.8138482951],"iteration":950,"passed_time":0.9221959585,"remaining_time":0.04751588009},
{"learn":[0.8137858957],"iteration":951,"passed_time":0.9232872764,"remaining_time":0.04655229965},
{"learn":[0.8137469823],"iteration":952,"passed_time":0.9243843604,"remaining_time":0.04558873551},
{"learn":[0.8136808254],"iteration":953,"passed_time":0.9254570848,"remaining_time":0.04462371688},
{"learn":[0.8136107177],"iteration":954,"passed_time":0.9264987349,"remaining_time":0.04365700845},
{"learn":[0.8135428348],"iteration":955,"passed_time":0.9275643626,"remaining_time":0.04269124681},
{"learn":[0.8134849647],"iteration":956,"passed_time":0.9286476731,"remaining_time":0.041726071},
{"learn":[0.8134033048],"iteration":957,"passed_time":0.9297014725,"remaining_time":0.04075935475},
{"learn":[0.8133438022],"iteration":958,"passed_time":0.9307689905,"remaining_time":0.03979304339},
{"learn":[0.8132888781],"iteration":959,"passed_time":0.9318546314,"remaining_time":0.03882727631},
{"learn":[0.8132289752],"iteration":960,"passed_time":0.9331066217,"remaining_time":0.03786801066},
{"learn":[0.813147829],"iteration":961,"passed_time":0.9344043482,"remaining_time":0.03690994307},
{"learn":[0.8130915985],"iteration":962,"passed_time":0.9354964733,"remaining_time":0.03594327052},
{"learn":[0.8130427662],"iteration":963,"passed_time":0.9365693033,"remaining_time":0.03497561714},
{"learn":[0.8129800012],"iteration":964,"passed_time":0.9376573452,"remaining_time":0.0340082975},
{"learn":[0.8129233836],"iteration":965,"passed_time":0.938750161,"remaining_time":0.03304089593},
{"learn":[0.8128779296],"iteration":966,"passed_time":0.9398247267,"remaining_time":0.03207261218},
{"learn":[0.8128457201],"iteration":967,"passed_time":0.9409215141,"remaining_time":0.03110484344},
{"learn":[0.8127864225],"iteration":968,"passed_time":0.9419599864,"remaining_time":0.0301349428},
{"learn":[0.8127166674],"iteration":969,"passed_time":0.9430312494,"remaining_time":0.02916591493},
{"learn":[0.8126473371],"iteration":970,"passed_time":0.9441135415,"remaining_time":0.02819700587},
{"learn":[0.8125674146],"iteration":971,"passed_time":0.9451779277,"remaining_time":0.02722734771},
{"learn":[0.8125048169],"iteration":972,"passed_time":0.9462763892,"remaining_time":0.0262584404},
{"learn":[0.8124604413],"iteration":973,"passed_time":0.9473450624,"remaining_time":0.02528847189},
{"learn":[0.8124135417],"iteration":974,"passed_time":0.9484719184,"remaining_time":0.02431979278},
{"learn":[0.8123466984],"iteration":975,"passed_time":0.9495526502,"remaining_time":0.02334965533},
{"learn":[0.812288997],"iteration":976,"passed_time":0.950744826,"remaining_time":0.02238191504},
{"learn":[0.8122289124],"iteration":977,"passed_time":0.9518709936,"remaining_time":0.02141223094},
{"learn":[0.8121306832],"iteration":978,"passed_time":0.9529386692,"remaining_time":0.02044097248},
{"learn":[0.8120671198],"iteration":979,"passed_time":0.9540113156,"remaining_time":0.01946961869},
{"learn":[0.8120256086],"iteration":980,"passed_time":0.955103304,"remaining_time":0.018498433},
{"learn":[0.8119615781],"iteration":981,"passed_time":0.9561560947,"remaining_time":0.01752628279},
{"learn":[0.8119030392],"iteration":982,"passed_time":0.9572464016,"remaining_time":0.01655461732},
{"learn":[0.8118311382],"iteration":983,"passed_time":0.9582980327,"remaining_time":0.01558208183},
{"learn":[0.8117676776],"iteration":984,"passed_time":0.9593824582,"remaining_time":0.01460988515},
{"learn":[0.8117136584],"iteration":985,"passed_time":0.9604953667,"remaining_time":0.01363786525},
{"learn":[0.811662157],"iteration":986,"passed_time":0.9615531118,"remaining_time":0.01266483329},
{"learn":[0.8116062554],"iteration":987,"passed_time":0.962627181,"remaining_time":0.01169182811},
{"learn":[0.8115385213],"iteration":988,"passed_time":0.9637605361,"remaining_time":0.01071927795},
{"learn":[0.8114925317],"iteration":989,"passed_time":0.9648648857,"remaining_time":0.009746109956},
{"learn":[0.8114435575],"iteration":990,"passed_time":0.9659494911,"remaining_time":0.008772497901},
{"learn":[0.8113941242],"iteration":991,"passed_time":0.9670254327,"remaining_time":0.0077985922},
{"learn":[0.8113197589],"iteration":992,"passed_time":0.9679885485,"remaining_time":0.006823685639},
{"learn":[0.8112610323],"iteration":993,"passed_time":0.9690194639,"remaining_time":0.005849212056},
{"learn":[0.8112071692],"iteration":994,"passed_time":0.9700694217,"remaining_time":0.004874720712},
{"learn":[0.8111686526],"iteration":995,"passed_time":0.9710836837,"remaining_time":0.003899934473},
{"learn":[0.8111135502],"iteration":996,"passed_time":0.9720637368,"remaining_time":0.002924966109},
{"learn":[0.8110516282],"iteration":997,"passed_time":0.9730650876,"remaining_time":0.001950030236},
{"learn":[0.8109942901],"iteration":998,"passed_time":0.9740908961,"remaining_time":0.0009750659621},
{"learn":[0.810947146],"iteration":999,"passed_time":0.9751324912,"remaining_time":0}
]}